Workbook

Sheet STUCT1
A1: No. | B1: Forecast? | C1: Ticket | D1: Node | E1: Name | F1: Parent | G1: Action | H1: STATUS | I1: STATUS Check | J1: Sector | K1: Comments | L1: SANITY | M1: Author
A2: 1 | B2: F0 | C2: No ticket | D2: G000001227 | E2: F34 HR - Fertility Reimbursement | F2: G000000589 | G2: New | H2: =IFERROR(VLOOKUP(Table2[[#This Row],[Ticket]],Okey!A:B,2,0),"") -> Ok | I2: Completed | J2: =VLOOKUP(Table2[[#This Row],[Author]],People!A:B,2,0) -> MGF | M2: Ronald Pierre Collado
A3: 2 | B3: F0 | C3: FR5620885 | D3: G000000431 | F3: G000000845 | G3: Move | H3: =IFERROR(VLOOKUP(Table2[[#This Row],[Ticket]],Okey!A:B,2,0),"") -> ok | I3: Completed | J3: =VLOOKUP(Table2[[#This Row],[Author]],People!A:B,2,0) -> MGF | M3: Nicolas Trautmann
A4: 3 | B4: F0 | C4: FR5684840 | D4: H000004347 | E4: SP Evobrutinib | F4: H000002092 | G4: New | H4: =IFERROR(VLOOKUP(Table2[[#This Row],[Ticket]],Okey!A:B,2,0),"") -> ok | I4: Completed | J4: =VLOOKUP(Table2[[#This Row],[Author]],People!A:B,2,0) -> HC | M4: Simone Oratovski
A5: 4 | B5: F0 | C5: FR5684840 | D5: H000004348 | E5: FF Evobrutinib | F5: H000002092 | G5: New | H5: =IFERROR(VLOOKUP(Table2[[#This Row],[Ticket]],Okey!A:B,2,0),"") -> ok | I5: Completed | J5: =VLOOKUP(Table2[[#This Row],[Author]],People!A:B,2,0) -> HC | M5: Simone Oratovski
A6: 5 | B6: F0 | C6: FR5684852 | D6: H000004349 | E6: SP Evobrutinib | F6: H000001807 | G6: New | H6: =IFERROR(VLOOKUP(Table2[[#This Row],[Ticket]],Okey!A:B,2,0),"") -> ok | I6: Completed | J6: =VLOOKUP(Table2[[#This Row],[Author]],People!A:B,2,0) -> HC | M6: Simone Oratovski
A7: 6 | B7: F0 | C7: FR5695335 | D7: H000004350 | E7: HC-BA-DX Centers of Excellence | F7: H000004177 | G7: New | H7: =IFERROR(VLOOKUP(Table2[[#This Row],[Ticket]],Okey!A:B,2,0),"") -> ok | I7: Completed | J7: =VLOOKUP(Table2[[#This Row],[Author]],People!A:B,2,0) -> MGF | M7: Joshua Cachola
A8: 7 | B8: F0 | C8: FR5695335 | D8: L000013599 | E8: LS-IT-B Business IT | F8: L000013388 | G8: New | H8: =IFERROR(VLOOKUP(Table2[[#This Row],[Ticket]],Okey!A:B,2,0),"") -> ok | I8: Completed | J8: =VLOOKUP(Table2[[#This Row],[Author]],People!A:B,2,0) -> MGF | M8: Joshua Cachola
A9: =1+A8 -> 8 | B9: F0 | C9: FR5695335 | D9: G000001123 | E9: EF-IT-ED Data Office for Enabling Functions | F9: G000000317 | G9: New | H9: =IFERROR(VLOOKUP(Table2[[#This Row],[Ticket]],Okey!A:B,2,0),"") -> ok | I9: Completed | J9: =VLOOKUP(Table2[[#This Row],[Author]],People!A:B,2,0) -> MGF | M9: Joshua Cachola
A10: =1+A9 -> 9 | B10: F0 | C10: FR5695335 | D10: G000001124 | E10: EF-IT-ES Data, Digital & IT - Site Mgmt & Patents | F10: G000000317 | G10: New | H10: =IFERROR(VLOOKUP(Table2[[#This Row],[Ticket]],Okey!A:B,2,0),"") -> ok | I10: Completed | J10: =VLOOKUP(Table2[[#This Row],[Author]],People!A:B,2,0) -> MGF | M10: Joshua Cachola
A11: =1+A10 -> 10 | B11: F0 | C11: FR5695335 | D11: G000001125 | E11: EF-IT-EC Key Capabilities | F11: G000000317 | G11: New | H11: =IFERROR(VLOOKUP(Table2[[#This Row],[Ticket]],Okey!A:B,2,0),"") -> ok | I11: Completed | J11: =VLOOKUP(Table2[[#This Row],[Author]],People!A:B,2,0) -> MGF | M11: Joshua Cachola
A12: =1+A11 -> 11 | B12: F0 | C12: FR5695335 | D12: G000001126 | E12: EF-IT-EM Sustainablity Management | F12: G000000317 | G12: New | H12: =IFERROR(VLOOKUP(Table2[[#This Row],[Ticket]],Okey!A:B,2,0),"") -> ok | I12: Completed | J12: =VLOOKUP(Table2[[#This Row],[Author]],People!A:B,2,0) -> MGF | M12: Joshua Cachola
A13: =1+A12 -> 12 | B13: F0 | C13: FR5695335 | D13: IT06031300 | E13: HC-BA-DX Centers of Excellence | F13: H000004350 | G13: New | H13: =IFERROR(VLOOKUP(Table2[[#This Row],[Ticket]],Okey!A:B,2,0),"") -> ok | I13: Completed | J13: =VLOOKUP(Table2[[#This Row],[Author]],People!A:B,2,0) -> MGF | M13: Joshua Cachola
A14: =1+A13 -> 13 | B14: F0 | C14: FR5695335 | D14: IT06051000 | E14: LS-IT-B Business IT | F14: L000013599 | G14: New | H14: =IFERROR(VLOOKUP(Table2[[#This Row],[Ticket]],Okey!A:B,2,0),"") -> ok | I14: Completed | J14: =VLOOKUP(Table2[[#This Row],[Author]],People!A:B,2,0) -> MGF | M14: Joshua Cachola
A15: =1+A14 -> 14 | B15: F0 | C15: FR5695335 | D15: IT06071400 | E15: EF-IT-ED Data Office for Enabling Functions | F15: G000001123 | G15: New | H15: =IFERROR(VLOOKUP(Table2[[#This Row],[Ticket]],Okey!A:B,2,0),"") -> ok | I15: Completed | J15: =VLOOKUP(Table2[[#This Row],[Author]],People!A:B,2,0) -> MGF | M15: Joshua Cachola
A16: =1+A15 -> 15 | B16: F0 | C16: FR5695335 | D16: IT06071500 | E16: EF-IT-ES Data, Digital & IT - Site Mgmt & Patents | F16: G000001124 | G16: New | H16: =IFERROR(VLOOKUP(Table2[[#This Row],[Ticket]],Okey!A:B,2,0),"") -> ok | I16: Completed | J16: =VLOOKUP(Table2[[#This Row],[Author]],People!A:B,2,0) -> MGF | M16: Joshua Cachola
A17: =1+A16 -> 16 | B17: F0 | C17: FR5695335 | D17: IT06071600 | E17: EF-IT-EC Key Capabilities | F17: G000001125 | G17: New | H17: =IFERROR(VLOOKUP(Table2[[#This Row],[Ticket]],Okey!A:B,2,0),"") -> ok | I17: Completed | J17: =VLOOKUP(Table2[[#This Row],[Author]],People!A:B,2,0) -> MGF | M17: Joshua Cachola
A18: =1+A17 -> 17 | B18: F0 | C18: FR5695335 | D18: IT06071700 | E18: EF-IT-EM Sustainablity Management | F18: G000001126 | G18: New | H18: =IFERROR(VLOOKUP(Table2[[#This Row],[Ticket]],Okey!A:B,2,0),"") -> ok | I18: Completed | J18: =VLOOKUP(Table2[[#This Row],[Author]],People!A:B,2,0) -> MGF | M18: Joshua Cachola
A19: =1+A18 -> 18 | B19: F0 | C19: FR5695357 | D19: IT06000000 | E19: EF-IT Information Technology | G19: Rename | H19: =IFERROR(VLOOKUP(Table2[[#This Row],[Ticket]],Okey!A:B,2,0),"") -> ok | I19: Completed | J19: =VLOOKUP(Table2[[#This Row],[Author]],People!A:B,2,0) -> MGF | M19: Joshua Cachola
A20: =1+A19 -> 19 | B20: F0 | C20: FR5695357 | D20: IT06010000 | E20: EF-IT-C Head Office & CISO | G20: Rename | H20: =IFERROR(VLOOKUP(Table2[[#This Row],[Ticket]],Okey!A:B,2,0),"") -> ok | I20: Completed | J20: =VLOOKUP(Table2[[#This Row],[Author]],People!A:B,2,0) -> MGF | M20: Joshua Cachola
A21: =1+A20 -> 20 | B21: F0 | C21: FR5695357 | D21: IT06020000 | E21: EF-IT-A Application Technology | G21: Rename | H21: =IFERROR(VLOOKUP(Table2[[#This Row],[Ticket]],Okey!A:B,2,0),"") -> ok | I21: Completed | J21: =VLOOKUP(Table2[[#This Row],[Author]],People!A:B,2,0) -> MGF | M21: Joshua Cachola
A22: =1+A21 -> 21 | B22: F0 | C22: FR5695357 | D22: IT06020100 | E22: EF-IT-AO Application Mgmt | G22: Rename | H22: =IFERROR(VLOOKUP(Table2[[#This Row],[Ticket]],Okey!A:B,2,0),"") -> ok | I22: Completed | J22: =VLOOKUP(Table2[[#This Row],[Author]],People!A:B,2,0) -> MGF | M22: Joshua Cachola
A23: =1+A22 -> 22 | B23: F0 | C23: FR5695357 | D23: IT06020300 | E23: EF-IT-AE ERP Next | G23: Rename | H23: =IFERROR(VLOOKUP(Table2[[#This Row],[Ticket]],Okey!A:B,2,0),"") -> ok | I23: Completed | J23: =VLOOKUP(Table2[[#This Row],[Author]],People!A:B,2,0) -> MGF | M23: Joshua Cachola
A24: =1+A23 -> 23 | B24: F0 | C24: FR5695357 | D24: IT06020600 | E24: EF-IT-AM Manufacturing, SCM & Quality | G24: Rename | H24: =IFERROR(VLOOKUP(Table2[[#This Row],[Ticket]],Okey!A:B,2,0),"") -> ok | I24: Completed | J24: =VLOOKUP(Table2[[#This Row],[Author]],People!A:B,2,0) -> MGF | M24: Joshua Cachola
A25: =1+A24 -> 24 | B25: F0 | C25: FR5695357 | D25: IT06020800 | E25: EF-IT-AR Apps R&D | G25: Rename | H25: =IFERROR(VLOOKUP(Table2[[#This Row],[Ticket]],Okey!A:B,2,0),"") -> ok | I25: Completed | J25: =VLOOKUP(Table2[[#This Row],[Author]],People!A:B,2,0) -> MGF | M25: Joshua Cachola
A26: =1+A25 -> 25 | B26: F0 | C26: FR5695357 | D26: IT06020900 | E26: EF-IT-AS Apps M&S | G26: Rename | H26: =IFERROR(VLOOKUP(Table2[[#This Row],[Ticket]],Okey!A:B,2,0),"") -> ok | I26: Completed | J26: =VLOOKUP(Table2[[#This Row],[Author]],People!A:B,2,0) -> MGF | M26: Joshua Cachola
A27: =1+A26 -> 26 | B27: F0 | C27: FR5695357 | D27: IT06021100 | E27: EF-IT-AA Corporate ERP Applications | G27: Rename | H27: =IFERROR(VLOOKUP(Table2[[#This Row],[Ticket]],Okey!A:B,2,0),"") -> ok | I27: Completed | J27: =VLOOKUP(Table2[[#This Row],[Author]],People!A:B,2,0) -> MGF | M27: Joshua Cachola
A28: =1+A27 -> 27 | B28: F0 | C28: FR5695357 | D28: IT06021200 | E28: EF-IT-AC Custom Apps & New Technology | G28: Rename | H28: =IFERROR(VLOOKUP(Table2[[#This Row],[Ticket]],Okey!A:B,2,0),"") -> ok | I28: Completed | J28: =VLOOKUP(Table2[[#This Row],[Author]],People!A:B,2,0) -> MGF | M28: Joshua Cachola
A29: =1+A28 -> 28 | B29: F0 | C29: FR5695357 | D29: IT06021300 | E29: EF-IT-AX Data Mgmt and Analytics | G29: Rename | H29: =IFERROR(VLOOKUP(Table2[[#This Row],[Ticket]],Okey!A:B,2,0),"") -> ok | I29: Completed | J29: =VLOOKUP(Table2[[#This Row],[Author]],People!A:B,2,0) -> MGF | M29: Joshua Cachola
A30: =1+A29 -> 29 | B30: F0 | C30: FR5695357 | D30: IT06021400 | E30: EF-IT-AT IT-Automation | G30: Rename | H30: =IFERROR(VLOOKUP(Table2[[#This Row],[Ticket]],Okey!A:B,2,0),"") -> ok | I30: Completed | J30: =VLOOKUP(Table2[[#This Row],[Author]],People!A:B,2,0) -> MGF | M30: Joshua Cachola
... A192: =1+A191 -> 191 | B192: F0 | C192: FR5714461 | D192: H000004349 | E192: IE - SP Evobrutinib | G192: Rename | H192: =IFERROR(VLOOKUP(Table2[[#This Row],[Ticket]],Okey!A:B,2,0),"") -> ok | I192: Completed | J192: =VLOOKUP(Table2[[#This Row],[Author]],People!A:B,2,0) -> HC | M192: Roland Earvin Combalicer
A193: =1+A192 -> 192 | B193: F0 | C193: FR5728795 | D193: G000000367 | F193: O000000009 | G193: Delete | H193: =IFERROR(VLOOKUP(Table2[[#This Row],[Ticket]],Okey!A:B,2,0),"") -> ok | I193: Completed | J193: =VLOOKUP(Table2[[#This Row],[Author]],People!A:B,2,0) -> MGF | M193: Marcus Morowski
A194: =1+A193 -> 193 | B194: F0 | C194: FR5728795 | D194: G000000368 | F194: O000000009 | G194: Delete | H194: =IFERROR(VLOOKUP(Table2[[#This Row],[Ticket]],Okey!A:B,2,0),"") -> ok | I194: Completed | J194: =VLOOKUP(Table2[[#This Row],[Author]],People!A:B,2,0) -> MGF | M194: Marcus Morowski
A195: =1+A194 -> 194 | B195: F0 | C195: FR5728795 | D195: G000000403 | F195: O000000009 | G195: Delete | H195: =IFERROR(VLOOKUP(Table2[[#This Row],[Ticket]],Okey!A:B,2,0),"") -> ok | I195: Completed | J195: =VLOOKUP(Table2[[#This Row],[Author]],People!A:B,2,0) -> MGF | M195: Marcus Morowski
A196: =1+A195 -> 195 | B196: F0 | C196: FR5728795 | D196: G000000405 | F196: O000000009 | G196: Delete | H196: =IFERROR(VLOOKUP(Table2[[#This Row],[Ticket]],Okey!A:B,2,0),"") -> ok | I196: Completed | J196: =VLOOKUP(Table2[[#This Row],[Author]],People!A:B,2,0) -> MGF | M196: Marcus Morowski
A197: =1+A196 -> 196 | B197: F0 | C197: FR5728795 | D197: G000000406 | F197: O000000009 | G197: Delete | H197: =IFERROR(VLOOKUP(Table2[[#This Row],[Ticket]],Okey!A:B,2,0),"") -> ok | I197: Completed | J197: =VLOOKUP(Table2[[#This Row],[Author]],People!A:B,2,0) -> MGF | M197: Marcus Morowski
A198: =1+A197 -> 197 | B198: F0 | C198: FR5728795 | D198: G000000407 | F198: O000000009 | G198: Delete | H198: =IFERROR(VLOOKUP(Table2[[#This Row],[Ticket]],Okey!A:B,2,0),"") -> ok | I198: Completed | J198: =VLOOKUP(Table2[[#This Row],[Author]],People!A:B,2,0) -> MGF | M198: Marcus Morowski
A199: =1+A198 -> 198 | B199: F0 | C199: FR5728795 | D199: G000000408 | F199: O000000009 | G199: Delete | H199: =IFERROR(VLOOKUP(Table2[[#This Row],[Ticket]],Okey!A:B,2,0),"") -> ok | I199: Completed | J199: =VLOOKUP(Table2[[#This Row],[Author]],People!A:B,2,0) -> MGF | M199: Marcus Morowski
A200: =1+A199 -> 199 | B200: F0 | C200: FR5728795 | D200: G000000409 | F200: O000000009 | G200: Delete | H200: =IFERROR(VLOOKUP(Table2[[#This Row],[Ticket]],Okey!A:B,2,0),"") -> ok | I200: Completed | J200: =VLOOKUP(Table2[[#This Row],[Author]],People!A:B,2,0) -> MGF | M200: Marcus Morowski
A201: =1+A200 -> 200 | B201: F0 | C201: FR5728795 | D201: L000009976 | F201: O000000009 | G201: Delete | H201: =IFERROR(VLOOKUP(Table2[[#This Row],[Ticket]],Okey!A:B,2,0),"") -> ok | I201: Completed | J201: =VLOOKUP(Table2[[#This Row],[Author]],People!A:B,2,0) -> MGF | M201: Marcus Morowski
A202: =1+A201 -> 201 | B202: F0 | C202: FR5728795 | D202: G000000687 | F202: O000000009 | G202: Delete | H202: =IFERROR(VLOOKUP(Table2[[#This Row],[Ticket]],Okey!A:B,2,0),"") -> ok | I202: Completed | J202: =VLOOKUP(Table2[[#This Row],[Author]],People!A:B,2,0) -> MGF | M202: Marcus Morowski
A203: =1+A202 -> 202 | B203: F0 | C203: FR5728795 | D203: G000000688 | F203: O000000009 | G203: Delete | H203: =IFERROR(VLOOKUP(Table2[[#This Row],[Ticket]],Okey!A:B,2,0),"") -> ok | I203: Completed | J203: =VLOOKUP(Table2[[#This Row],[Author]],People!A:B,2,0) -> MGF | M203: Marcus Morowski
A204: =1+A203 -> 203 | B204: F0 | C204: FR5728795 | D204: G000000689 | F204: O000000009 | G204: Delete | H204: =IFERROR(VLOOKUP(Table2[[#This Row],[Ticket]],Okey!A:B,2,0),"") -> ok | I204: Completed | J204: =VLOOKUP(Table2[[#This Row],[Author]],People!A:B,2,0) -> MGF | M204: Marcus Morowski
... A245: =1+A244 -> 244 | B245: F0 | C245: FR5728795 | D245: G000000946 | F245: G000000523 | G245: Move | H245: =IFERROR(VLOOKUP(Table2[[#This Row],[Ticket]],Okey!A:B,2,0),"") -> ok | I245: Completed | J245: =VLOOKUP(Table2[[#This Row],[Author]],People!A:B,2,0) -> MGF | M245: Marcus Morowski
A246: =1+A245 -> 245 | B246: F0 | C246: FR5728795 | D246: G000001127 | E246: SM-ET Material Costs | F246: G000000354 | G246: New | H246: =IFERROR(VLOOKUP(Table2[[#This Row],[Ticket]],Okey!A:B,2,0),"") -> ok | I246: Completed | J246: =VLOOKUP(Table2[[#This Row],[Author]],People!A:B,2,0) -> MGF | M246: Marcus Morowski
A247: =1+A246 -> 246 | B247: F0 | C247: FR5728795 | D247: G000000365 | E247: SM-L Lab Services | G247: Rename | H247: =IFERROR(VLOOKUP(Table2[[#This Row],[Ticket]],Okey!A:B,2,0),"") -> ok | I247: Completed | J247: =VLOOKUP(Table2[[#This Row],[Author]],People!A:B,2,0) -> MGF | M247: Marcus Morowski
A248: =1+A247 -> 247 | B248: F0 | C248: FR5728795 | D248: G000000366 | E248: SM-L Lab Services | G248: Rename | H248: =IFERROR(VLOOKUP(Table2[[#This Row],[Ticket]],Okey!A:B,2,0),"") -> ok | I248: Completed | J248: =VLOOKUP(Table2[[#This Row],[Author]],People!A:B,2,0) -> MGF | M248: Marcus Morowski
A249: =1+A248 -> 248 | B249: F0 | C249: FR5728795 | D249: G000000370 | E249: SM-LO Lab. Op. Eng | G249: Rename | H249: =IFERROR(VLOOKUP(Table2[[#This Row],[Ticket]],Okey!A:B,2,0),"") -> ok | I249: Completed | J249: =VLOOKUP(Table2[[#This Row],[Author]],People!A:B,2,0) -> MGF | M249: Marcus Morowski
A250: =1+A249 -> 249 | B250: F0 | C250: FR5728795 | D250: G000000384 | E250: SM-LT w/o Material Costs | G250: Rename | H250: =IFERROR(VLOOKUP(Table2[[#This Row],[Ticket]],Okey!A:B,2,0),"") -> ok | I250: Completed | J250: =VLOOKUP(Table2[[#This Row],[Author]],People!A:B,2,0) -> MGF | M250: Marcus Morowski
A251: =1+A250 -> 250 | B251: F0 | C251: FR5728795 | D251: G000000383 | E251: SM-LT Material Costs | G251: Rename | H251: =IFERROR(VLOOKUP(Table2[[#This Row],[Ticket]],Okey!A:B,2,0),"") -> ok | I251: Completed | J251: =VLOOKUP(Table2[[#This Row],[Author]],People!A:B,2,0) -> MGF | M251: Marcus Morowski
A252: =1+A251 -> 251 | B252: F0 | C252: FR5728795 | D252: G000000461 | E252: SM-D Strategy Realization & Enablement | G252: Rename | H252: =IFERROR(VLOOKUP(Table2[[#This Row],[Ticket]],Okey!A:B,2,0),"") -> ok | I252: Completed | J252: =VLOOKUP(Table2[[#This Row],[Author]],People!A:B,2,0) -> MGF | M252: Marcus Morowski
A253: =1+A252 -> 252 | B253: F0 | C253: FR5728795 | D253: G000000462 | E253: SM-D Strategy Realization & Enablement | G253: Rename | H253: =IFERROR(VLOOKUP(Table2[[#This Row],[Ticket]],Okey!A:B,2,0),"") -> ok | I253: Completed | J253: =VLOOKUP(Table2[[#This Row],[Author]],People!A:B,2,0) -> MGF | M253: Marcus Morowski
A254: =1+A253 -> 253 | B254: F0 | C254: FR5728795 | D254: G000000463 | E254: SM-D Business Excellence | G254: Rename | H254: =IFERROR(VLOOKUP(Table2[[#This Row],[Ticket]],Okey!A:B,2,0),"") -> ok | I254: Completed | J254: =VLOOKUP(Table2[[#This Row],[Author]],People!A:B,2,0) -> MGF | M254: Marcus Morowski
A255: =1+A254 -> 254 | B255: F0 | C255: FR5728795 | D255: G000000466 | E255: SM-DC Strategic Contracting | G255: Rename | H255: =IFERROR(VLOOKUP(Table2[[#This Row],[Ticket]],Okey!A:B,2,0),"") -> ok | I255: Completed | J255: =VLOOKUP(Table2[[#This Row],[Author]],People!A:B,2,0) -> MGF | M255: Marcus Morowski
A256: =1+A255 -> 255 | B256: F0 | C256: FR5728795 | D256: G000000470 | E256: SM-DQ Quality Management | G256: Rename | H256: =IFERROR(VLOOKUP(Table2[[#This Row],[Ticket]],Okey!A:B,2,0),"") -> ok | I256: Completed | J256: =VLOOKUP(Table2[[#This Row],[Author]],People!A:B,2,0) -> MGF | M256: Marcus Morowski
A257: =1+A256 -> 256 | B257: F0 | C257: FR5728795 | D257: G000000473 | E257: SM-DD Data & Digital Enablement | G257: Rename | H257: =IFERROR(VLOOKUP(Table2[[#This Row],[Ticket]],Okey!A:B,2,0),"") -> ok | I257: Completed | J257: =VLOOKUP(Table2[[#This Row],[Author]],People!A:B,2,0) -> MGF | M257: Marcus Morowski
A258: =1+A257 -> 257 | B258: F0 | C258: FR5728795 | D258: G000000868 | E258: SM-DP People, Change & Comms. | G258: Rename | H258: =IFERROR(VLOOKUP(Table2[[#This Row],[Ticket]],Okey!A:B,2,0),"") -> ok | I258: Completed | J258: =VLOOKUP(Table2[[#This Row],[Author]],People!A:B,2,0) -> MGF | M258: Marcus Morowski
... A300: =1+A299 -> 299 | B300: F0 | C300: FR5728795 | D300: G000000352 | E300: Site Management & Other 1 | G300: Rename | H300: =IFERROR(VLOOKUP(Table2[[#This Row],[Ticket]],Okey!A:B,2,0),"") -> ok | I300: Completed | J300: =VLOOKUP(Table2[[#This Row],[Author]],People!A:B,2,0) -> MGF | M300: Marcus Morowski
A301: =1+A300 -> 300 | B301: F0 | C301: FR5728795 | D301: G000000352 | E301: SM-ET Material Costs | F301: G000000354 | G301: Rename/Move | H301: =IFERROR(VLOOKUP(Table2[[#This Row],[Ticket]],Okey!A:B,2,0),"") -> ok | I301: Completed | J301: =VLOOKUP(Table2[[#This Row],[Author]],People!A:B,2,0) -> MGF | M301: Marcus Morowski
A302: =1+A301 -> 301 | B302: F0 | C302: FR5728795 | D302: G000000369 | E302: SM-LTS Sample Services | F302: G000000381 | G302: Rename/Move | H302: =IFERROR(VLOOKUP(Table2[[#This Row],[Ticket]],Okey!A:B,2,0),"") -> ok | I302: Completed | J302: =VLOOKUP(Table2[[#This Row],[Author]],People!A:B,2,0) -> MGF | M302: Marcus Morowski
A303: =1+A302 -> 302 | B303: F0 | C303: FR5728795 | D303: G000000864 | E303: SM-LL Ana. LS | F303: G000000365 | G303: Rename/Move | H303: =IFERROR(VLOOKUP(Table2[[#This Row],[Ticket]],Okey!A:B,2,0),"") -> ok | I303: Completed | J303: =VLOOKUP(Table2[[#This Row],[Author]],People!A:B,2,0) -> MGF | M303: Marcus Morowski
A304: =1+A303 -> 303 | B304: F0 | C304: FR5728795 | D304: G000000865 | E304: SM-LE Ana. EL | F304: G000000365 | G304: Rename/Move | H304: =IFERROR(VLOOKUP(Table2[[#This Row],[Ticket]],Okey!A:B,2,0),"") -> ok | I304: Completed | J304: =VLOOKUP(Table2[[#This Row],[Author]],People!A:B,2,0) -> MGF | M304: Marcus Morowski
A305: =1+A304 -> 304 | B305: F0 | C305: FR5728795 | D305: G000001098 | E305: SM-LH Ana. HC | F305: G000000365 | G305: Rename/Move | H305: =IFERROR(VLOOKUP(Table2[[#This Row],[Ticket]],Okey!A:B,2,0),"") -> ok | I305: Completed | J305: =VLOOKUP(Table2[[#This Row],[Author]],People!A:B,2,0) -> MGF | M305: Marcus Morowski
A306: =1+A305 -> 305 | B306: F0 | C306: FR5728795 | D306: G000000381 | E306: SM-LT Lab Tech. Serv. | F306: G000000365 | G306: Rename/Move | H306: =IFERROR(VLOOKUP(Table2[[#This Row],[Ticket]],Okey!A:B,2,0),"") -> ok | I306: Completed | J306: =VLOOKUP(Table2[[#This Row],[Author]],People!A:B,2,0) -> MGF | M306: Marcus Morowski
A307: =1+A306 -> 306 | B307: F0 | C307: FR5728795 | D307: G000000467 | E307: SM-DD Customer Service | F307: G000000473 | G307: Rename/Move | H307: =IFERROR(VLOOKUP(Table2[[#This Row],[Ticket]],Okey!A:B,2,0),"") -> ok | I307: Completed | J307: =VLOOKUP(Table2[[#This Row],[Author]],People!A:B,2,0) -> MGF | M307: Marcus Morowski
A308: =1+A307 -> 307 | B308: F0 | C308: FR5728795 | D308: G000000379 | E308: SM-DD Application Support | F308: G000000473 | G308: Rename/Move | H308: =IFERROR(VLOOKUP(Table2[[#This Row],[Ticket]],Okey!A:B,2,0),"") -> ok | I308: Completed | J308: =VLOOKUP(Table2[[#This Row],[Author]],People!A:B,2,0) -> MGF | M308: Marcus Morowski
A309: =1+A308 -> 308 | B309: F0 | C309: FR5728795 | D309: G000000377 | E309: SM-DD ERP Support | F309: G000000473 | G309: Rename/Move | H309: =IFERROR(VLOOKUP(Table2[[#This Row],[Ticket]],Okey!A:B,2,0),"") -> ok | I309: Completed | J309: =VLOOKUP(Table2[[#This Row],[Author]],People!A:B,2,0) -> MGF | M309: Marcus Morowski
A310: =1+A309 -> 309 | B310: F0 | C310: FR5728795 | D310: G000000380 | E310: SM-DD Material Costs | F310: G000000473 | G310: Rename/Move | H310: =IFERROR(VLOOKUP(Table2[[#This Row],[Ticket]],Okey!A:B,2,0),"") -> ok | I310: Completed | J310: =VLOOKUP(Table2[[#This Row],[Author]],People!A:B,2,0) -> MGF | M310: Marcus Morowski
A311: =1+A310 -> 310 | B311: F0 | C311: FR5728795 | D311: G000000469 | E311: SM-DD IT Cost Center | F311: G000000473 | G311: Rename/Move | H311: =IFERROR(VLOOKUP(Table2[[#This Row],[Ticket]],Okey!A:B,2,0),"") -> ok | I311: Completed | J311: =VLOOKUP(Table2[[#This Row],[Author]],People!A:B,2,0) -> MGF | M311: Marcus Morowski
A312: =1+A311 -> 311 | B312: F0 | C312: FR5728795 | D312: G000000501 | E312: MRE | F312: G000000850 | G312: Rename/Move | H312: =IFERROR(VLOOKUP(Table2[[#This Row],[Ticket]],Okey!A:B,2,0),"") -> ok | I312: Completed | J312: =VLOOKUP(Table2[[#This Row],[Author]],People!A:B,2,0) -> MGF | M312: Marcus Morowski
... A374: =1+A373 -> 373 | B374: F0 | C374: FR5728795 | D374: G000001025 | E374: SC Bldgs. Electronics DA | F374: G000001013 | G374: Rename/Move | H374: =IFERROR(VLOOKUP(Table2[[#This Row],[Ticket]],Okey!A:B,2,0),"") -> ok | I374: Completed | J374: =VLOOKUP(Table2[[#This Row],[Author]],People!A:B,2,0) -> MGF | M374: Marcus Morowski
A375: =1+A374 -> 374 | B375: F0 | C375: FR5747314 | D375: RPL_E4_US05 | E375: RPL_E4_US05 | F375: L000013447 | G375: New | H375: =IFERROR(VLOOKUP(Table2[[#This Row],[Ticket]],Okey!A:B,2,0),"") -> ok | I375: Completed | J375: LS | M375: Anne-Francoise Dugast
A376: =1+A375 -> 375 | B376: F0 | C376: FR5756501 | D376: H000004351 | E376: ES - Medical Studies Evobrutinib | F376: H000003990 | G376: New | H376: =IFERROR(VLOOKUP(Table2[[#This Row],[Ticket]],Okey!A:B,2,0),"") -> ok | I376: Completed | J376: =VLOOKUP(Table2[[#This Row],[Author]],People!A:B,2,0) -> HC | M376: Elena Rasines Martin
A377: =1+A376 -> 376 | B377: F0 | C377: FR5761353 | D377: H000004337 | E377: ES - Sales Promotion Xevinapant | G377: Rename | H377: =IFERROR(VLOOKUP(Table2[[#This Row],[Ticket]],Okey!A:B,2,0),"") -> ok | I377: Completed | J377: =VLOOKUP(Table2[[#This Row],[Author]],People!A:B,2,0) -> HC | M377: Roland Earvin Combalicer
A378: =1+A377 -> 377 | B378: F0 | C378: FR5761353 | D378: H000004338 | E378: ES - Medical non R&D Xevinapant | G378: Rename | H378: =IFERROR(VLOOKUP(Table2[[#This Row],[Ticket]],Okey!A:B,2,0),"") -> ok | I378: Completed | J378: =VLOOKUP(Table2[[#This Row],[Author]],People!A:B,2,0) -> HC | M378: Roland Earvin Combalicer
A379: =1+A378 -> 378 | B379: F0 | C379: FR5766051 | D379: H000004349 | E379: IE - SP Evobrutinib | G379: Rename | H379: =IFERROR(VLOOKUP(Table2[[#This Row],[Ticket]],Okey!A:B,2,0),"") -> ok | I379: Completed | J379: =VLOOKUP(Table2[[#This Row],[Author]],People!A:B,2,0) -> HC | M379: Roland Earvin Combalicer
A380: =1+A379 -> 379 | B380: F0 | C380: FR5766051 | D380: H000004352 | E380: GB - FF- Xevinapant | F380: H000002080 | G380: Rename/Move | H380: =IFERROR(VLOOKUP(Table2[[#This Row],[Ticket]],Okey!A:B,2,0),"") -> ok | I380: Completed | J380: =VLOOKUP(Table2[[#This Row],[Author]],People!A:B,2,0) -> HC | M380: Roland Earvin Combalicer
A381: =1+A380 -> 380 | B381: F0 | C381: FR5766051 | D381: H000004353 | E381: GB - LRD - Xevinapant | F381: H000002111 | G381: Rename/Move | H381: =IFERROR(VLOOKUP(Table2[[#This Row],[Ticket]],Okey!A:B,2,0),"") -> ok | I381: Completed | J381: =VLOOKUP(Table2[[#This Row],[Author]],People!A:B,2,0) -> HC | M381: Roland Earvin Combalicer
A382: =1+A381 -> 381 | B382: F0 | C382: FR5766051 | D382: H000004354 | E382: GB - SP - Xevinapant | F382: H000002080 | G382: Rename/Move | H382: =IFERROR(VLOOKUP(Table2[[#This Row],[Ticket]],Okey!A:B,2,0),"") -> ok | I382: Completed | J382: =VLOOKUP(Table2[[#This Row],[Author]],People!A:B,2,0) -> HC | M382: Roland Earvin Combalicer
A383: =1+A382 -> 382 | B383: F0 | C383: FR5766051 | D383: H000004355 | E383: IE - FF - Evobrutinib | F383: H000001807 | G383: Rename/Move | H383: =IFERROR(VLOOKUP(Table2[[#This Row],[Ticket]],Okey!A:B,2,0),"") -> ok | I383: Completed | J383: =VLOOKUP(Table2[[#This Row],[Author]],People!A:B,2,0) -> HC | M383: Roland Earvin Combalicer
A384: =1+A383 -> 383 | B384: F0 | C384: FR5766051 | D384: H000004356 | E384: IE - LRD - Xevinapant | F384: H000001826 | G384: Rename/Move | H384: =IFERROR(VLOOKUP(Table2[[#This Row],[Ticket]],Okey!A:B,2,0),"") -> ok | I384: Completed | J384: =VLOOKUP(Table2[[#This Row],[Author]],People!A:B,2,0) -> HC | M384: Roland Earvin Combalicer
A385: =1+A384 -> 384 | B385: F0 | C385: FR5766051 | D385: H000004357 | E385: IE - SP - Xevinapant | F385: H000001795 | G385: Rename/Move | H385: =IFERROR(VLOOKUP(Table2[[#This Row],[Ticket]],Okey!A:B,2,0),"") -> ok | I385: Completed | J385: =VLOOKUP(Table2[[#This Row],[Author]],People!A:B,2,0) -> HC | M385: Roland Earvin Combalicer
A386: =1+A385 -> 385 | B386: F0 | C386: FR5766051 | D386: H000004358 | E386: IE - SP - Xevinapant | F386: H000001795 | G386: Rename/Move | H386: =IFERROR(VLOOKUP(Table2[[#This Row],[Ticket]],Okey!A:B,2,0),"") -> ok | I386: Completed | J386: =VLOOKUP(Table2[[#This Row],[Author]],People!A:B,2,0) -> HC | M386: Roland Earvin Combalicer
A387: =1+A386 -> 386 | B387: F0 | C387: FR5769280 | D387: H000004359 | E387: US - OE&I - Commercial Operations | F387: H000003648 | G387: New | H387: =IFERROR(VLOOKUP(Table2[[#This Row],[Ticket]],Okey!A:B,2,0),"") -> ok | I387: Completed | J387: =VLOOKUP(Table2[[#This Row],[Author]],People!A:B,2,0) -> HC | M387: Rizza Domingo
A388: =1+A387 -> 387 | B388: F0 | C388: FR5769280 | D388: H000004360 | E388: US - OE&I - Commercial Operations | F388: H000003672 | G388: New | H388: =IFERROR(VLOOKUP(Table2[[#This Row],[Ticket]],Okey!A:B,2,0),"") -> ok | I388: Completed | J388: =VLOOKUP(Table2[[#This Row],[Author]],People!A:B,2,0) -> HC | M388: Rizza Domingo
A389: =1+A388 -> 388 | B389: F0 | C389: FR5769280 | D389: H000004361 | E389: US - OE&I - Commercial Operations | F389: H000003694 | G389: New | H389: =IFERROR(VLOOKUP(Table2[[#This Row],[Ticket]],Okey!A:B,2,0),"") -> ok | I389: Completed | J389: =VLOOKUP(Table2[[#This Row],[Author]],People!A:B,2,0) -> HC | M389: Rizza Domingo
A390: =1+A389 -> 389 | B390: F0 | C390: FR5769280 | D390: H000004362 | E390: US - OE&I - Commercial Operations | F390: H000003715 | G390: New | H390: =IFERROR(VLOOKUP(Table2[[#This Row],[Ticket]],Okey!A:B,2,0),"") -> ok | I390: Completed | J390: =VLOOKUP(Table2[[#This Row],[Author]],People!A:B,2,0) -> HC | M390: Rizza Domingo
A391: =1+A390 -> 390 | B391: F0 | C391: FR5769280 | D391: H000004363 | E391: US - OE&I - Commercial Operations | F391: H000003856 | G391: New | H391: =IFERROR(VLOOKUP(Table2[[#This Row],[Ticket]],Okey!A:B,2,0),"") -> ok | I391: Completed | J391: =VLOOKUP(Table2[[#This Row],[Author]],People!A:B,2,0) -> HC | M391: Rizza Domingo
A392: =1+A391 -> 391 | B392: F0 | C392: FR5769280 | D392: H000004364 | E392: 1261DA Launch and Technology Center | F392: H000000562 | G392: Rename/Move | H392: =IFERROR(VLOOKUP(Table2[[#This Row],[Ticket]],Okey!A:B,2,0),"") -> ok | I392: Completed | J392: =VLOOKUP(Table2[[#This Row],[Author]],People!A:B,2,0) -> HC | M392: Rizza Domingo
A393: =1+A392 -> 392 | B393: F0 | C393: FR5780415 | D393: G000000433 | E393: SM-S Environment, Health & Safety | G393: Rename | H393: =IFERROR(VLOOKUP(Table2[[#This Row],[Ticket]],Okey!A:B,2,0),"") -> ok | I393: Completed | J393: =VLOOKUP(Table2[[#This Row],[Author]],People!A:B,2,0) -> MGF | M393: Manuel Walther
A394: =1+A393 -> 393 | B394: F0 | C394: FR5780415 | D394: G000000394 | E394: SM-ST Technical Plant Safety | G394: Rename | H394: =IFERROR(VLOOKUP(Table2[[#This Row],[Ticket]],Okey!A:B,2,0),"") -> ok | I394: Completed | J394: =VLOOKUP(Table2[[#This Row],[Author]],People!A:B,2,0) -> MGF | M394: Manuel Walther
A395: =1+A394 -> 394 | B395: F0 | C395: FR5780415 | D395: G000000395 | E395: SM-ST Technic. Plant Safety_I | G395: Rename | H395: =IFERROR(VLOOKUP(Table2[[#This Row],[Ticket]],Okey!A:B,2,0),"") -> ok | I395: Completed | J395: =VLOOKUP(Table2[[#This Row],[Author]],People!A:B,2,0) -> MGF | M395: Manuel Walther
A396: =1+A395 -> 395 | B396: F0 | C396: FR5780415 | D396: G000000396 | E396: SM-ST Material Costs | G396: Rename | H396: =IFERROR(VLOOKUP(Table2[[#This Row],[Ticket]],Okey!A:B,2,0),"") -> ok | I396: Completed | J396: =VLOOKUP(Table2[[#This Row],[Author]],People!A:B,2,0) -> MGF | M396: Manuel Walther
A397: =1+A396 -> 396 | B397: F0 | C397: FR5780415 | D397: G000000845 | E397: 'SM-G Gernsheim K01067 | G397: Rename | H397: =IFERROR(VLOOKUP(Table2[[#This Row],[Ticket]],Okey!A:B,2,0),"") -> ok | I397: Completed | J397: =VLOOKUP(Table2[[#This Row],[Author]],People!A:B,2,0) -> MGF | M397: Manuel Walther
A398: =1+A397 -> 397 | B398: F0 | C398: FR5780415 | D398: G000000686 | E398: SM-I Open Area DA | F398: G000000412 | G398: Rename/Move | H398: =IFERROR(VLOOKUP(Table2[[#This Row],[Ticket]],Okey!A:B,2,0),"") -> ok | I398: Completed | J398: =VLOOKUP(Table2[[#This Row],[Author]],People!A:B,2,0) -> MGF | M398: Manuel Walther
A399: =1+A398 -> 398 | B399: F0 | C399: FR5780415 | D399: G000000499 | E399: SM-I Open Area DA CCV | F399: G000000498 | G399: Rename/Move | H399: =IFERROR(VLOOKUP(Table2[[#This Row],[Ticket]],Okey!A:B,2,0),"") -> ok | I399: Completed | J399: =VLOOKUP(Table2[[#This Row],[Author]],People!A:B,2,0) -> MGF | M399: Manuel Walther
A400: =1+A399 -> 399 | B400: F0 | C400: FR5780415 | D400: G000000500 | E400: SM-I FS Open Area DA | F400: G000000498 | G400: Rename/Move | H400: =IFERROR(VLOOKUP(Table2[[#This Row],[Ticket]],Okey!A:B,2,0),"") -> ok | I400: Completed | J400: =VLOOKUP(Table2[[#This Row],[Author]],People!A:B,2,0) -> MGF | M400: Manuel Walther
A401: =1+A400 -> 400 | B401: F0 | C401: FR5780415 | D401: G000000404 | E401: SM-IP Material Cost Centers | F401: G000000886 | G401: Rename/Move | H401: =IFERROR(VLOOKUP(Table2[[#This Row],[Ticket]],Okey!A:B,2,0),"") -> ok | I401: Completed | J401: =VLOOKUP(Table2[[#This Row],[Author]],People!A:B,2,0) -> MGF | M401: Manuel Walther
A402: =1+A401 -> 401 | B402: F0 | C402: FR5780415 | D402: G000000922 | E402: SM-IPC/ IPE/ IPI/ IPP | F402: G000000886 | G402: Rename/Move | H402: =IFERROR(VLOOKUP(Table2[[#This Row],[Ticket]],Okey!A:B,2,0),"") -> ok | I402: Completed | J402: =VLOOKUP(Table2[[#This Row],[Author]],People!A:B,2,0) -> MGF | M402: Manuel Walther
A403: =1+A402 -> 402 | B403: F0 | C403: FR5780415 | D403: G000000923 | E403: SM-IE Ext. Energy Costs DA | F403: G000000887 | G403: Rename/Move | H403: =IFERROR(VLOOKUP(Table2[[#This Row],[Ticket]],Okey!A:B,2,0),"") -> ok | I403: Completed | J403: =VLOOKUP(Table2[[#This Row],[Author]],People!A:B,2,0) -> MGF | M403: Manuel Walther
...

Sheet Sheet11
A1: L000013817 | B1: L000013445
A2: L000013818 | B2: L000013417
A3: L000013819 | B3: L000006420
A4: L000013820 | B4: L000006420
A5: L000013821 | B5: L000013174
A6: L000013822 | B6: L000013174
A7: L000013823 | B7: L000013785
A8: L000006425 | B8: L000013819
A9: L000006429 | B9: L000013819
A10: L000006431 | B10: L000013820
A11: L000011451 | B11: L000013820
A12: L000007087 | B12: L000013821
... A40: L000006295 | B40: L000013685

Sheet Sheet10
A1: G000001191 | B1: MBS S&T - Business Process Management
A2: G000000392 | B2: SM-PT
A3: G000000389 | B3: SM-PM und PT
A4: G000000918 | B4: SM-PTT Material Management
A5: G000000919 | B5: SM-PTT Technical Warehouse
A6: P000000196 | B6: PG1 Blending+Packaging
A7: P000000197 | B7: PG2 Coating
A8: P000000198 | B8: PG1 Substrates
A9: L000005722 | B9: BM - Comm NA - South Pharma
A10: L000013350 | B10: CDMO - APAC Sales
A11: P000000001 | B11: EL-OP Optronics
A12: P000000002 | B12: EL-OP BU Head & Other
... A149: P000000331 | B149: Quality Gernsheim

Sheet Sheet9
A1: G000000994 | B1: G000000529
A2: G000000995 | B2: G000000529
A3: G000000993 | B3: G000000873
A4: G000001357 | B4: G000001146
A5: G000001191 | B5: G000001146
A6: G000000511 | B6: G000000873
A7: G000000512 | B7: G000000873
A8: G000000513 | B8: G000000873
A9: G000000514 | B9: G000000873
A10: G000001007 | B10: G000000873
A11: G000001065 | B11: G000000873
A12: G000001066 | B12: G000000873
... A149: P000000331 | B149: P000000330

Sheet Sheet7
A1: KR00 | I1: KR00
A2: G000001357 | B2: MBS S&T Learning & Develop., Knwldg Mgt | C2: X | I2: G000001146 | J2: G000001357
A3: G000001191 | B3: MBS S&T - Business Process Management | C3: X | I3: G000001143 | J3: G000001358
A4: G000000392 | B4: SM-PT | C4: X | I4: P000000001 | J4: P000001254
A5: G000000389 | B5: SM-PM und PT | C5: X | I5: P000001254 | J5: P000001255
A6: G000000918 | B6: SM-PTT Material Management | C6: X | I6: P000001254 | J6: P000001256
A7: G000000919 | B7: SM-PTT Technical Warehouse | C7: X | I7: P000001254 | J7: P000001257
A8: G000000387 | B8: SM-PM | C8: X | I8: P000001254 | J8: P000001258
A9: G000000391 | B9: SM-PMA | C9: X | I9: P000000024 | J9: P000001259
A10: P000000196 | B10: PG1 Blending+Packaging | C10: X | I10: P000001259 | J10: P000001260
A11: P000000197 | B11: PG2 Coating | C11: X | I11: P000001259 | J11: P000001261
A12: P000000198 | B12: PG1 Substrates | C12: X | I12: P000001259 | J12: P000001262
A13: G000001358 | B13: GMV MBS Hub Wroclaw - ABP | C13: X | I13: P000001259 | J13: P000001263
... A17: P000001257 | B17: EL-OP-M M&I Operations | C17: X | I17: P000000590 | J17: P000001267
A18: P000001258 | B18: EL-OP-M M&I R&D | C18: X | O18: L000013595
A19: P000000001 | B19: EL-OP Optronics | C19: X | O19: L000013595
A20: P000000002 | B20: EL-OP BU Head & Other | C20: X
A21: P000000695 | B21: EL-OP BU head Organization | C21: X
A22: P000000696 | B22: EL-OP Inventor Remuneration | C22: X
A23: P000000697 | B23: EL-OP Intangible Assets | C23: X
A24: P000000698 | B24: EL-OP Other | C24: X
A25: P000000022 | B25: EL-OP-W LC Windows | C25: X
A26: P000000055 | B26: EL-OP-S Supply Chain Optronics | C26: X
A27: P000000505 | B27: Optronics Production Sites | C27: X
A28: P000000056 | B28: EL-OP-SD Site Darmstadt, Germany | C28: X
A29: P000001172 | B29: EL-OP-SDPP Production Planning | C29: X
A30: P000000087 | B30: EL-OP-SA Site Atsugi, Japan | C30: X
A31: P000000097 | B31: EL-OP-SZ Site Suzhou, China | C31: X
A32: P000000107 | B32: EL-OP-ST Site Taoyuan, Taiwan | C32: X | H32: 1000
A33: P000000117 | B33: EL-OP-SH Site Hsinchu, Taiwan | C33: X | H33: L000013824 | I33: mRNA CDMO QAO | J33: X | K33: X | L33: X | M33: X | N33: X
A34: P000000127 | B34: EL-OP-SP Site Poseung, S. Korea | C34: X | H34: L000013825 | I34: mRNA CDMO Support Functions | J34: X | K34: X | L34: X | M34: X | N34: X
A35: P000000137 | B35: EL-OP-SS Site Shanghai, China | C35: X | H35: P000000331 | I35: Quality Gernsheim | J35: X | K35: X | L35: X | M35: X | N35: X
A36: P000000506 | B36: EL-OP-SC Supply Chain Excellence | C36: X
A37: P000000507 | B37: EL-OP-SQ QA Optronics | C37: X
A38: P000001167 | B38: EL-OP-SG Global Demand & Supply Planning | C38: X
A39: P000001168 | B39: EL-OP-SV Value Stream Mngt | C39: X
A40: P000001109 | B40: EL-OP-L LC/DPM] | C40: X
A41: P000001110 | B41: EL-OP-LC LC/DPM Sales CN | C41: X
A42: P000001111 | B42: EL-OP-LT LC/DPM Sales TW & JP | C42: X
A43: P000001112 | B43: EL-OP-LM LC/DPM Marketing | C43: X
A44: P000001113 | B44: EL-OP-LM LC/DPM Marketing Organization | C44: X
A45: P000001114 | B45: EL-OP-LM LC/DPM Sales Promotion | C45: X
A46: P000001115 | B46: EL-OP-L LC/DPM Royalties/Commissions | C46: X
A47: P000001116 | B47: EL-OP-L LC/DPM Other | C47: X
... A116: P000001267 | B116: Licrivision | C116: X

Sheet Sheet6
A1: 1000
A2: G000001146 | B2: G000001357
A3: L000013445 | B3: L000013817
A4: L000013417 | B4: L000013818
A5: L000006420 | B5: L000013819
A6: L000006420 | B6: L000013820
A7: L000013174 | B7: L000013821
A8: L000013174 | B8: L000013822
A9: L000013785 | B9: L000013823
A10: G000001143 | B10: G000001358
A11: P000000001 | B11: P000001254
A12: P000001254 | B12: P000001255
A13: P000001254 | B13: P000001256
... A24: P000000590 | B24: P000001267

Sheet Sheet5
A1: 25014377
A2: 25014151

Sheet Sheet4
A1: 1000
A2: G000001357 | B2: MBS S&T Learning & Develop., Knwldg Mgt | C2: X | D2: X | E2: X | F2: X | G2: X
A3: G000001191 | B3: MBS S&T - Business Process Management | C3: X | D3: X | E3: X | F3: X | G3: X
A4: G000000392 | B4: SM-PT | C4: X | D4: X | E4: X | F4: X | G4: X
A5: G000000389 | B5: SM-PM und PT | C5: X | D5: X | E5: X | F5: X | G5: X
A6: G000000918 | B6: SM-PTT Material Management | C6: X | D6: X | E6: X | F6: X | G6: X
A7: G000000919 | B7: SM-PTT Technical Warehouse | C7: X | D7: X | E7: X | F7: X | G7: X
A8: G000000919 | B8: SM-PTT IVV Allocation CCs | C8: X | D8: X | E8: X | F8: X | G8: X
A9: G000000387 | B9: SM-PM | C9: X | D9: X | E9: X | F9: X | G9: X
A10: G000000391 | B10: SM-PMA | C10: X | D10: X | E10: X | F10: X | G10: X
A11: P000000196 | B11: PG1 Blending+Packaging | C11: X | D11: X | E11: X | F11: X | G11: X
A12: P000000197 | B12: PG2 Coating | C12: X | D12: X | E12: X | F12: X | G12: X
A13: P000000198 | B13: PG1 Substrates | C13: X | D13: X | E13: X | F13: X | G13: X
... A141: P000001267 | B141: Licrivision | C141: X | D141: X | E141: X | F141: X | G141: X

Sheet Sheet3
B1: 1000
B2: G000000359 | C2: SM-H Site & HQ Development Services | D2: X | E2: X | F2: X | G2: X | H2: X
B4: KR00
B5: G000000359 | C5: SM-H Site & HQ Development Services | D5: X

Sheet Sheet2
A1: 1000
A2: G000001356 | B2: EF-IT-PX | C2: X | D2: X | E2: X | F2: X | G2: X
A3: IT06100900 | B3: EF-IT-PX | C3: X | D3: X | E3: X | F3: X | G3: X
A5: KR00
A6: G000001356 | B6: EF-IT-PX | C6: X
A7: IT06100900 | B7: EF-IT-PX | C7: X
A10: 1000
A11: G000000340 | B11: G000001356
A12: G000001356 | B12: IT06100900
A14: Kr00
A15: G000000340 | B15: G000001356
A16: G000001356 | B16: IT06100900

Sheet Sheet1
A1: 1000
A2: G000001281 | B2: GPA PS - Core Ext.Cost | C2: X | D2: X | E2: X | F2: X | G2: X
A3: G000001282 | B3: GPB PS - Healthcare Ext.Cost | C3: X | D3: X | E3: X | F3: X | G3: X
A4: G000001283 | B4: GPC PS - Life Science Ext.Cost | C4: X | D4: X | E4: X | F4: X | G4: X
A5: G000001284 | B5: GPD PS - Electronics Ext.Cost | C5: X | D5: X | E5: X | F5: X | G5: X
A7: KR00
A8: G000001281 | B8: GPA PS - Core Ext.Cost | C8: X
A9: G000001282 | B9: GPB PS - Healthcare Ext.Cost | C9: X
A10: G000001283 | B10: GPC PS - Life Science Ext.Cost | C10: X
A11: G000001284 | B11: GPD PS - Electronics Ext.Cost | C11: X

Sheet People
A1: Opened By | B1: Sector
A2: Joshua Cachola | B2: MGF
A3: Simone Oratovski | B3: HC
A4: Nicolas Trautmann | B4: MGF
A5: Henry Ifurung Jr. | B5: HC
A6: Phoebe Anne Fortaleza | B6: LS
A7: Joebeth Navarro | B7: HC
A8: Paul Kopp | B8: MGF
A9: Maureen Cardano | B9: HC
A10: Roland Earvin Combalicer | B10: HC
A11: Marcus Morowski | B11: MGF
A12: Megan Wang | B12: MGF
... A47: Gerhard Doeller | B47: EL

Sheet 2023
A1: No. | B1: Forecast? | C1: Ticket | D1: Node | E1: Name | F1: Parent | G1: Action | H1: STATUS | I1: STATUS Check | J1: Sector | K1: Comments | L1: SANITY | M1: Author
A2: 1 | B2: F1 | C2: FR5068879 | D2: L000011515 | F2: O000000009 | G2: Delete | H2: =IFERROR(VLOOKUP(Table2[[#This Row],[Ticket]],Okey!A:B,2,0),"") -> Ok | I2: Closed | J2: =VLOOKUP(Table2[[#This Row],[Author]],People!A:B,2,0) -> MGF | M2: Phoebe Anne Fortaleza
A3: =1+A2 -> 2 | B3: F1 | C3: FR5068879 | D3: L000013398 | E3: BioVV - Quality & Regulatory -G | F3: L000006935 | G3: New | H3: =IFERROR(VLOOKUP(Table2[[#This Row],[Ticket]],Okey!A:B,2,0),"") -> ok | I3: Closed | J3: =VLOOKUP(Table2[[#This Row],[Author]],People!A:B,2,0) -> MGF | M3: Phoebe Anne Fortaleza
A4: =1+A3 -> 3 | B4: F1 | C4: FR5072548 | D4: G000000958 | F4: G000000955 | G4: Move | H4: =IFERROR(VLOOKUP(Table2[[#This Row],[Ticket]],Okey!A:B,2,0),"") -> ok | I4: Closed | J4: =VLOOKUP(Table2[[#This Row],[Author]],People!A:B,2,0) -> HC | M4: Nadine Anic
A5: =1+A4 -> 4 | B5: F1 | C5: FR5072548 | D5: G000000959 | F5: G000000958 | G5: Move | H5: =IFERROR(VLOOKUP(Table2[[#This Row],[Ticket]],Okey!A:B,2,0),"") -> ok | I5: Closed | J5: =VLOOKUP(Table2[[#This Row],[Author]],People!A:B,2,0) -> HC | M5: Nadine Anic
A6: =1+A5 -> 5 | B6: F1 | C6: FR5072548 | D6: G000000960 | F6: G000000958 | G6: Move | H6: =IFERROR(VLOOKUP(Table2[[#This Row],[Ticket]],Okey!A:B,2,0),"") -> ok | I6: Closed | J6: =VLOOKUP(Table2[[#This Row],[Author]],People!A:B,2,0) -> HC | M6: Nadine Anic
A7: =1+A6 -> 6 | B7: F1 | C7: FR5072548 | D7: G000000961 | F7: G000000958 | G7: Move | H7: =IFERROR(VLOOKUP(Table2[[#This Row],[Ticket]],Okey!A:B,2,0),"") -> ok | I7: Closed | J7: =VLOOKUP(Table2[[#This Row],[Author]],People!A:B,2,0) -> MGF | M7: Nadine Anic
A8: =1+A7 -> 7 | B8: F1 | C8: FR5072548 | D8: G000000962 | F8: G000000958 | G8: Move | H8: =IFERROR(VLOOKUP(Table2[[#This Row],[Ticket]],Okey!A:B,2,0),"") -> ok | I8: Closed | J8: =VLOOKUP(Table2[[#This Row],[Author]],People!A:B,2,0) -> MGF | M8: Nadine Anic
A9: =1+A8 -> 8 | B9: F1 | C9: FR5072548 | D9: G000000963 | F9: G000000958 | G9: Move | H9: =IFERROR(VLOOKUP(Table2[[#This Row],[Ticket]],Okey!A:B,2,0),"") -> ok | I9: Closed | J9: =VLOOKUP(Table2[[#This Row],[Author]],People!A:B,2,0) -> MGF | M9: Nadine Anic
A10: =1+A9 -> 9 | B10: F1 | C10: FR5072548 | D10: G000000964 | F10: G000000958 | G10: Move | H10: =IFERROR(VLOOKUP(Table2[[#This Row],[Ticket]],Okey!A:B,2,0),"") -> ok | I10: Closed | J10: =VLOOKUP(Table2[[#This Row],[Author]],People!A:B,2,0) -> MGF | M10: Nadine Anic
A11: =1+A10 -> 10 | B11: F1 | C11: FR5072548 | D11: G000000965 | F11: G000000958 | G11: Move | H11: =IFERROR(VLOOKUP(Table2[[#This Row],[Ticket]],Okey!A:B,2,0),"") -> ok | I11: Closed | J11: =VLOOKUP(Table2[[#This Row],[Author]],People!A:B,2,0) -> MGF | M11: Nadine Anic
A12: =1+A11 -> 11 | B12: F1 | C12: FR5072548 | D12: G000000966 | F12: G000000955 | G12: Move | H12: =IFERROR(VLOOKUP(Table2[[#This Row],[Ticket]],Okey!A:B,2,0),"") -> ok | I12: Closed | J12: =VLOOKUP(Table2[[#This Row],[Author]],People!A:B,2,0) -> MGF | M12: Nadine Anic
A13: =1+A12 -> 12 | B13: F1 | C13: FR5072548 | D13: G000000967 | F13: G000000956 | G13: Move | H13: =IFERROR(VLOOKUP(Table2[[#This Row],[Ticket]],Okey!A:B,2,0),"") -> ok | I13: Closed | J13: =VLOOKUP(Table2[[#This Row],[Author]],People!A:B,2,0) -> MGF | M13: Nadine Anic
A14: =1+A13 -> 13 | B14: F1 | C14: FR5072548 | D14: G000000968 | F14: G000000967 | G14: Move | H14: =IFERROR(VLOOKUP(Table2[[#This Row],[Ticket]],Okey!A:B,2,0),"") -> ok | I14: Closed | J14: =VLOOKUP(Table2[[#This Row],[Author]],People!A:B,2,0) -> MGF | M14: Nadine Anic
A15: =1+A14 -> 14 | B15: F1 | C15: FR5072548 | D15: G000000969 | F15: G000000967 | G15: Move | H15: =IFERROR(VLOOKUP(Table2[[#This Row],[Ticket]],Okey!A:B,2,0),"") -> ok | I15: Closed | J15: =VLOOKUP(Table2[[#This Row],[Author]],People!A:B,2,0) -> MGF | M15: Nadine Anic
... A41: =1+A40 -> 40 | B41: F1 | C41: FR5072548 | D41: G000000995 | F41: G000000993 | G41: Move | H41: =IFERROR(VLOOKUP(Table2[[#This Row],[Ticket]],Okey!A:B,2,0),"") -> ok | I41: Closed | J41: =VLOOKUP(Table2[[#This Row],[Author]],People!A:B,2,0) -> MGF | M41: Nadine Anic
A42: =1+A41 -> 41 | B42: F1 | C42: FR5082089 | D42: G000000461 | E42: SM-B Strategy Realization & Enablement | G42: Rename | H42: =IFERROR(VLOOKUP(Table2[[#This Row],[Ticket]],Okey!A:B,2,0),"") -> ok | I42: Closed | J42: =VLOOKUP(Table2[[#This Row],[Author]],People!A:B,2,0) -> MGF | M42: Sybille Rogmans
A43: =1+A42 -> 42 | B43: F1 | C43: FR5082089 | D43: G000000462 | E43: SM-B Strategy Realization & Enablement | G43: Rename | H43: =IFERROR(VLOOKUP(Table2[[#This Row],[Ticket]],Okey!A:B,2,0),"") -> ok | I43: Closed | J43: =VLOOKUP(Table2[[#This Row],[Author]],People!A:B,2,0) -> MGF | M43: Sybille Rogmans
A44: =1+A43 -> 43 | B44: F1 | C44: FR5082089 | D44: G000000463 | E44: SM-BB Business Excellence | G44: Rename | H44: =IFERROR(VLOOKUP(Table2[[#This Row],[Ticket]],Okey!A:B,2,0),"") -> ok | I44: Closed | J44: =VLOOKUP(Table2[[#This Row],[Author]],People!A:B,2,0) -> MGF | M44: Sybille Rogmans
A45: =1+A44 -> 44 | B45: F1 | C45: FR5082089 | D45: G000000464 | E45: SM-BS Strategy Realization | G45: Rename | H45: =IFERROR(VLOOKUP(Table2[[#This Row],[Ticket]],Okey!A:B,2,0),"") -> ok | I45: Closed | J45: =VLOOKUP(Table2[[#This Row],[Author]],People!A:B,2,0) -> MGF | M45: Sybille Rogmans
A46: =1+A45 -> 45 | B46: F1 | C46: FR5082089 | D46: G000000466 | E46: SM-BC Strategic Contracting | G46: Rename | H46: =IFERROR(VLOOKUP(Table2[[#This Row],[Ticket]],Okey!A:B,2,0),"") -> ok | I46: Closed | J46: =VLOOKUP(Table2[[#This Row],[Author]],People!A:B,2,0) -> MGF | M46: Sybille Rogmans
A47: =1+A46 -> 46 | B47: F1 | C47: FR5082089 | D47: G000000470 | E47: SM-BQ dummy 6 | G47: Rename | H47: =IFERROR(VLOOKUP(Table2[[#This Row],[Ticket]],Okey!A:B,2,0),"") -> ok | I47: Closed | J47: =VLOOKUP(Table2[[#This Row],[Author]],People!A:B,2,0) -> MGF | M47: Sybille Rogmans
A48: =1+A47 -> 47 | B48: F1 | C48: FR5082089 | D48: G000000473 | E48: SM-BD Data & Digital Enablement | G48: Rename | H48: =IFERROR(VLOOKUP(Table2[[#This Row],[Ticket]],Okey!A:B,2,0),"") -> ok | I48: Closed | J48: =VLOOKUP(Table2[[#This Row],[Author]],People!A:B,2,0) -> MGF | M48: Sybille Rogmans
A49: =1+A48 -> 48 | B49: F1 | C49: FR5082089 | D49: G000000868 | E49: SM-BP People, Change & Comms | G49: Rename | H49: =IFERROR(VLOOKUP(Table2[[#This Row],[Ticket]],Okey!A:B,2,0),"") -> ok | I49: Closed | J49: =VLOOKUP(Table2[[#This Row],[Author]],People!A:B,2,0) -> MGF | M49: Sybille Rogmans
A50: =1+A49 -> 49 | B50: F1 | C50: FR5082089 | D50: G000000471 | E50: SM-BQ Quality Management | F50: G000000470 | G50: Rename/Move | H50: =IFERROR(VLOOKUP(Table2[[#This Row],[Ticket]],Okey!A:B,2,0),"") -> ok | I50: Closed | J50: =VLOOKUP(Table2[[#This Row],[Author]],People!A:B,2,0) -> MGF | M50: Sybille Rogmans
A51: =1+A50 -> 50 | B51: F1 | C51: FR5092977 | D51: G000000355 | E51: SM Site Management | G51: Rename | H51: =IFERROR(VLOOKUP(Table2[[#This Row],[Ticket]],Okey!A:B,2,0),"") -> ok | I51: Closed | J51: =VLOOKUP(Table2[[#This Row],[Author]],People!A:B,2,0) -> MGF | M51: Nicolas Trautmann
A52: =1+A51 -> 51 | B52: F1 | C52: FR5092977 | D52: G000000359 | E52: SM-H Strategy & Transform. | G52: Rename | H52: =IFERROR(VLOOKUP(Table2[[#This Row],[Ticket]],Okey!A:B,2,0),"") -> ok | I52: Closed | J52: =VLOOKUP(Table2[[#This Row],[Author]],People!A:B,2,0) -> MGF | M52: Nicolas Trautmann
A53: =1+A52 -> 52 | B53: F1 | C53: FR5092977 | D53: G000000365 | E53: SM-A Analytical Services | G53: Rename | H53: =IFERROR(VLOOKUP(Table2[[#This Row],[Ticket]],Okey!A:B,2,0),"") -> ok | I53: Closed | J53: =VLOOKUP(Table2[[#This Row],[Author]],People!A:B,2,0) -> MGF | M53: Nicolas Trautmann
A54: =1+A53 -> 53 | B54: F1 | C54: FR5092977 | D54: G000000372 | E54: SM-E Engineering Services | G54: Rename | H54: =IFERROR(VLOOKUP(Table2[[#This Row],[Ticket]],Okey!A:B,2,0),"") -> ok | I54: Closed | J54: =VLOOKUP(Table2[[#This Row],[Author]],People!A:B,2,0) -> MGF | M54: Nicolas Trautmann
A55: =1+A54 -> 54 | B55: F1 | C55: FR5092977 | D55: G000000410 | E55: SM-U | G55: Rename | H55: =IFERROR(VLOOKUP(Table2[[#This Row],[Ticket]],Okey!A:B,2,0),"") -> ok | I55: Closed | J55: =VLOOKUP(Table2[[#This Row],[Author]],People!A:B,2,0) -> MGF | M55: Nicolas Trautmann
A56: =1+A55 -> 55 | B56: F1 | C56: FR5092977 | D56: G000000439 | E56: SM-Verrechnungen / Sachkosten | G56: Rename | H56: =IFERROR(VLOOKUP(Table2[[#This Row],[Ticket]],Okey!A:B,2,0),"") -> ok | I56: Closed | J56: =VLOOKUP(Table2[[#This Row],[Author]],People!A:B,2,0) -> MGF | M56: Nicolas Trautmann
A57: =1+A56 -> 56 | B57: F1 | C57: FR5092977 | D57: G000000890 | E57: SM-HG Fluxum | G57: Rename | H57: =IFERROR(VLOOKUP(Table2[[#This Row],[Ticket]],Okey!A:B,2,0),"") -> ok | I57: Closed | J57: =VLOOKUP(Table2[[#This Row],[Author]],People!A:B,2,0) -> MGF | M57: Nicolas Trautmann
A58: =1+A57 -> 57 | B58: F1 | C58: FR5092977 | D58: G000000360 | E58: SM-HF Future | G58: Rename | H58: =IFERROR(VLOOKUP(Table2[[#This Row],[Ticket]],Okey!A:B,2,0),"") -> ok | I58: Closed | J58: =VLOOKUP(Table2[[#This Row],[Author]],People!A:B,2,0) -> MGF | M58: Nicolas Trautmann
A59: =1+A58 -> 58 | B59: F1 | C59: FR5092977 | D59: G000000361 | E59: DA Goes Global | G59: Rename | H59: =IFERROR(VLOOKUP(Table2[[#This Row],[Ticket]],Okey!A:B,2,0),"") -> ok | I59: Closed | J59: =VLOOKUP(Table2[[#This Row],[Author]],People!A:B,2,0) -> MGF | M59: Nicolas Trautmann
A60: =1+A59 -> 59 | B60: F1 | C60: FR5092977 | D60: G000000362 | E60: SM-HM Marketing&Dialog | G60: Rename | H60: =IFERROR(VLOOKUP(Table2[[#This Row],[Ticket]],Okey!A:B,2,0),"") -> ok | I60: Closed | J60: =VLOOKUP(Table2[[#This Row],[Author]],People!A:B,2,0) -> MGF | M60: Nicolas Trautmann
A61: =1+A60 -> 60 | B61: F1 | C61: FR5092977 | D61: G000000888 | E61: SM-HR HQ Relations & Mgmt of | G61: Rename | H61: =IFERROR(VLOOKUP(Table2[[#This Row],[Ticket]],Okey!A:B,2,0),"") -> ok | I61: Closed | J61: =VLOOKUP(Table2[[#This Row],[Author]],People!A:B,2,0) -> MGF | M61: Nicolas Trautmann
A62: =1+A61 -> 61 | B62: F1 | C62: FR5092977 | D62: G000000889 | E62: SM-HP Plattforms | G62: Rename | H62: =IFERROR(VLOOKUP(Table2[[#This Row],[Ticket]],Okey!A:B,2,0),"") -> ok | I62: Closed | J62: =VLOOKUP(Table2[[#This Row],[Author]],People!A:B,2,0) -> MGF | M62: Nicolas Trautmann
... A207: =1+A206 -> 206 | B207: F1 | C207: FR5092977 | D207: G000000416 | E207: SM-SCC Conference & Catering | G207: Rename | H207: =IFERROR(VLOOKUP(Table2[[#This Row],[Ticket]],Okey!A:B,2,0),"") -> ok | I207: Closed | J207: =VLOOKUP(Table2[[#This Row],[Author]],People!A:B,2,0) -> MGF | M207: Nicolas Trautmann
A208: =1+A207 -> 207 | B208: F1 | C208: FR5099062 | D208: H000004191 | E208: Medical - Local R&D | F208: H000000447 | G208: New | H208: =IFERROR(VLOOKUP(Table2[[#This Row],[Ticket]],Okey!A:B,2,0),"") -> ok | I208: Closed | J208: =VLOOKUP(Table2[[#This Row],[Author]],People!A:B,2,0) -> MGF | M208: Megan Wang
A209: =1+A208 -> 208 | B209: F1 | C209: FR5107986 | D209: H000000813 | E209: CMS International | G209: Rename | H209: =IFERROR(VLOOKUP(Table2[[#This Row],[Ticket]],Okey!A:B,2,0),"") -> ok | I209: Closed | J209: =VLOOKUP(Table2[[#This Row],[Author]],People!A:B,2,0) -> MGF | M209: Marlon Abadia
A210: =1+A209 -> 209 | B210: F1 | C210: FR5107986 | D210: H000000814 | E210: CMS Clinical Biomarker & Tech. | G210: Rename | H210: =IFERROR(VLOOKUP(Table2[[#This Row],[Ticket]],Okey!A:B,2,0),"") -> ok | I210: Closed | J210: =VLOOKUP(Table2[[#This Row],[Author]],People!A:B,2,0) -> MGF | M210: Marlon Abadia
A211: =1+A210 -> 210 | B211: F1 | C211: FR5107986 | D211: H000000899 | E211: CMS Data Sciences | G211: Rename | H211: =IFERROR(VLOOKUP(Table2[[#This Row],[Ticket]],Okey!A:B,2,0),"") -> ok | I211: Closed | J211: =VLOOKUP(Table2[[#This Row],[Author]],People!A:B,2,0) -> MGF | M211: Marlon Abadia
A212: =1+A211 -> 211 | B212: F1 | C212: FR5107986 | D212: H000000815 | E212: CMS Quantitative Pharmacology | G212: Rename | H212: =IFERROR(VLOOKUP(Table2[[#This Row],[Ticket]],Okey!A:B,2,0),"") -> ok | I212: Closed | J212: =VLOOKUP(Table2[[#This Row],[Author]],People!A:B,2,0) -> MGF | M212: Marlon Abadia
A213: =1+A212 -> 212 | B213: F1 | C213: FR5107986 | D213: H000000816 | E213: CMS Comp Diagnostics & Biomarker | F213: H000000906 | G213: Rename/Move | H213: =IFERROR(VLOOKUP(Table2[[#This Row],[Ticket]],Okey!A:B,2,0),"") -> ok | I213: Closed | J213: =VLOOKUP(Table2[[#This Row],[Author]],People!A:B,2,0) -> MGF | M213: Marlon Abadia
A214: =1+A213 -> 213 | B214: F1 | C214: FR5107986 | D214: H000000818 | F214: H000000906 | G214: Move | H214: =IFERROR(VLOOKUP(Table2[[#This Row],[Ticket]],Okey!A:B,2,0),"") -> ok | I214: Closed | J214: =VLOOKUP(Table2[[#This Row],[Author]],People!A:B,2,0) -> MGF | M214: Marlon Abadia
A215: =1+A214 -> 214 | B215: F1 | C215: FR5107986 | D215: H000000819 | E215: CMS Epideminology | F215: H000000906 | G215: Rename/Move | H215: =IFERROR(VLOOKUP(Table2[[#This Row],[Ticket]],Okey!A:B,2,0),"") -> ok | I215: Closed | J215: =VLOOKUP(Table2[[#This Row],[Author]],People!A:B,2,0) -> MGF | M215: Marlon Abadia
A216: =1+A215 -> 215 | B216: F1 | C216: FR5107986 | D216: H000004192 | E216: CMS International | F216: H000000906 | G216: New | H216: =IFERROR(VLOOKUP(Table2[[#This Row],[Ticket]],Okey!A:B,2,0),"") -> ok | I216: Closed | J216: =VLOOKUP(Table2[[#This Row],[Author]],People!A:B,2,0) -> MGF | M216: Marlon Abadia
A217: =1+A216 -> 216 | B217: F1 | C217: FR5109402 | D217: G000001005 | E217: SM-EP Site Darmstadt | F217: G000000421 | G217: New | H217: =IFERROR(VLOOKUP(Table2[[#This Row],[Ticket]],Okey!A:B,2,0),"") -> ok | I217: Closed | J217: =VLOOKUP(Table2[[#This Row],[Author]],People!A:B,2,0) -> MGF | M217: Paul Kopp
A218: =1+A217 -> 217 | B218: F1 | C218: FR5109402 | D218: G000001006 | E218: SM-EP Site Gernsheim | F218: G000000421 | G218: New | H218: =IFERROR(VLOOKUP(Table2[[#This Row],[Ticket]],Okey!A:B,2,0),"") -> ok | I218: Closed | J218: =VLOOKUP(Table2[[#This Row],[Author]],People!A:B,2,0) -> MGF | M218: Paul Kopp
A219: =1+A218 -> 218 | B219: F1 | C219: FR5109402 | D219: G000001007 | E219: SM-EP Site Hohenbrunn | F219: G000000421 | G219: New | H219: =IFERROR(VLOOKUP(Table2[[#This Row],[Ticket]],Okey!A:B,2,0),"") -> ok | I219: Closed | J219: =VLOOKUP(Table2[[#This Row],[Author]],People!A:B,2,0) -> MGF | M219: Paul Kopp
A220: =1+A219 -> 219 | B220: F1 | C220: FR5109402 | D220: G000001008 | E220: SM-EP Grundstücke KGaA | F220: G000000421 | G220: New | H220: =IFERROR(VLOOKUP(Table2[[#This Row],[Ticket]],Okey!A:B,2,0),"") -> ok | I220: Closed | J220: =VLOOKUP(Table2[[#This Row],[Author]],People!A:B,2,0) -> MGF | M220: Paul Kopp
A221: =1+A220 -> 220 | B221: F1 | C221: FR5109402 | D221: G000001009 | E221: SM-EP Verrechnungs-Kostenstellen | F221: G000000421 | G221: New | H221: =IFERROR(VLOOKUP(Table2[[#This Row],[Ticket]],Okey!A:B,2,0),"") -> ok | I221: Closed | J221: =VLOOKUP(Table2[[#This Row],[Author]],People!A:B,2,0) -> MGF | M221: Paul Kopp
A222: =1+A221 -> 221 | B222: F1 | C222: FR5109402 | D222: G000001010 | E222: SM-EP Gebäude DA | F222: G000000421 | G222: New | H222: =IFERROR(VLOOKUP(Table2[[#This Row],[Ticket]],Okey!A:B,2,0),"") -> ok | I222: Closed | J222: =VLOOKUP(Table2[[#This Row],[Author]],People!A:B,2,0) -> MGF | M222: Paul Kopp
A223: =1+A222 -> 222 | B223: F1 | C223: FR5109402 | D223: G000001011 | E223: SM-EP Freiflächen DA | F223: G000000421 | G223: New | H223: =IFERROR(VLOOKUP(Table2[[#This Row],[Ticket]],Okey!A:B,2,0),"") -> ok | I223: Closed | J223: =VLOOKUP(Table2[[#This Row],[Author]],People!A:B,2,0) -> MGF | M223: Paul Kopp
A224: =1+A223 -> 223 | B224: F1 | C224: FR5109402 | D224: G000001012 | E224: Full Service Gebäude DA | F224: G000000421 | G224: New | H224: =IFERROR(VLOOKUP(Table2[[#This Row],[Ticket]],Okey!A:B,2,0),"") -> ok | I224: Closed | J224: =VLOOKUP(Table2[[#This Row],[Author]],People!A:B,2,0) -> MGF | M224: Paul Kopp
A225: =1+A224 -> 224 | B225: F1 | C225: FR5109402 | D225: G000001013 | E225: Shell and Core Gebäude DA | F225: G000000421 | G225: New | H225: =IFERROR(VLOOKUP(Table2[[#This Row],[Ticket]],Okey!A:B,2,0),"") -> ok | I225: Closed | J225: =VLOOKUP(Table2[[#This Row],[Author]],People!A:B,2,0) -> MGF | M225: Paul Kopp
A226: =1+A225 -> 225 | B226: F1 | C226: FR5109402 | D226: G000001014 | E226: Lease Hold Gebäude DA | F226: G000000421 | G226: New | H226: =IFERROR(VLOOKUP(Table2[[#This Row],[Ticket]],Okey!A:B,2,0),"") -> ok | I226: Closed | J226: =VLOOKUP(Table2[[#This Row],[Author]],People!A:B,2,0) -> MGF | M226: Paul Kopp
... A315: =1+A314 -> 314 | B315: F1 | C315: FR5115101 | D315: H000004194 | E315: ES - Medical non R&D Evobrutinib | F315: H000003990 | G315: New | H315: =IFERROR(VLOOKUP(Table2[[#This Row],[Ticket]],Okey!A:B,2,0),"") -> ok | I315: Closed | J315: =VLOOKUP(Table2[[#This Row],[Author]],People!A:B,2,0) -> MGF | M315: Karl Anatoly Uy
A316: =1+A315 -> 315 | B316: F1 | C316: FR5133979 | D316: H000003837 | E316: US - MAPS - Value & Access, Contract Ops | G316: Rename | H316: =IFERROR(VLOOKUP(Table2[[#This Row],[Ticket]],Okey!A:B,2,0),"") -> ok | I316: Closed | J316: =VLOOKUP(Table2[[#This Row],[Author]],People!A:B,2,0) -> MGF | M316: Karl Anatoly Uy
A317: =1+A316 -> 316 | B317: F1 | C317: FR5133979 | D317: H000003839 | E317: US - MAPS - Channel Acct Mgmt & Ops | G317: Rename | H317: =IFERROR(VLOOKUP(Table2[[#This Row],[Ticket]],Okey!A:B,2,0),"") -> ok | I317: Closed | J317: =VLOOKUP(Table2[[#This Row],[Author]],People!A:B,2,0) -> MGF | M317: Karl Anatoly Uy
A318: =1+A317 -> 317 | B318: F1 | C318: FR5133979 | D318: H000003843 | E318: US - MAPS - Value & Access | G318: Rename | H318: =IFERROR(VLOOKUP(Table2[[#This Row],[Ticket]],Okey!A:B,2,0),"") -> ok | I318: Closed | J318: =VLOOKUP(Table2[[#This Row],[Author]],People!A:B,2,0) -> MGF | M318: Karl Anatoly Uy
A319: =1+A318 -> 318 | B319: F1 | C319: FR5133979 | D319: H000003844 | E319: US - MAPS - Contract, Pricing & Insights | G319: Rename | H319: =IFERROR(VLOOKUP(Table2[[#This Row],[Ticket]],Okey!A:B,2,0),"") -> ok | I319: Closed | J319: =VLOOKUP(Table2[[#This Row],[Author]],People!A:B,2,0) -> MGF | M319: Karl Anatoly Uy
A320: =1+A319 -> 319 | B320: F1 | C320: FR5133979 | D320: H000003846 | E320: US - MAPS - Channel Acct Mgmt & Ops | G320: Rename | H320: =IFERROR(VLOOKUP(Table2[[#This Row],[Ticket]],Okey!A:B,2,0),"") -> ok | I320: Closed | J320: =VLOOKUP(Table2[[#This Row],[Author]],People!A:B,2,0) -> MGF | M320: Karl Anatoly Uy
A321: =1+A320 -> 320 | B321: F1 | C321: FR5134014 | D321: H000001447 | E321: CN-FD ISS FBU Head | F321: H000001446 | G321: Rename/Move | H321: =IFERROR(VLOOKUP(Table2[[#This Row],[Ticket]],Okey!A:B,2,0),"") -> ok | I321: Closed | J321: =VLOOKUP(Table2[[#This Row],[Author]],People!A:B,2,0) -> MGF | M321: Joebeth Navarro
A322: =1+A321 -> 321 | B322: F1 | C322: FR5134014 | D322: H000001452 | E322: CN-FD ISS MKT Non-HCP MCM | F322: H000001451 | G322: Rename/Move | H322: =IFERROR(VLOOKUP(Table2[[#This Row],[Ticket]],Okey!A:B,2,0),"") -> ok | I322: Closed | J322: =VLOOKUP(Table2[[#This Row],[Author]],People!A:B,2,0) -> MGF | M322: Joebeth Navarro
A323: =1+A322 -> 322 | B323: F1 | C323: FR5134014 | D323: H000001454 | E323: CN-FD ISS BSE Team | F323: H000001453 | G323: Rename/Move | H323: =IFERROR(VLOOKUP(Table2[[#This Row],[Ticket]],Okey!A:B,2,0),"") -> ok | I323: Closed | J323: =VLOOKUP(Table2[[#This Row],[Author]],People!A:B,2,0) -> MGF | M323: Joebeth Navarro
A324: =1+A323 -> 323 | B324: F1 | C324: FR5134014 | D324: H000004195 | E324: CN-FD FF Sales Mega Center | F324: H000001432 | G324: New | H324: =IFERROR(VLOOKUP(Table2[[#This Row],[Ticket]],Okey!A:B,2,0),"") -> ok | I324: Closed | J324: =VLOOKUP(Table2[[#This Row],[Author]],People!A:B,2,0) -> MGF | M324: Joebeth Navarro
A325: =1+A324 -> 324 | B325: F1 | C325: FR5134014 | D325: H000004196 | E325: CN-FD ISS MKT Non-HCP Head | F325: H000001451 | G325: New | H325: =IFERROR(VLOOKUP(Table2[[#This Row],[Ticket]],Okey!A:B,2,0),"") -> ok | I325: Closed | J325: =VLOOKUP(Table2[[#This Row],[Author]],People!A:B,2,0) -> MGF | M325: Joebeth Navarro
A326: =1+A325 -> 325 | B326: F1 | C326: FR5134014 | D326: H000004197 | E326: CN-FD ISS MKT Non-HCP CE | F326: H000001451 | G326: New | H326: =IFERROR(VLOOKUP(Table2[[#This Row],[Ticket]],Okey!A:B,2,0),"") -> ok | I326: Closed | J326: =VLOOKUP(Table2[[#This Row],[Author]],People!A:B,2,0) -> MGF | M326: Joebeth Navarro
A327: =1+A326 -> 326 | B327: F1 | C327: FR5134014 | D327: H000004198 | E327: CN-FD SP Sales Mega Center | F327: H000001467 | G327: New | H327: =IFERROR(VLOOKUP(Table2[[#This Row],[Ticket]],Okey!A:B,2,0),"") -> ok | I327: Closed | J327: =VLOOKUP(Table2[[#This Row],[Author]],People!A:B,2,0) -> MGF | M327: Joebeth Navarro
A328: =1+A327 -> 327 | B328: F1 | C328: FR5134014 | D328: H000004199 | E328: CN-FD SP MKT Non-HCP Head | F328: H000001483 | G328: New | H328: =IFERROR(VLOOKUP(Table2[[#This Row],[Ticket]],Okey!A:B,2,0),"") -> ok | I328: Closed | J328: =VLOOKUP(Table2[[#This Row],[Author]],People!A:B,2,0) -> MGF | M328: Joebeth Navarro
A329: =1+A328 -> 328 | B329: F1 | C329: FR5134014 | D329: H000004200 | E329: CN-FD SP MKT Non-HCP CE | F329: H000001483 | G329: New | H329: =IFERROR(VLOOKUP(Table2[[#This Row],[Ticket]],Okey!A:B,2,0),"") -> ok | I329: Closed | J329: =VLOOKUP(Table2[[#This Row],[Author]],People!A:B,2,0) -> MGF | M329: Joebeth Navarro
A330: =1+A329 -> 329 | B330: F1 | C330: FR5134014 | D330: H000001432 | E330: CN - FD Field Force National Sales | G330: Rename | H330: =IFERROR(VLOOKUP(Table2[[#This Row],[Ticket]],Okey!A:B,2,0),"") -> ok | I330: Closed | J330: =VLOOKUP(Table2[[#This Row],[Author]],People!A:B,2,0) -> MGF | M330: Joebeth Navarro
A331: =1+A330 -> 330 | B331: F1 | C331: FR5134014 | D331: H000001433 | E331: CN - FD FF Sales Head | G331: Rename | H331: =IFERROR(VLOOKUP(Table2[[#This Row],[Ticket]],Okey!A:B,2,0),"") -> ok | I331: Closed | J331: =VLOOKUP(Table2[[#This Row],[Author]],People!A:B,2,0) -> MGF | M331: Joebeth Navarro
A332: =1+A331 -> 331 | B332: F1 | C332: FR5134014 | D332: H000001434 | E332: CN - FD FF Sales North | G332: Rename | H332: =IFERROR(VLOOKUP(Table2[[#This Row],[Ticket]],Okey!A:B,2,0),"") -> ok | I332: Closed | J332: =VLOOKUP(Table2[[#This Row],[Author]],People!A:B,2,0) -> MGF | M332: Joebeth Navarro
A333: =1+A332 -> 332 | B333: F1 | C333: FR5134014 | D333: H000001435 | E333: CN - FD FF Sales South | G333: Rename | H333: =IFERROR(VLOOKUP(Table2[[#This Row],[Ticket]],Okey!A:B,2,0),"") -> ok | I333: Closed | J333: =VLOOKUP(Table2[[#This Row],[Author]],People!A:B,2,0) -> MGF | M333: Joebeth Navarro
A334: =1+A333 -> 333 | B334: F1 | C334: FR5134014 | D334: H000001436 | E334: CN - FD FF Sales East | G334: Rename | H334: =IFERROR(VLOOKUP(Table2[[#This Row],[Ticket]],Okey!A:B,2,0),"") -> ok | I334: Closed | J334: =VLOOKUP(Table2[[#This Row],[Author]],People!A:B,2,0) -> MGF | M334: Joebeth Navarro
A335: =1+A334 -> 334 | B335: F1 | C335: FR5134014 | D335: H000001437 | E335: CN - FD FF Sales West | G335: Rename | H335: =IFERROR(VLOOKUP(Table2[[#This Row],[Ticket]],Okey!A:B,2,0),"") -> ok | I335: Closed | J335: =VLOOKUP(Table2[[#This Row],[Author]],People!A:B,2,0) -> MGF | M335: Joebeth Navarro
A336: =1+A335 -> 335 | B336: F1 | C336: FR5134014 | D336: H000001438 | E336: CN - FD FF Sales RMM | G336: Rename | H336: =IFERROR(VLOOKUP(Table2[[#This Row],[Ticket]],Okey!A:B,2,0),"") -> ok | I336: Closed | J336: =VLOOKUP(Table2[[#This Row],[Author]],People!A:B,2,0) -> MGF | M336: Joebeth Navarro
A337: =1+A336 -> 336 | B337: F1 | C337: FR5134014 | D337: H000001448 | E337: CN - FD ISS PMO | G337: Rename | H337: =IFERROR(VLOOKUP(Table2[[#This Row],[Ticket]],Okey!A:B,2,0),"") -> ok | I337: Closed | J337: =VLOOKUP(Table2[[#This Row],[Author]],People!A:B,2,0) -> MGF | M337: Joebeth Navarro
A338: =1+A337 -> 337 | B338: F1 | C338: FR5134014 | D338: H000001449 | E338: CN - FD ISS PMO team | G338: Rename | H338: =IFERROR(VLOOKUP(Table2[[#This Row],[Ticket]],Okey!A:B,2,0),"") -> ok | I338: Closed | J338: =VLOOKUP(Table2[[#This Row],[Author]],People!A:B,2,0) -> MGF | M338: Joebeth Navarro
A339: =1+A338 -> 338 | B339: F1 | C339: FR5134014 | D339: H000001451 | E339: CN - FD ISS MKT Non-HCP | G339: Rename | H339: =IFERROR(VLOOKUP(Table2[[#This Row],[Ticket]],Okey!A:B,2,0),"") -> ok | I339: Closed | J339: =VLOOKUP(Table2[[#This Row],[Author]],People!A:B,2,0) -> MGF | M339: Joebeth Navarro
A340: =1+A339 -> 339 | B340: F1 | C340: FR5134014 | D340: H000001467 | E340: CN - FD Sales Promotion National Sales | G340: Rename | H340: =IFERROR(VLOOKUP(Table2[[#This Row],[Ticket]],Okey!A:B,2,0),"") -> ok | I340: Closed | J340: =VLOOKUP(Table2[[#This Row],[Author]],People!A:B,2,0) -> MGF | M340: Joebeth Navarro
A341: =1+A340 -> 340 | B341: F1 | C341: FR5134014 | D341: H000001468 | E341: CN - FD SP Sales Head | G341: Rename | H341: =IFERROR(VLOOKUP(Table2[[#This Row],[Ticket]],Okey!A:B,2,0),"") -> ok | I341: Closed | J341: =VLOOKUP(Table2[[#This Row],[Author]],People!A:B,2,0) -> MGF | M341: Joebeth Navarro
... A348: =1+A347 -> 347 | B348: F1 | C348: FR5134014 | D348: H000001484 | E348: CN - FD SP MKT Non - HCP MCM | G348: Rename | H348: =IFERROR(VLOOKUP(Table2[[#This Row],[Ticket]],Okey!A:B,2,0),"") -> ok | I348: Closed | J348: =VLOOKUP(Table2[[#This Row],[Author]],People!A:B,2,0) -> MGF | M348: Joebeth Navarro
A349: =1+A348 -> 348 | B349: F1 | C349: FR5136045 | D349: L000011136 | E349: LS Management -G | F349: L000011110 | G349: Rename/Move | H349: =IFERROR(VLOOKUP(Table2[[#This Row],[Ticket]],Okey!A:B,2,0),"") -> ok | I349: Closed | J349: =VLOOKUP(Table2[[#This Row],[Author]],People!A:B,2,0) -> MGF | M349: Phoebe Anne Fortaleza
A350: =1+A349 -> 349 | B350: F1 | C350: FR5136045 | D350: L000011336 | E350: Technology Pioneering | F350: L000013275 | G350: Rename/Move | H350: =IFERROR(VLOOKUP(Table2[[#This Row],[Ticket]],Okey!A:B,2,0),"") -> ok | I350: Closed | J350: =VLOOKUP(Table2[[#This Row],[Author]],People!A:B,2,0) -> MGF | M350: Phoebe Anne Fortaleza
A351: =1+A350 -> 350 | B351: F1 | C351: FR5136045 | D351: L000013324 | F351: L000013275 | G351: Move | H351: =IFERROR(VLOOKUP(Table2[[#This Row],[Ticket]],Okey!A:B,2,0),"") -> ok | I351: Closed | J351: =VLOOKUP(Table2[[#This Row],[Author]],People!A:B,2,0) -> MGF | M351: Phoebe Anne Fortaleza
A352: =1+A351 -> 351 | B352: F1 | C352: FR5136045 | D352: L000013325 | F352: L000013275 | G352: Move | H352: =IFERROR(VLOOKUP(Table2[[#This Row],[Ticket]],Okey!A:B,2,0),"") -> ok | I352: Closed | J352: =VLOOKUP(Table2[[#This Row],[Author]],People!A:B,2,0) -> MGF | M352: Phoebe Anne Fortaleza
A353: =1+A352 -> 352 | B353: F1 | C353: FR5136045 | D353: L000013326 | F353: L000013275 | G353: Move | H353: =IFERROR(VLOOKUP(Table2[[#This Row],[Ticket]],Okey!A:B,2,0),"") -> ok | I353: Closed | J353: =VLOOKUP(Table2[[#This Row],[Author]],People!A:B,2,0) -> MGF | M353: Phoebe Anne Fortaleza
A354: =1+A353 -> 353 | B354: F1 | C354: FR5138688 | D354: H000004116 | E354: FR - Sales promotion Xevinapant | F354: H000001612 | G354: Move | H354: =IFERROR(VLOOKUP(Table2[[#This Row],[Ticket]],Okey!A:B,2,0),"") -> ok | I354: Closed | J354: =VLOOKUP(Table2[[#This Row],[Author]],People!A:B,2,0) -> MGF | M354: Thibault Pernelle
A355: =1+A354 -> 354 | B355: F1 | C355: FR5138688 | D355: H000004201 | E355: FR - Medical non R&D Evobrutinib | F355: H000001637 | G355: New | H355: =IFERROR(VLOOKUP(Table2[[#This Row],[Ticket]],Okey!A:B,2,0),"") -> ok | I355: Closed | J355: =VLOOKUP(Table2[[#This Row],[Author]],People!A:B,2,0) -> MGF | M355: Thibault Pernelle
A356: =1+A355 -> 355 | B356: F1 | C356: FR5138688 | D356: H000004202 | E356: FR - Sales promotion Evobrutinib | F356: H000001619 | G356: New | H356: =IFERROR(VLOOKUP(Table2[[#This Row],[Ticket]],Okey!A:B,2,0),"") -> ok | I356: Closed | J356: =VLOOKUP(Table2[[#This Row],[Author]],People!A:B,2,0) -> MGF | M356: Thibault Pernelle
A357: =1+A356 -> 356 | B357: F1 | C357: FR5140150 | D357: H000004203 | E357: FR - Production costs | F357: H000000186 | G357: New | H357: =IFERROR(VLOOKUP(Table2[[#This Row],[Ticket]],Okey!A:B,2,0),"") -> ok | I357: Closed | J357: =VLOOKUP(Table2[[#This Row],[Author]],People!A:B,2,0) -> MGF | M357: Thibault Pernelle
A358: =1+A357 -> 357 | B358: F1 | C358: FR5140253 | D358: H000004204 | E358: GB - ISS -Xevinapant | F358: H000002080 | G358: New | H358: =IFERROR(VLOOKUP(Table2[[#This Row],[Ticket]],Okey!A:B,2,0),"") -> ok | I358: Closed | J358: =VLOOKUP(Table2[[#This Row],[Author]],People!A:B,2,0) -> MGF | M358: Basak Buyukkosker
A359: =1+A358 -> 358 | B359: F1 | C359: FR5140253 | D359: H000004205 | E359: GB - ISS- Evobrutinib | F359: H000002092 | G359: New | H359: =IFERROR(VLOOKUP(Table2[[#This Row],[Ticket]],Okey!A:B,2,0),"") -> ok | I359: Closed | J359: =VLOOKUP(Table2[[#This Row],[Author]],People!A:B,2,0) -> MGF | M359: Basak Buyukkosker
A360: =1+A359 -> 359 | B360: F1 | C360: FR5140253 | D360: H000004206 | E360: GB - LRD Evobrutinib | F360: H000002111 | G360: New | H360: =IFERROR(VLOOKUP(Table2[[#This Row],[Ticket]],Okey!A:B,2,0),"") -> ok | I360: Closed | J360: =VLOOKUP(Table2[[#This Row],[Author]],People!A:B,2,0) -> MGF | M360: Basak Buyukkosker
A361: =1+A360 -> 360 | B361: F1 | C361: FR5140253 | D361: H000004207 | E361: GB - Medical Non R&D Xevinapant | F361: H000002116 | G361: New | H361: =IFERROR(VLOOKUP(Table2[[#This Row],[Ticket]],Okey!A:B,2,0),"") -> ok | I361: Closed | J361: =VLOOKUP(Table2[[#This Row],[Author]],People!A:B,2,0) -> MGF | M361: Basak Buyukkosker
A362: =1+A361 -> 361 | B362: F1 | C362: FR5140253 | D362: H000004208 | E362: GB - Medical Non R&D Evobrutinib | F362: H000002116 | G362: New | H362: =IFERROR(VLOOKUP(Table2[[#This Row],[Ticket]],Okey!A:B,2,0),"") -> ok | I362: Closed | J362: =VLOOKUP(Table2[[#This Row],[Author]],People!A:B,2,0) -> MGF | M362: Basak Buyukkosker
A363: =1+A362 -> 362 | B363: F1 | C363: FR5141188 | D363: H000004209 | E363: SCALA_1786 0000000350 | F363: H000000729 | G363: New | H363: =IFERROR(VLOOKUP(Table2[[#This Row],[Ticket]],Okey!A:B,2,0),"") -> ok | I363: Closed | J363: =VLOOKUP(Table2[[#This Row],[Author]],People!A:B,2,0) -> MGF | M363: Marlon Abadia
...

Sheet Sectors
A1: P | B1: Electronics
A2: L | B2: Life Science
A3: H | B3: Healthcare
A4: G | B4: MGF
A5: O | B5: No known

Sheet Okey
A1: FR5208660 | B1: Ok
A2: FR5265964 | B2: Ok
A3: FR5266249 | B3: Ok
A4: FR5267957 | B4: Ok
A5: FR5267969 | B5: Ok
A6: FR5286834 | B6: Ok
A7: FR5068879 | B7: Ok
A8: FR5072548 | B8: Ok
A9: FR5082089 | B9: Ok
A10: FR5092977 | B10: Ok
A11: FR5099062 | B11: Ok
A12: FR5107986 | B12: Ok
... A230: FR7064446 | B230: ok

Sheet Sheet8
A1: No. | B1: Forecast? | C1: Ticket | D1: Node | E1: Name | F1: Parent | G1: Action | H1: STATUS | I1: STATUS Check | J1: Sector | K1: Comments | L1: SANITY | M1: Author
A2: 3727 | B2: F1 | C2: FR7010885 | D2: G000000919 | E2: SM-PTT IVV Allocation CCs | G2: Rename | J2: MGF | K2: WTF, duplicated | L2: not done | M2: Marcus Morowski

Sheet Pvt
A1: STATUS | H1: Please wait for the GCOH structure preview, but based on our record, everything has been accounted for already.
A3: Row Labels | B3: Count of No. | C3: sd
A4: FR6934915 | B4: 3 | C4: ok
A5: Completed | B5: 3
A6: FR6952137 | B6: 2 | C6: ok
A7: Completed | B7: 2
A8: FR6995596 | B8: 7 | C8: ok
A9: Completed | B9: 7
A10: FR7010885 | B10: 7 | C10: ok
A11: Completed | B11: 6
A12: Not to work on | B12: 1
A13: FR7015139 | B13: 3 | C13: ok
A14: Completed | B14: 3
A15: FR7037412 | B15: 42 | C15: ok
A16: Completed | B16: 42
A17: FR7040358 | B17: 1 | C17: ok
A18: Completed | B18: 1
A19: FR7040888 | B19: 110 | C19: ok
A20: Completed | B20: 110
A21: FR7047478 | B21: 7 | C21: ok
A22: Completed | B22: 7
A23: FR7049853 | B23: 7 | C23: ok
A24: Completed | B24: 7
A25: FR7052523 | B25: 13 | C25: ok
A26: Completed | B26: 13
A27: FR7052768 | B27: 3 | C27: ok
A28: Completed | B28: 3
A29: FR7060566 | B29: 2 | C29: ok
A30: Completed | B30: 2
A31: FR7064446 | B31: 1 | C31: ok
A32: Completed | B32: 1
A33: Grand Total | B33: 208

Sheet KPI
A2: STATUS | B2: (All)
A4: Count of No. | B4: Column Labels
B5: F0 | G5: F0 Total | H5: F1 | M5: F1 Total | N5: F2 | S5: F2 Total | T5: F3 | Y5: F3 Total | Z5: Grand Total
A6: Row Labels | B6: Delete | C6: Move | D6: New | E6: Rename | F6: Rename/Move | H6: Delete | I6: Move | J6: New | K6: Rename | L6: Rename/Move | N6: Delete | O6: Move | P6: New | Q6: Rename | R6: Rename/Move | T6: Delete | U6: Move | V6: New | W6: Rename | X6: Rename/Move
A7: MGF | B7: 50 | C7: 48 | D7: 192 | E7: 273 | F7: 116 | G7: 679 | H7: 5 | I7: 43 | J7: 20 | K7: 65 | L7: 7 | M7: 140 | O7: 23 | P7: 29 | Q7: 46 | R7: 4 | S7: 102 | U7: 15 | V7: 23 | W7: 54 | X7: 1 | Y7: 93 | Z7: 1014
A8: LS | B8: 9 | C8: 374 | D8: 95 | E8: 164 | F8: 18 | G8: 660 | H8: 2 | I8: 77 | J8: 30 | K8: 96 | L8: 22 | M8: 227 | O8: 403 | P8: 81 | Q8: 82 | S8: 566 | U8: 245 | V8: 20 | W8: 68 | X8: 4 | Y8: 337 | Z8: 1790
A9: HC | B9: 5 | C9: 1 | D9: 21 | E9: 14 | F9: 8 | G9: 49 | H9: 1 | I9: 1 | J9: 5 | K9: 12 | M9: 19 | N9: 14 | O9: 8 | P9: 5 | Q9: 8 | R9: 1 | S9: 36 | T9: 7 | U9: 11 | V9: 3 | W9: 3 | Y9: 24 | Z9: 128
A10: EL | B10: 14 | D10: 105 | E10: 158 | F10: 22 | G10: 299 | H10: 20 | I10: 4 | J10: 26 | K10: 529 | L10: 4 | M10: 583 | O10: 4 | P10: 15 | Q10: 1 | S10: 20 | U10: 67 | V10: 13 | W10: 3 | X10: 1 | Y10: 84 | Z10: 986
A11: Grand Total | B11: 78 | C11: 423 | D11: 413 | E11: 609 | F11: 164 | G11: 1687 | H11: 28 | I11: 125 | J11: 81 | K11: 702 | L11: 33 | M11: 969 | N11: 14 | O11: 438 | P11: 130 | Q11: 137 | R11: 5 | S11: 724 | T11: 7 | U11: 338 | V11: 59 | W11: 128 | X11: 6 | Y11: 538 | Z11: 3918
