Workbook

Sheet pvt
A1: STATUS
A3: Row Labels | B3: Count of Node
A4: FR8342498 | B4: 3
A5: ON TM1 | B5: 3
A6: FR8345021 | B6: 2
A7: ON TM1 | B7: 2
A8: FR8348206 | B8: 3
A9: ON TM1 | B9: 3
A10: Grand Total | B10: 8

Sheet Okey
A1: FR5208660 | B1: Ok
A2: FR5265964 | B2: Ok
A3: FR5266249 | B3: Ok
A4: FR5267957 | B4: Ok
A5: FR5267969 | B5: Ok
A6: FR5286834 | B6: Ok
A7: FR5068879 | B7: Ok
A8: FR5072548 | B8: Ok
A9: FR5082089 | B9: Ok
A10: FR5092977 | B10: Ok
A11: FR5099062 | B11: Ok
A12: FR5107986 | B12: Ok
... A350: FR8348206 | B350: ok

Sheet STUCT1
A1: No. | B1: Forecast? | C1: Ticket | D1: Node | E1: Name | F1: Parent | G1: Action | H1: STATUS | I1: STATUS Check | J1: Sector | K1: Comments | L1: SANITY | M1: Author
A2: 1 | B2: F1 | C2: FR8003901 | D2: IT08030000 | E2: MGF_(non-IT) | F2: G000000244 | G2: New | H2: =IFERROR(VLOOKUP(Table2[[#This Row], [Ticket]],Okey!A:B,2,0),"") -> ok | I2: ON TM1 | J2: MGF | M2: Joshua Cachola
A3: =1+A2 -> 2 | B3: F1 | C3: FR8003901 | D3: G000000850 | F3: G000000400 | G3: Move | H3: =IFERROR(VLOOKUP(Table2[[#This Row], [Ticket]],Okey!A:B,2,0),"") -> ok | I3: ON TM1 | J3: MGF | M3: Manuel Walther
A4: =1+A3 -> 3 | B4: F1 | C4: FR8003901 | D4: G000000927 | E4: NO USE | F4: G000000873 | G4: Rename/Move | H4: =IFERROR(VLOOKUP(Table2[[#This Row], [Ticket]],Okey!A:B,2,0),"") -> ok | I4: ON TM1 | J4: MGF | M4: Manuel Walther
A5: =1+A4 -> 4 | B5: F1 | C5: FR8003901 | D5: G000000928 | E5: NO USE | F5: G000000873 | G5: Rename/Move | H5: =IFERROR(VLOOKUP(Table2[[#This Row], [Ticket]],Okey!A:B,2,0),"") -> ok | I5: ON TM1 | J5: MGF | M5: Manuel Walther
A6: =1+A5 -> 5 | B6: F1 | C6: FR8003901 | D6: G000000849 | E6: NO USE | F6: G000000873 | G6: Rename/Move | H6: =IFERROR(VLOOKUP(Table2[[#This Row], [Ticket]],Okey!A:B,2,0),"") -> ok | I6: ON TM1 | J6: MGF | M6: Manuel Walther
A7: =1+A6 -> 6 | B7: F1 | C7: FR8003901 | D7: G000000851 | E7: NO USE | F7: G000000873 | G7: Rename/Move | H7: =IFERROR(VLOOKUP(Table2[[#This Row], [Ticket]],Okey!A:B,2,0),"") -> ok | I7: ON TM1 | J7: MGF | M7: Manuel Walther
A8: =1+A7 -> 7 | B8: F1 | C8: FR8003901 | D8: G000000847 | E8: SM-G Mirror CC Typ-C Equipment | G8: Rename | H8: =IFERROR(VLOOKUP(Table2[[#This Row], [Ticket]],Okey!A:B,2,0),"") -> ok | I8: ON TM1 | J8: MGF | M8: Manuel Walther
A9: =1+A8 -> 8 | B9: F1 | C9: FR8003901 | D9: G000000848 | E9: SM-G Mirror CC Typ-R Reimburs. (h alloc) | G9: Rename | H9: =IFERROR(VLOOKUP(Table2[[#This Row], [Ticket]],Okey!A:B,2,0),"") -> ok | I9: ON TM1 | J9: MGF | M9: Manuel Walther
A10: =1+A9 -> 9 | B10: F1 | C10: FR8003901 | D10: G000000929 | E10: NO USE | G10: Rename | H10: =IFERROR(VLOOKUP(Table2[[#This Row], [Ticket]],Okey!A:B,2,0),"") -> ok | I10: ON TM1 | J10: MGF | M10: Manuel Walther
A11: =1+A10 -> 10 | B11: F1 | C11: FR8003901 | D11: G000000930 | E11: NO USE | G11: Rename | H11: =IFERROR(VLOOKUP(Table2[[#This Row], [Ticket]],Okey!A:B,2,0),"") -> ok | I11: ON TM1 | J11: MGF | M11: Manuel Walther
A12: =1+A11 -> 11 | B12: F1 | C12: FR8003901 | D12: G000000931 | E12: NO USE | G12: Rename | H12: =IFERROR(VLOOKUP(Table2[[#This Row], [Ticket]],Okey!A:B,2,0),"") -> ok | I12: ON TM1 | J12: MGF | M12: Manuel Walther
A13: =1+A12 -> 12 | B13: F1 | C13: FR8003901 | D13: G000000926 | E13: NO USE | G13: Rename | H13: =IFERROR(VLOOKUP(Table2[[#This Row], [Ticket]],Okey!A:B,2,0),"") -> ok | I13: ON TM1 | J13: MGF | M13: Manuel Walther
A14: =1+A13 -> 13 | B14: F1 | C14: FR8003901 | D14: G000000852 | E14: NO USE | G14: Rename | H14: =IFERROR(VLOOKUP(Table2[[#This Row], [Ticket]],Okey!A:B,2,0),"") -> ok | I14: ON TM1 | J14: MGF | M14: Manuel Walther
A15: =1+A14 -> 14 | B15: F1 | C15: FR8003901 | D15: G000000935 | E15: NO USE | G15: Rename | H15: =IFERROR(VLOOKUP(Table2[[#This Row], [Ticket]],Okey!A:B,2,0),"") -> ok | I15: ON TM1 | J15: MGF | M15: Manuel Walther
A16: =1+A15 -> 15 | B16: F1 | C16: FR8003901 | D16: G000000936 | E16: NO USE | G16: Rename | H16: =IFERROR(VLOOKUP(Table2[[#This Row], [Ticket]],Okey!A:B,2,0),"") -> ok | I16: ON TM1 | J16: MGF | M16: Manuel Walther
A17: =1+A16 -> 16 | B17: F1 | C17: FR8003901 | D17: G000000937 | E17: NO USE | G17: Rename | H17: =IFERROR(VLOOKUP(Table2[[#This Row], [Ticket]],Okey!A:B,2,0),"") -> ok | I17: ON TM1 | J17: MGF | M17: Manuel Walther
A18: =1+A17 -> 17 | B18: F1 | C18: FR8003901 | D18: G000000938 | E18: NO USE | G18: Rename | H18: =IFERROR(VLOOKUP(Table2[[#This Row], [Ticket]],Okey!A:B,2,0),"") -> ok | I18: ON TM1 | J18: MGF | M18: Manuel Walther
A19: =1+A18 -> 18 | B19: F1 | C19: FR8003901 | D19: G000000939 | E19: NO USE | G19: Rename | H19: =IFERROR(VLOOKUP(Table2[[#This Row], [Ticket]],Okey!A:B,2,0),"") -> ok | I19: ON TM1 | J19: MGF | M19: Manuel Walther
A20: =1+A19 -> 19 | B20: F1 | C20: FR8003901 | D20: G000000940 | E20: NO USE | G20: Rename | H20: =IFERROR(VLOOKUP(Table2[[#This Row], [Ticket]],Okey!A:B,2,0),"") -> ok | I20: ON TM1 | J20: MGF | M20: Manuel Walther
A21: =1+A20 -> 20 | B21: F1 | C21: FR8026550 | D21: RDC0000095 | F21: H000004396 | G21: Move | H21: =IFERROR(VLOOKUP(Table2[[#This Row], [Ticket]],Okey!A:B,2,0),"") -> ok | I21: ON TM1 | J21: MGF | M21: Erjo Miguel Tagle
A22: =1+A21 -> 21 | B22: F1 | C22: FR8025258 | D22: H000004863 | E22: SCALA_1248 A350 | F22: H000000726 | G22: New | H22: =IFERROR(VLOOKUP(Table2[[#This Row], [Ticket]],Okey!A:B,2,0),"") -> ok | I22: ON TM1 | J22: MGF | M22: Erjo Miguel Tagle
A23: =1+A22 -> 22 | B23: F1 | C23: FR8025258 | D23: H000004864 | E23: SCALA_1248 A351 | F23: H000000802 | G23: New | H23: =IFERROR(VLOOKUP(Table2[[#This Row], [Ticket]],Okey!A:B,2,0),"") -> ok | I23: ON TM1 | J23: MGF | M23: Erjo Miguel Tagle
A24: =1+A23 -> 23 | B24: F1 | C24: FR8025258 | D24: H000004865 | E24: SCALA_1248 A353 | F24: H000000802 | G24: New | H24: =IFERROR(VLOOKUP(Table2[[#This Row], [Ticket]],Okey!A:B,2,0),"") -> ok | I24: ON TM1 | J24: MGF | M24: Erjo Miguel Tagle
A25: =1+A24 -> 24 | B25: F1 | C25: FR8025258 | D25: RDC0000095 | F25: H000004396 | G25: Move | H25: =IFERROR(VLOOKUP(Table2[[#This Row], [Ticket]],Okey!A:B,2,0),"") -> ok | I25: ON TM1 | J25: MGF | M25: Erjo Miguel Tagle
A26: =1+A25 -> 25 | B26: F1 | C26: FR8068790 | D26: H000004866 | E26: MERCK SERONO ITALY - BARI (CCH) | F26: H000000471 | G26: New | H26: =IFERROR(VLOOKUP(Table2[[#This Row], [Ticket]],Okey!A:B,2,0),"") -> ok | I26: ON TM1 | J26: HC | M26: Murilo Barbosa
A27: =1+A26 -> 26 | B27: F1 | C27: FR8068790 | D27: H000004867 | E27: 1250BA - OPERATIONS | F27: H000004866 | G27: New | H27: =IFERROR(VLOOKUP(Table2[[#This Row], [Ticket]],Okey!A:B,2,0),"") -> ok | I27: ON TM1 | J27: HC | M27: Murilo Barbosa
A28: =1+A27 -> 27 | B28: F1 | C28: FR8068790 | D28: H000004868 | E28: 1250BA - OPERATIONS SUPPORT SERVICES | F28: H000004866 | G28: New | H28: =IFERROR(VLOOKUP(Table2[[#This Row], [Ticket]],Okey!A:B,2,0),"") -> ok | I28: ON TM1 | J28: HC | M28: Murilo Barbosa
A29: =1+A28 -> 28 | B29: F1 | C29: FR8068790 | D29: H000004869 | E29: 1250BA - SITE INFRASTRUCTURE | F29: H000004866 | G29: New | H29: =IFERROR(VLOOKUP(Table2[[#This Row], [Ticket]],Okey!A:B,2,0),"") -> ok | I29: ON TM1 | J29: HC | M29: Murilo Barbosa
A30: =1+A29 -> 29 | B30: F1 | C30: FR8068790 | D30: H000004870 | E30: 1250BA - QUALITY | F30: H000004866 | G30: New | H30: =IFERROR(VLOOKUP(Table2[[#This Row], [Ticket]],Okey!A:B,2,0),"") -> ok | I30: ON TM1 | J30: HC | M30: Murilo Barbosa
A31: =1+A30 -> 30 | B31: F1 | C31: FR8068790 | D31: H000004871 | E31: 1250BA - OTHERS | F31: H000004866 | G31: New | H31: =IFERROR(VLOOKUP(Table2[[#This Row], [Ticket]],Okey!A:B,2,0),"") -> ok | I31: ON TM1 | J31: HC | M31: Murilo Barbosa
A32: =1+A31 -> 31 | B32: F1 | C32: FR8068790 | D32: H000004872 | E32: 1250BA - MANUFACTURING | F32: H000004867 | G32: New | H32: =IFERROR(VLOOKUP(Table2[[#This Row], [Ticket]],Okey!A:B,2,0),"") -> ok | I32: ON TM1 | J32: HC | M32: Murilo Barbosa
A33: =1+A32 -> 32 | B33: F1 | C33: FR8068790 | D33: H000004873 | E33: 1250BA - PACKAGING | F33: H000004867 | G33: New | H33: =IFERROR(VLOOKUP(Table2[[#This Row], [Ticket]],Okey!A:B,2,0),"") -> ok | I33: ON TM1 | J33: HC | M33: Murilo Barbosa
A34: =1+A33 -> 33 | B34: F1 | C34: FR8068790 | D34: H000004874 | E34: 1250BA - MAINTENANCE AND ENGINEERING | F34: H000004868 | G34: New | H34: =IFERROR(VLOOKUP(Table2[[#This Row], [Ticket]],Okey!A:B,2,0),"") -> ok | I34: ON TM1 | J34: HC | M34: Murilo Barbosa
A35: =1+A34 -> 34 | B35: F1 | C35: FR8068790 | D35: H000004875 | E35: 1250BA - SUPPLY AND PLANNING | F35: H000004868 | G35: New | H35: =IFERROR(VLOOKUP(Table2[[#This Row], [Ticket]],Okey!A:B,2,0),"") -> ok | I35: ON TM1 | J35: HC | M35: Murilo Barbosa
A36: =1+A35 -> 35 | B36: F1 | C36: FR8068790 | D36: H000004876 | E36: 1250BA - SITE SERVICES | F36: H000004868 | G36: New | H36: =IFERROR(VLOOKUP(Table2[[#This Row], [Ticket]],Okey!A:B,2,0),"") -> ok | I36: ON TM1 | J36: HC | M36: Murilo Barbosa
A37: =1+A36 -> 36 | B37: F1 | C37: FR8068790 | D37: H000004877 | E37: 1250BA - MANUFACTURING FACILITIES | F37: H000004869 | G37: New | H37: =IFERROR(VLOOKUP(Table2[[#This Row], [Ticket]],Okey!A:B,2,0),"") -> ok | I37: ON TM1 | J37: HC | M37: Murilo Barbosa
... A53: =1+A52 -> 52 | B53: F1 | C53: FR8078176 | D53: IT06042600 | E53: EF-DS-TIX Special Projects | F53: G000001461 | G53: New | H53: =IFERROR(VLOOKUP(Table2[[#This Row], [Ticket]],Okey!A:B,2,0),"") -> ok | I53: ON TM1 | J53: MGF | M53: Jay-R Lizardo
A54: =1+A53 -> 53 | B54: F1 | C54: FR8089834 | D54: G000000416 | E54: SM-RG Restaurants & Catering | G54: Rename | H54: =IFERROR(VLOOKUP(Table2[[#This Row], [Ticket]],Okey!A:B,2,0),"") -> ok | I54: ON TM1 | J54: HC
A55: =1+A54 -> 54 | B55: F1 | C55: FR8089834 | D55: G000000882 | E55: SM-RG Catering & Ursprung | G55: Rename | H55: =IFERROR(VLOOKUP(Table2[[#This Row], [Ticket]],Okey!A:B,2,0),"") -> ok | I55: ON TM1 | J55: HC
A56: =1+A55 -> 55 | B56: F1 | C56: FR8110672 | D56: P000001381 | E56: Discontinued/Divested Sites | F56: P000000578 | G56: New | H56: =IFERROR(VLOOKUP(Table2[[#This Row], [Ticket]],Okey!A:B,2,0),"") -> ok | I56: ON TM1 | J56: EL | M56: John Rowie Del Rosario
A57: =1+A56 -> 56 | B57: F1 | C57: FR8110672 | D57: P000001382 | E57: Customer Supply Management | F57: P000000467 | G57: New | H57: =IFERROR(VLOOKUP(Table2[[#This Row], [Ticket]],Okey!A:B,2,0),"") -> ok | I57: ON TM1 | J57: EL | M57: John Rowie Del Rosario
A58: =1+A57 -> 57 | B58: F1 | C58: FR8110672 | D58: P000001383 | E58: Supply Planning Asia 1 (TW & CN) | F58: P000000467 | G58: New | H58: =IFERROR(VLOOKUP(Table2[[#This Row], [Ticket]],Okey!A:B,2,0),"") -> ok | I58: ON TM1 | J58: EL | M58: John Rowie Del Rosario
A59: =1+A58 -> 58 | B59: F1 | C59: FR8110672 | D59: P000001384 | E59: Supply Planning Asia 2 (KR & JP) | F59: P000000467 | G59: New | H59: =IFERROR(VLOOKUP(Table2[[#This Row], [Ticket]],Okey!A:B,2,0),"") -> ok | I59: ON TM1 | J59: EL | M59: John Rowie Del Rosario
A60: =1+A59 -> 59 | B60: F1 | C60: FR8110672 | D60: P000001385 | E60: Supply Planning Europe | F60: P000000467 | G60: New | H60: =IFERROR(VLOOKUP(Table2[[#This Row], [Ticket]],Okey!A:B,2,0),"") -> ok | I60: ON TM1 | J60: EL | M60: John Rowie Del Rosario
A61: =1+A60 -> 60 | B61: F1 | C61: FR8110672 | D61: P000001386 | E61: Supply Planning US | F61: P000000467 | G61: New | H61: =IFERROR(VLOOKUP(Table2[[#This Row], [Ticket]],Okey!A:B,2,0),"") -> ok | I61: ON TM1 | J61: EL | M61: John Rowie Del Rosario
A62: =1+A61 -> 61 | B62: F1 | C62: FR8110672 | D62: P000001387 | E62: S&OP & SPOC Form. & Optronics | F62: P000000467 | G62: New | H62: =IFERROR(VLOOKUP(Table2[[#This Row], [Ticket]],Okey!A:B,2,0),"") -> ok | I62: ON TM1 | J62: EL | M62: John Rowie Del Rosario
A63: =1+A62 -> 62 | B63: F1 | C63: FR8110672 | D63: P000001388 | E63: S&OP & SPOC Spec Gas & Thin Films | F63: P000000467 | G63: New | H63: =IFERROR(VLOOKUP(Table2[[#This Row], [Ticket]],Okey!A:B,2,0),"") -> ok | I63: ON TM1 | J63: EL | M63: John Rowie Del Rosario
A64: =1+A63 -> 63 | B64: F1 | C64: FR8110672 | D64: P000001389 | E64: Supply Chain Enablement | F64: P000000467 | G64: New | H64: =IFERROR(VLOOKUP(Table2[[#This Row], [Ticket]],Okey!A:B,2,0),"") -> ok | I64: ON TM1 | J64: EL | M64: John Rowie Del Rosario
A65: =1+A64 -> 64 | B65: F1 | C65: FR8110672 | D65: P000001390 | E65: Global Synthesis & Purification Quality | F65: P000000483 | G65: New | H65: =IFERROR(VLOOKUP(Table2[[#This Row], [Ticket]],Okey!A:B,2,0),"") -> ok | I65: ON TM1 | J65: EL | M65: John Rowie Del Rosario
A66: =1+A65 -> 65 | B66: F1 | C66: FR8110672 | D66: P000001391 | E66: Global Formulations & Optronics Quality | F66: P000000483 | G66: New | H66: =IFERROR(VLOOKUP(Table2[[#This Row], [Ticket]],Okey!A:B,2,0),"") -> ok | I66: ON TM1 | J66: EL | M66: John Rowie Del Rosario
A67: =1+A66 -> 66 | B67: F1 | C67: FR8110672 | D67: P000001392 | E67: Global Supply Chain Quality | F67: P000000483 | G67: New | H67: =IFERROR(VLOOKUP(Table2[[#This Row], [Ticket]],Okey!A:B,2,0),"") -> ok | I67: ON TM1 | J67: EL | M67: John Rowie Del Rosario
... A90: =1+A89 -> 89 | B90: F1 | C90: FR8110672 | D90: P000001415 | E90: Syn. & Purif. US Sites | F90: P000001412 | G90: New | H90: =IFERROR(VLOOKUP(Table2[[#This Row], [Ticket]],Okey!A:B,2,0),"") -> ok | I90: ON TM1 | J90: EL | M90: John Rowie Del Rosario
A91: =1+A90 -> 90 | B91: F1 | C91: FR8110672 | D91: P000000494 | F91: P000000555 | G91: Move | H91: =IFERROR(VLOOKUP(Table2[[#This Row], [Ticket]],Okey!A:B,2,0),"") -> ok | I91: ON TM1 | J91: EL | M91: John Rowie Del Rosario
A92: =1+A91 -> 91 | B92: F1 | C92: FR8110672 | D92: P000000259 | F92: P000000642 | G92: Move | H92: =IFERROR(VLOOKUP(Table2[[#This Row], [Ticket]],Okey!A:B,2,0),"") -> ok | I92: ON TM1 | J92: EL | M92: John Rowie Del Rosario
A93: =1+A92 -> 92 | B93: F1 | C93: FR8110672 | D93: P000000269 | F93: P000000642 | G93: Move | H93: =IFERROR(VLOOKUP(Table2[[#This Row], [Ticket]],Okey!A:B,2,0),"") -> ok | I93: ON TM1 | J93: EL | M93: John Rowie Del Rosario
A94: =1+A93 -> 93 | B94: F1 | C94: FR8110672 | D94: P000000466 | F94: P000000000 | G94: Move | H94: =IFERROR(VLOOKUP(Table2[[#This Row], [Ticket]],Okey!A:B,2,0),"") -> ok | I94: ON TM1 | J94: EL | M94: John Rowie Del Rosario
A95: =1+A94 -> 94 | B95: F1 | C95: FR8110672 | D95: P000000087 | F95: P000001381 | G95: Move | H95: =IFERROR(VLOOKUP(Table2[[#This Row], [Ticket]],Okey!A:B,2,0),"") -> ok | I95: ON TM1 | J95: EL | M95: John Rowie Del Rosario
A96: =1+A95 -> 95 | B96: F1 | C96: FR8110672 | D96: P000000526 | F96: P000000578 | G96: Move | H96: =IFERROR(VLOOKUP(Table2[[#This Row], [Ticket]],Okey!A:B,2,0),"") -> ok | I96: ON TM1 | J96: EL | M96: John Rowie Del Rosario
A97: =1+A96 -> 96 | B97: F1 | C97: FR8110672 | D97: P000000513 | F97: P000000578 | G97: Move | H97: =IFERROR(VLOOKUP(Table2[[#This Row], [Ticket]],Okey!A:B,2,0),"") -> ok | I97: ON TM1 | J97: EL | M97: John Rowie Del Rosario
A98: =1+A97 -> 97 | B98: F1 | C98: FR8110672 | D98: P000000520 | F98: P000000578 | G98: Move | H98: =IFERROR(VLOOKUP(Table2[[#This Row], [Ticket]],Okey!A:B,2,0),"") -> ok | I98: ON TM1 | J98: EL | M98: John Rowie Del Rosario
A99: =1+A98 -> 98 | B99: F1 | C99: FR8110672 | D99: P000000522 | F99: P000000578 | G99: Move | H99: =IFERROR(VLOOKUP(Table2[[#This Row], [Ticket]],Okey!A:B,2,0),"") -> ok | I99: ON TM1 | J99: EL | M99: John Rowie Del Rosario
A100: =1+A99 -> 99 | B100: F1 | C100: FR8110672 | D100: P000001171 | F100: P000000522 | G100: Move | H100: =IFERROR(VLOOKUP(Table2[[#This Row], [Ticket]],Okey!A:B,2,0),"") -> ok | I100: ON TM1 | J100: EL | M100: John Rowie Del Rosario
A101: =1+A100 -> 100 | B101: F1 | C101: FR8110672 | D101: P000000506 | F101: P000000467 | G101: Move | H101: =IFERROR(VLOOKUP(Table2[[#This Row], [Ticket]],Okey!A:B,2,0),"") -> ok | I101: ON TM1 | J101: EL | M101: John Rowie Del Rosario
A102: =1+A101 -> 101 | B102: F1 | C102: FR8110672 | D102: P000001280 | F102: P000000467 | G102: Move | H102: =IFERROR(VLOOKUP(Table2[[#This Row], [Ticket]],Okey!A:B,2,0),"") -> ok | I102: ON TM1 | J102: EL | M102: John Rowie Del Rosario
... A147: =1+A146 -> 146 | B147: F1 | C147: FR8110672 | D147: P000000149 | F147: P000001412 | G147: Move | H147: =IFERROR(VLOOKUP(Table2[[#This Row], [Ticket]],Okey!A:B,2,0),"") -> ok | I147: ON TM1 | J147: EL | M147: John Rowie Del Rosario
A148: =1+A147 -> 147 | B148: F1 | C148: FR8110672 | D148: P000001280 | E148: Supply Planning & S&OP DS&S | G148: Rename | H148: =IFERROR(VLOOKUP(Table2[[#This Row], [Ticket]],Okey!A:B,2,0),"") -> ok | I148: ON TM1 | J148: EL | M148: John Rowie Del Rosario
A149: =1+A148 -> 148 | B149: F1 | C149: FR8110672 | D149: P000000521 | E149: Japan Tolling incl. PHPS Ops | G149: Rename | H149: =IFERROR(VLOOKUP(Table2[[#This Row], [Ticket]],Okey!A:B,2,0),"") -> ok | I149: ON TM1 | J149: EL | M149: John Rowie Del Rosario
A150: =1+A149 -> 149 | B150: F1 | C150: FR8110672 | D150: P000000486 | E150: Global Customer Quality | G150: Rename | H150: =IFERROR(VLOOKUP(Table2[[#This Row], [Ticket]],Okey!A:B,2,0),"") -> ok | I150: ON TM1 | J150: EL | M150: John Rowie Del Rosario
A151: =1+A150 -> 150 | B151: F1 | C151: FR8110672 | D151: P000000488 | E151: Global Process Quality | G151: Rename | H151: =IFERROR(VLOOKUP(Table2[[#This Row], [Ticket]],Okey!A:B,2,0),"") -> ok | I151: ON TM1 | J151: EL | M151: John Rowie Del Rosario
A152: =1+A151 -> 151 | B152: F1 | C152: FR8110672 | D152: P000000484 | E152: EL-SC-Q Proj. & Program Mgmt | G152: Rename | H152: =IFERROR(VLOOKUP(Table2[[#This Row], [Ticket]],Okey!A:B,2,0),"") -> ok | I152: ON TM1 | J152: EL | M152: John Rowie Del Rosario
A153: =1+A152 -> 152 | B153: F1 | C153: FR8118359 | D153: G000001461 | F153: G000000272 | G153: Move | H153: =IFERROR(VLOOKUP(Table2[[#This Row], [Ticket]],Okey!A:B,2,0),"") -> ok | I153: ON TM1 | J153: MGF | M153: Jay-R Lizardo
A154: =1+A153 -> 153 | B154: F1 | C154: FR8131311 | D154: H000004892 | E154: MERCK BRAZIL - RIO (CCH) | F154: H000000544 | G154: New | H154: =IFERROR(VLOOKUP(Table2[[#This Row], [Ticket]],Okey!A:B,2,0),"") -> ok | I154: ON TM1 | J154: HC | M154: Peter Souza
A155: =1+A154 -> 154 | B155: F1 | C155: FR8131311 | D155: H000004893 | E155: 1227RI - OPERATIONS | F155: H000004892 | G155: New | H155: =IFERROR(VLOOKUP(Table2[[#This Row], [Ticket]],Okey!A:B,2,0),"") -> ok | I155: ON TM1 | J155: HC | M155: Peter Souza
A156: =1+A155 -> 155 | B156: F1 | C156: FR8131311 | D156: H000004894 | E156: 1227RI - OPERATIONS SUPPORT SERVICES | F156: H000004892 | G156: New | H156: =IFERROR(VLOOKUP(Table2[[#This Row], [Ticket]],Okey!A:B,2,0),"") -> ok | I156: ON TM1 | J156: HC | M156: Peter Souza
A157: =1+A156 -> 156 | B157: F1 | C157: FR8131311 | D157: H000004895 | E157: 1227RI - SITE INFRASTRUCTURE | F157: H000004892 | G157: New | H157: =IFERROR(VLOOKUP(Table2[[#This Row], [Ticket]],Okey!A:B,2,0),"") -> ok | I157: ON TM1 | J157: HC | M157: Peter Souza
A158: =1+A157 -> 157 | B158: F1 | C158: FR8131311 | D158: H000004896 | E158: 1227RI - QUALITY | F158: H000004892 | G158: New | H158: =IFERROR(VLOOKUP(Table2[[#This Row], [Ticket]],Okey!A:B,2,0),"") -> ok | I158: ON TM1 | J158: HC | M158: Peter Souza
A159: =1+A158 -> 158 | B159: F1 | C159: FR8131311 | D159: H000004897 | E159: 1227RI - OTHERS | F159: H000004892 | G159: New | H159: =IFERROR(VLOOKUP(Table2[[#This Row], [Ticket]],Okey!A:B,2,0),"") -> ok | I159: ON TM1 | J159: HC | M159: Peter Souza
A160: =1+A159 -> 159 | B160: F1 | C160: FR8131311 | D160: H000004898 | E160: 1227RI - MANUFACTURING | F160: H000004893 | G160: New | H160: =IFERROR(VLOOKUP(Table2[[#This Row], [Ticket]],Okey!A:B,2,0),"") -> ok | I160: ON TM1 | J160: HC | M160: Peter Souza
A161: =1+A160 -> 160 | B161: F1 | C161: FR8131311 | D161: H000004899 | E161: 1227RI - PACKAGING | F161: H000004893 | G161: New | H161: =IFERROR(VLOOKUP(Table2[[#This Row], [Ticket]],Okey!A:B,2,0),"") -> ok | I161: ON TM1 | J161: HC | M161: Peter Souza
A162: =1+A161 -> 161 | B162: F1 | C162: FR8131311 | D162: H000004900 | E162: 1227RI - MAINTENANCE AND ENGINEERING | F162: H000004894 | G162: New | H162: =IFERROR(VLOOKUP(Table2[[#This Row], [Ticket]],Okey!A:B,2,0),"") -> ok | I162: ON TM1 | J162: HC | M162: Peter Souza
A163: =1+A162 -> 162 | B163: F1 | C163: FR8131311 | D163: H000004901 | E163: 1227RI - SUPPLY AND PLANNING | F163: H000004894 | G163: New | H163: =IFERROR(VLOOKUP(Table2[[#This Row], [Ticket]],Okey!A:B,2,0),"") -> ok | I163: ON TM1 | J163: HC | M163: Peter Souza
A164: =1+A163 -> 163 | B164: F1 | C164: FR8131311 | D164: H000004902 | E164: 1227RI - SITE SERVICES | F164: H000004894 | G164: New | H164: =IFERROR(VLOOKUP(Table2[[#This Row], [Ticket]],Okey!A:B,2,0),"") -> ok | I164: ON TM1 | J164: HC | M164: Peter Souza
A165: =1+A164 -> 164 | B165: F1 | C165: FR8131311 | D165: H000004903 | E165: 1227RI - MANUFACTURING FACILITIES | F165: H000004895 | G165: New | H165: =IFERROR(VLOOKUP(Table2[[#This Row], [Ticket]],Okey!A:B,2,0),"") -> ok | I165: ON TM1 | J165: HC | M165: Peter Souza
... A178: =1+A177 -> 177 | B178: F1 | C178: FR8131311 | D178: H000004916 | E178: 1227RI - MCC | F178: H000004907 | G178: New | H178: =IFERROR(VLOOKUP(Table2[[#This Row], [Ticket]],Okey!A:B,2,0),"") -> ok | I178: ON TM1 | J178: HC | M178: Peter Souza
A179: =1+A178 -> 178 | B179: F1 | C179: FR8131311 | D179: H000004913 | F179: H000004908 | G179: Move | H179: =IFERROR(VLOOKUP(Table2[[#This Row], [Ticket]],Okey!A:B,2,0),"") -> ok | I179: ON TM1 | J179: HC | M179: Peter Souza
A180: =1+A179 -> 179 | B180: F1 | C180: FR8131311 | D180: H000004914 | F180: H000004908 | G180: Move | H180: =IFERROR(VLOOKUP(Table2[[#This Row], [Ticket]],Okey!A:B,2,0),"") -> ok | I180: ON TM1 | J180: HC | M180: Peter Souza
A181: =1+A180 -> 180 | B181: F1 | C181: FR8131311 | D181: H000004915 | F181: H000004908 | G181: Move | H181: =IFERROR(VLOOKUP(Table2[[#This Row], [Ticket]],Okey!A:B,2,0),"") -> ok | I181: ON TM1 | J181: HC | M181: Peter Souza
A182: =1+A181 -> 181 | B182: F1 | C182: FR8131311 | D182: H000004916 | F182: H000004908 | G182: Move | H182: =IFERROR(VLOOKUP(Table2[[#This Row], [Ticket]],Okey!A:B,2,0),"") -> ok | I182: ON TM1 | J182: HC | M182: Peter Souza
A183: =1+A182 -> 182 | B183: F1 | C183: FR8131311 | D183: H000004917 | E183: SCALA_1248 A350 | F183: H000000726 | G183: New | H183: =IFERROR(VLOOKUP(Table2[[#This Row], [Ticket]],Okey!A:B,2,0),"") -> ok | I183: ON TM1 | J183: HC | M183: Erjo Miguel Tagle
A184: =1+A183 -> 183 | B184: F1 | C184: FR8131311 | D184: H000004918 | E184: SCALA_1248 A351 | F184: H000000802 | G184: New | H184: =IFERROR(VLOOKUP(Table2[[#This Row], [Ticket]],Okey!A:B,2,0),"") -> ok | I184: ON TM1 | J184: HC | M184: Erjo Miguel Tagle
A185: =1+A184 -> 184 | B185: F1 | C185: FR8131311 | D185: H000004919 | E185: SCALA_1248 A353 | F185: H000000802 | G185: New | H185: =IFERROR(VLOOKUP(Table2[[#This Row], [Ticket]],Okey!A:B,2,0),"") -> ok | I185: ON TM1 | J185: HC | M185: Erjo Miguel Tagle
A186: =1+A185 -> 185 | B186: F1 | C186: FR8143873 | D186: H000004920 | E186: Business Unit RT | F186: H000003975 | G186: New | H186: =IFERROR(VLOOKUP(Table2[[#This Row], [Ticket]],Okey!A:B,2,0),"") -> ok | I186: ON TM1 | J186: HC | M186: Rayneil
A187: =1+A186 -> 186 | B187: F1 | C187: FR8143873 | D187: H000004921 | E187: Field Force RT | F187: H000004920 | G187: New | H187: =IFERROR(VLOOKUP(Table2[[#This Row], [Ticket]],Okey!A:B,2,0),"") -> ok | I187: ON TM1 | J187: HC | M187: Rayneil
A188: =1+A187 -> 187 | B188: F1 | C188: FR8143873 | D188: H000004922 | E188: ISS RT | F188: H000004920 | G188: New | H188: =IFERROR(VLOOKUP(Table2[[#This Row], [Ticket]],Okey!A:B,2,0),"") -> ok | I188: ON TM1 | J188: HC | M188: Rayneil
A189: =1+A188 -> 188 | B189: F1 | C189: FR8143873 | D189: H000004923 | E189: Sales Promotion Ogsiveo | F189: H000004920 | G189: New | H189: =IFERROR(VLOOKUP(Table2[[#This Row], [Ticket]],Okey!A:B,2,0),"") -> ok | I189: ON TM1 | J189: HC | M189: Rayneil
A190: =1+A189 -> 189 | B190: F1 | C190: FR8143873 | D190: H000004924 | E190: Sales Promotion Ezmekli | F190: H000004920 | G190: New | H190: =IFERROR(VLOOKUP(Table2[[#This Row], [Ticket]],Okey!A:B,2,0),"") -> ok | I190: ON TM1 | J190: HC | M190: Rayneil
A191: =1+A190 -> 190 | B191: F1 | C191: FR8143873 | D191: H000004925 | E191: Medical Dptm. RT | F191: H000003990 | G191: New | H191: =IFERROR(VLOOKUP(Table2[[#This Row], [Ticket]],Okey!A:B,2,0),"") -> ok | I191: ON TM1 | J191: HC | M191: Rayneil
A192: =1+A191 -> 191 | B192: F1 | C192: FR8143873 | D192: H000004926 | E192: Medical non R&D Ogsiveo | F192: H000003990 | G192: New | H192: =IFERROR(VLOOKUP(Table2[[#This Row], [Ticket]],Okey!A:B,2,0),"") -> ok | I192: ON TM1 | J192: HC | M192: Rayneil
A193: =1+A192 -> 192 | B193: F1 | C193: FR8143873 | D193: H000004927 | E193: Medical non R&D Ezmekli | F193: H000003990 | G193: New | H193: =IFERROR(VLOOKUP(Table2[[#This Row], [Ticket]],Okey!A:B,2,0),"") -> ok | I193: ON TM1 | J193: HC | M193: Rayneil
...

Sheet Sheet3
A1: 1000
A2: RDC0000142 | B2: Oligo Therapeutics | C2: X | D2: X | E2: X | F2: X | G2: X
A3: H000005088 | B3: Focus30 Global R&D | C3: X | D3: X | E3: X | F3: X | G3: X
A4: H000005089 | B4: Focus30 Local R&D | C4: X | D4: X | E4: X | F4: X | G4: X
A5: H000005018 | B5: 510.00 TEAD-No Program | C5: X | D5: X | E5: X | F5: X | G5: X
A6: H000005021 | B6: 550.00 VRK1 |No Program | C6: X | D6: X | E6: X | F6: X | G6: X
A10: 1000 | B10: Standard
A11: RDC0000130 | B11: RDC0000142
A12: H000000965 | B12: H000005088
A13: H000000965 | B13: H000005089
A14: G000000873 | B14: G000000889
A15: G000000873 | B15: G000001018
A16: H000004934 | B16: H000005016

Sheet Sheet2
A1: H000004992 | B1: H000004991
A2: H000004993 | B2: H000004991
A3: H000004994 | B3: H000004991
A4: H000005066 | B4: H000005048
A5: H000005067 | B5: H000005048
A6: H000005068 | B6: H000005048
A7: H000005069 | B7: H000005048
A8: H000005070 | B8: H000005048
A9: H000005071 | B9: H000005048
A10: H000005072 | B10: H000005048
A11: H000005073 | B11: H000005048
A12: H000005074 | B12: H000005048
... A27: L000009814 | B27: L000009795
A28: RDC0000142

Sheet Sheet1
A1: H000005066 | B1: US - Rare - Opinion Leader Laison | C1: H00000 | D1: 5066 | E1: =+C1&D1 -> H000005066 | M1: 1000 | V1: 1000
A2: H000005067 | B2: US - Rare GSI - Market Insights & Frcst | C2: H00000 | D2: =+D1+1 -> 5067 | E2: =+C2&D2 -> H000005067 | M2: H000005066 | N2: US - Rare - Opinion Leader Laison | O2: X | P2: X | Q2: X | R2: X | S2: X | V2: H000005048 | W2: H000005066
A3: H000005068 | B3: US - Rare OE&I - Cap. Bldg Eng. & Events | C3: H00000 | D3: =+D2+1 -> 5068 | E3: =+C3&D3 -> H000005068 | M3: H000005067 | N3: US - Rare GSI - Market Insights & Frcst | O3: X | P3: X | Q3: X | R3: X | S3: X | V3: H000005048 | W3: H000005067
A4: H000005069 | B4: US - Rare Diseases - GPA - Advocacy | C4: H00000 | D4: =+D3+1 -> 5069 | E4: =+C4&D4 -> H000005069 | M4: H000005068 | N4: US - Rare OE&I - Cap. Bldg Eng. & Events | O4: X | P4: X | Q4: X | R4: X | S4: X | V4: H000005048 | W4: H000005068
A5: H000005070 | B5: US - Rare Diseases - GPA - Govt Affairs | C5: H00000 | D5: =+D4+1 -> 5070 | E5: =+C5&D5 -> H000005070 | M5: H000005069 | N5: US - Rare Diseases - GPA - Advocacy | O5: X | P5: X | Q5: X | R5: X | S5: X | V5: H000005048 | W5: H000005069
A6: H000005071 | B6: US - Rare GPA - Innovative Med Policy | C6: H00000 | D6: =+D5+1 -> 5071 | E6: =+C6&D6 -> H000005071 | M6: H000005070 | N6: US - Rare Diseases - GPA - Govt Affairs | O6: X | P6: X | Q6: X | R6: X | S6: X | V6: H000005048 | W6: H000005070
A7: H000005072 | B7: US - Rare Diseases - Communications | C7: H00000 | D7: =+D6+1 -> 5072 | E7: =+C7&D7 -> H000005072 | M7: H000005071 | N7: US - Rare GPA - Innovative Med Policy | O7: X | P7: X | Q7: X | R7: X | S7: X | V7: H000005048 | W7: H000005071
A8: H000005073 | B8: US - Rare Diseases - New Product | C8: H00000 | D8: =+D7+1 -> 5073 | E8: =+C8&D8 -> H000005073 | M8: H000005072 | N8: US - Rare Diseases - Communications | O8: X | P8: X | Q8: X | R8: X | S8: X | V8: H000005048 | W8: H000005072
A9: H000005074 | B9: US - Rare Diseases - Hedge | C9: H00000 | D9: =+D8+1 -> 5074 | E9: =+C9&D9 -> H000005074 | M9: H000005073 | N9: US - Rare Diseases - New Product | O9: X | P9: X | Q9: X | R9: X | S9: X | V9: H000005048 | W9: H000005073
A10: H000005075 | B10: US - Rare Diseases - OE&I - Comm Ops | C10: H00000 | D10: =+D9+1 -> 5075 | E10: =+C10&D10 -> H000005075 | M10: H000005074 | N10: US - Rare Diseases - Hedge | O10: X | P10: X | Q10: X | R10: X | S10: X | V10: H000005048 | W10: H000005074
A11: H000005076 | B11: US - Rare Diseases - MAPS Value&Access | C11: H00000 | D11: =+D10+1 -> 5076 | E11: =+C11&D11 -> H000005076 | M11: H000005075 | N11: US - Rare Diseases - OE&I - Comm Ops | O11: X | P11: X | Q11: X | R11: X | S11: X | V11: H000005048 | W11: H000005075
A12: H000005077 | B12: US - Rare - MAPS Field Patient Svcs | C12: H00000 | D12: =+D11+1 -> 5077 | E12: =+C12&D12 -> H000005077 | M12: H000005076 | N12: US - Rare Diseases - MAPS Value&Access | O12: X | P12: X | Q12: X | R12: X | S12: X | V12: H000005048 | W12: H000005076
A13: H000005078 | B13: US - Rare Diseases - Medical Education | C13: H00000 | D13: =+D12+1 -> 5078 | E13: =+C13&D13 -> H000005078 | M13: H000005077 | N13: US - Rare - MAPS Field Patient Svcs | O13: X | P13: X | Q13: X | R13: X | S13: X | V13: H000005048 | W13: H000005077
... A22: H000005087 | B22: US - Rare Diseases - Samples | C22: H00000 | D22: =+D21+1 -> 5087 | E22: =+C22&D22 -> H000005087 | M22: H000005086 | N22: US - Rare Diseases - Studies | O22: X | P22: X | Q22: X | R22: X | S22: X | V22: H000005059 | W22: H000005086
M23: H000005087 | N23: US - Rare Diseases - Samples | O23: X | P23: X | Q23: X | R23: X | S23: X | V23: H000005059 | W23: H000005087
M24: H000005055 | N24: US - Rare Diseases - OE&I Data Strat | O24: X | P24: X | Q24: X | R24: X | S24: X
M25: L000009814 | N25: Cranbury 3PL WH -G | O25: X | P25: X | Q25: X | R25: X | S25: X

Sheet Names
A1: 1000
A2: G000000951 | B2: SC Gebaeude Electronics DA | C2: X | D2: X | E2: X | F2: X | G2: X
A3: G000000531 | B3: Freiflaechen und allg. Infrastruktur | C3: X | D3: X | E3: X | F3: X | G3: X
A4: G000000532 | B4: Freiflaechen und Parken | C4: X | D4: X | E4: X | F4: X | G4: X
A5: G000000945 | B5: Allgemeine Infrastruktur | C5: X | D5: X | E5: X | F5: X | G5: X
A6: G000000089 | B6: SM-IE Energy Operations & Management | C6: X | D6: X | E6: X | F6: X | G6: X
A7: G000000472 | B7: SM-HI Ideenmanagement | C7: X | D7: X | E7: X | F7: X | G7: X
A8: L000013826 | B8: LW - Ecommerce Specialist | C8: X | D8: X | E8: X | F8: X | G8: X
A9: L000013827 | B9: LW - Global Digital Camp | C9: X | D9: X | E9: X | F9: X | G9: X
A10: L000013828 | B10: LW - Content Manager | C10: X | D10: X | E10: X | F10: X | G10: X
A11: L000013829 | B11: LW - Mark&Digit Comm Spe | C11: X | D11: X | E11: X | F11: X | G11: X
A12: L000013830 | B12: Schnelldorf DF Operations CCV | C12: X | D12: X | E12: X | F12: X | G12: X
A13: L000013831 | B13: LS ERP Travel | C13: X | D13: X | E13: X | F13: X | G13: X
... A235: H000004395 | B235: IF-China & International exc GH | C235: X | D235: X | E235: X | F235: X | G235: X
A237: KR00
A238: G000000951 | B238: SC Gebaeude Electronics DA | C238: X
A239: G000000531 | B239: Freiflaechen und allg. Infrastruktur | C239: X
A240: G000000532 | B240: Freiflaechen und Parken | C240: X
A241: G000000945 | B241: Allgemeine Infrastruktur | C241: X
A242: G000000089 | B242: SM-IE Energy Operations & Management | C242: X
A243: G000000472 | B243: SM-HI Ideenmanagement | C243: X
A244: G000001265 | B244: GMR MBS Innovation & Data-Int.Automation | C244: X
A245: G000001211 | B245: GLW MBS FS&P PO-Perform.Mgmt &Compl. PO | C245: X
A246: G000001219 | B246: GMG MBS FS&P Ent.S.-Communication Serv. | C246: X
A247: G000000006 | B247: F79 CO - Group Controlling | C247: X
A248: G000000008 | B248: GK3 CO - Group Controlling (L2) | C248: X
A249: G000001287 | B249: GYG MBS Hub Bangalore - SLS Buss Operati | C249: X
... A388: P000000533 | B388: EL-TF Thin Film Commercial | C388: X

Sheet NEW NODES
A1: 1000 | D1: KR00
A2: L000013126 | B2: L000013826 | D2: G000000613 | E2: G000001359
A3: L000013126 | B3: L000013827 | D3: G000000622 | E3: G000001360
A4: L000013126 | B4: L000013828 | D4: G000000622 | E4: G000001361
A5: L000013126 | B5: L000013829 | D5: G000000622 | E5: G000001362
A6: L000012340 | B6: L000013830 | D6: G000000622 | E6: G000001363
A7: L000013799 | B7: L000013831 | D7: G000000622 | E7: G000001364
A8: L000009975 | B8: L000013832 | D8: G000000622 | E8: G000001365
A9: L000013451 | B9: L000013833 | D9: G000000622 | E9: G000001366
A10: L000013833 | B10: L000013834 | D10: G000000184 | E10: G000001367
A11: L000013833 | B11: L000013835 | D11: G000001367 | E11: G000001368
A12: L000013779 | B12: L000013836 | D12: G000001367 | E12: G000001369
A13: L000013854 | B13: L000013837 | D13: G000001368 | E13: G000001370
... A74: P000000554 | B74: P000001275 | D74: P000000748 | E74: P000001324
A75: P000000554 | B75: P000001276
A76: P000000554 | B76: P000001277
A77: P000001275 | B77: P000001278
A78: P000001275 | B78: P000001279
A79: P000001275 | B79: P000001280
A80: P000001275 | B80: P000001281
A81: P000001275 | B81: P000001282
A82: P000001276 | B82: P000001283
A83: P000001276 | B83: P000001284
A84: P000001276 | B84: P000001285
A85: P000001276 | B85: P000001286
A86: P000001276 | B86: P000001287
... A125: H000000172 | B125: H000004395

Sheet People
A1: Opened By | B1: Sector
A2: Joshua Cachola | B2: MGF
A3: Simone Oratovski | B3: HC
A4: Nicolas Trautmann | B4: MGF
A5: Henry Ifurung Jr. | B5: HC
A6: Phoebe Anne Fortaleza | B6: LS
A7: Joebeth Navarro | B7: HC
A8: Paul Kopp | B8: MGF
A9: Maureen Cardano | B9: HC
A10: Roland Earvin Combalicer | B10: HC
A11: Marcus Morowski | B11: MGF
A12: Megan Wang | B12: MGF
... A55: Hui Zhang | B55: LS

Sheet 2023
A1: No. | B1: Forecast? | C1: Ticket | D1: Node | E1: Name | F1: Parent | G1: Action | H1: STATUS | I1: STATUS Check | J1: Sector | K1: Comments | L1: SANITY | M1: Author
A2: 1 | B2: F1 | C2: FR5068879 | D2: L000011515 | F2: O000000009 | G2: Delete | H2: =IFERROR(VLOOKUP(Table2[[#This Row], [Ticket]],Okey!A:B,2,0),"") -> ok | I2: Closed | J2: =VLOOKUP(Table2[[#This Row], [Author]],People!A:B,2,0) -> MGF | M2: Phoebe Anne Fortaleza
A3: =1+A2 -> 2 | B3: F1 | C3: FR5068879 | D3: L000013398 | E3: BioVV - Quality & Regulatory -G | F3: L000006935 | G3: New | H3: =IFERROR(VLOOKUP(Table2[[#This Row], [Ticket]],Okey!A:B,2,0),"") -> ok | I3: Closed | J3: =VLOOKUP(Table2[[#This Row], [Author]],People!A:B,2,0) -> MGF | M3: Phoebe Anne Fortaleza
A4: =1+A3 -> 3 | B4: F1 | C4: FR5072548 | D4: G000000958 | F4: G000000955 | G4: Move | H4: =IFERROR(VLOOKUP(Table2[[#This Row], [Ticket]],Okey!A:B,2,0),"") -> ok | I4: Closed | J4: =VLOOKUP(Table2[[#This Row], [Author]],People!A:B,2,0) -> MGF | M4: Nadine Anic
A5: =1+A4 -> 4 | B5: F1 | C5: FR5072548 | D5: G000000959 | F5: G000000958 | G5: Move | H5: =IFERROR(VLOOKUP(Table2[[#This Row], [Ticket]],Okey!A:B,2,0),"") -> ok | I5: Closed | J5: =VLOOKUP(Table2[[#This Row], [Author]],People!A:B,2,0) -> MGF | M5: Nadine Anic
A6: =1+A5 -> 5 | B6: F1 | C6: FR5072548 | D6: G000000960 | F6: G000000958 | G6: Move | H6: =IFERROR(VLOOKUP(Table2[[#This Row], [Ticket]],Okey!A:B,2,0),"") -> ok | I6: Closed | J6: =VLOOKUP(Table2[[#This Row], [Author]],People!A:B,2,0) -> MGF | M6: Nadine Anic
A7: =1+A6 -> 6 | B7: F1 | C7: FR5072548 | D7: G000000961 | F7: G000000958 | G7: Move | H7: =IFERROR(VLOOKUP(Table2[[#This Row], [Ticket]],Okey!A:B,2,0),"") -> ok | I7: Closed | J7: =VLOOKUP(Table2[[#This Row], [Author]],People!A:B,2,0) -> MGF | M7: Nadine Anic
A8: =1+A7 -> 7 | B8: F1 | C8: FR5072548 | D8: G000000962 | F8: G000000958 | G8: Move | H8: =IFERROR(VLOOKUP(Table2[[#This Row], [Ticket]],Okey!A:B,2,0),"") -> ok | I8: Closed | J8: =VLOOKUP(Table2[[#This Row], [Author]],People!A:B,2,0) -> MGF | M8: Nadine Anic
A9: =1+A8 -> 8 | B9: F1 | C9: FR5072548 | D9: G000000963 | F9: G000000958 | G9: Move | H9: =IFERROR(VLOOKUP(Table2[[#This Row], [Ticket]],Okey!A:B,2,0),"") -> ok | I9: Closed | J9: =VLOOKUP(Table2[[#This Row], [Author]],People!A:B,2,0) -> MGF | M9: Nadine Anic
A10: =1+A9 -> 9 | B10: F1 | C10: FR5072548 | D10: G000000964 | F10: G000000958 | G10: Move | H10: =IFERROR(VLOOKUP(Table2[[#This Row], [Ticket]],Okey!A:B,2,0),"") -> ok | I10: Closed | J10: =VLOOKUP(Table2[[#This Row], [Author]],People!A:B,2,0) -> MGF | M10: Nadine Anic
A11: =1+A10 -> 10 | B11: F1 | C11: FR5072548 | D11: G000000965 | F11: G000000958 | G11: Move | H11: =IFERROR(VLOOKUP(Table2[[#This Row], [Ticket]],Okey!A:B,2,0),"") -> ok | I11: Closed | J11: =VLOOKUP(Table2[[#This Row], [Author]],People!A:B,2,0) -> MGF | M11: Nadine Anic
A12: =1+A11 -> 11 | B12: F1 | C12: FR5072548 | D12: G000000966 | F12: G000000955 | G12: Move | H12: =IFERROR(VLOOKUP(Table2[[#This Row], [Ticket]],Okey!A:B,2,0),"") -> ok | I12: Closed | J12: =VLOOKUP(Table2[[#This Row], [Author]],People!A:B,2,0) -> MGF | M12: Nadine Anic
A13: =1+A12 -> 12 | B13: F1 | C13: FR5072548 | D13: G000000967 | F13: G000000956 | G13: Move | H13: =IFERROR(VLOOKUP(Table2[[#This Row], [Ticket]],Okey!A:B,2,0),"") -> ok | I13: Closed | J13: =VLOOKUP(Table2[[#This Row], [Author]],People!A:B,2,0) -> MGF | M13: Nadine Anic
A14: =1+A13 -> 13 | B14: F1 | C14: FR5072548 | D14: G000000968 | F14: G000000967 | G14: Move | H14: =IFERROR(VLOOKUP(Table2[[#This Row], [Ticket]],Okey!A:B,2,0),"") -> ok | I14: Closed | J14: =VLOOKUP(Table2[[#This Row], [Author]],People!A:B,2,0) -> MGF | M14: Nadine Anic
A15: =1+A14 -> 14 | B15: F1 | C15: FR5072548 | D15: G000000969 | F15: G000000967 | G15: Move | H15: =IFERROR(VLOOKUP(Table2[[#This Row], [Ticket]],Okey!A:B,2,0),"") -> ok | I15: Closed | J15: =VLOOKUP(Table2[[#This Row], [Author]],People!A:B,2,0) -> MGF | M15: Nadine Anic
... A41: =1+A40 -> 40 | B41: F1 | C41: FR5072548 | D41: G000000995 | F41: G000000993 | G41: Move | H41: =IFERROR(VLOOKUP(Table2[[#This Row], [Ticket]],Okey!A:B,2,0),"") -> ok | I41: Closed | J41: =VLOOKUP(Table2[[#This Row], [Author]],People!A:B,2,0) -> #N/A | M41: Nadine Anic
A42: =1+A41 -> 41 | B42: F1 | C42: FR5082089 | D42: G000000461 | E42: SM-B Strategy Realization & Enablement | G42: Rename | H42: =IFERROR(VLOOKUP(Table2[[#This Row], [Ticket]],Okey!A:B,2,0),"") -> ok | I42: Closed | J42: =VLOOKUP(Table2[[#This Row], [Author]],People!A:B,2,0) -> #N/A | M42: Sybille Rogmans
A43: =1+A42 -> 42 | B43: F1 | C43: FR5082089 | D43: G000000462 | E43: SM-B Strategy Realization & Enablement | G43: Rename | H43: =IFERROR(VLOOKUP(Table2[[#This Row], [Ticket]],Okey!A:B,2,0),"") -> ok | I43: Closed | J43: =VLOOKUP(Table2[[#This Row], [Author]],People!A:B,2,0) -> #N/A | M43: Sybille Rogmans
A44: =1+A43 -> 43 | B44: F1 | C44: FR5082089 | D44: G000000463 | E44: SM-BB Business Excellence | G44: Rename | H44: =IFERROR(VLOOKUP(Table2[[#This Row], [Ticket]],Okey!A:B,2,0),"") -> ok | I44: Closed | J44: =VLOOKUP(Table2[[#This Row], [Author]],People!A:B,2,0) -> #N/A | M44: Sybille Rogmans
A45: =1+A44 -> 44 | B45: F1 | C45: FR5082089 | D45: G000000464 | E45: SM-BS Strategy Realization | G45: Rename | H45: =IFERROR(VLOOKUP(Table2[[#This Row], [Ticket]],Okey!A:B,2,0),"") -> ok | I45: Closed | J45: =VLOOKUP(Table2[[#This Row], [Author]],People!A:B,2,0) -> #N/A | M45: Sybille Rogmans
A46: =1+A45 -> 45 | B46: F1 | C46: FR5082089 | D46: G000000466 | E46: SM-BC Strategic Contracting | G46: Rename | H46: =IFERROR(VLOOKUP(Table2[[#This Row], [Ticket]],Okey!A:B,2,0),"") -> ok | I46: Closed | J46: =VLOOKUP(Table2[[#This Row], [Author]],People!A:B,2,0) -> #N/A | M46: Sybille Rogmans
A47: =1+A46 -> 46 | B47: F1 | C47: FR5082089 | D47: G000000470 | E47: SM-BQ dummy 6 | G47: Rename | H47: =IFERROR(VLOOKUP(Table2[[#This Row], [Ticket]],Okey!A:B,2,0),"") -> ok | I47: Closed | J47: =VLOOKUP(Table2[[#This Row], [Author]],People!A:B,2,0) -> #N/A | M47: Sybille Rogmans
A48: =1+A47 -> 47 | B48: F1 | C48: FR5082089 | D48: G000000473 | E48: SM-BD Data & Digital Enablement | G48: Rename | H48: =IFERROR(VLOOKUP(Table2[[#This Row], [Ticket]],Okey!A:B,2,0),"") -> ok | I48: Closed | J48: =VLOOKUP(Table2[[#This Row], [Author]],People!A:B,2,0) -> #N/A | M48: Sybille Rogmans
A49: =1+A48 -> 48 | B49: F1 | C49: FR5082089 | D49: G000000868 | E49: SM-BP People, Change & Comms | G49: Rename | H49: =IFERROR(VLOOKUP(Table2[[#This Row], [Ticket]],Okey!A:B,2,0),"") -> ok | I49: Closed | J49: =VLOOKUP(Table2[[#This Row], [Author]],People!A:B,2,0) -> #N/A | M49: Sybille Rogmans
A50: =1+A49 -> 49 | B50: F1 | C50: FR5082089 | D50: G000000471 | E50: SM-BQ Quality Management | F50: G000000470 | G50: Rename/Move | H50: =IFERROR(VLOOKUP(Table2[[#This Row], [Ticket]],Okey!A:B,2,0),"") -> ok | I50: Closed | J50: =VLOOKUP(Table2[[#This Row], [Author]],People!A:B,2,0) -> #N/A | M50: Sybille Rogmans
A51: =1+A50 -> 50 | B51: F1 | C51: FR5092977 | D51: G000000355 | E51: SM Site Management | G51: Rename | H51: =IFERROR(VLOOKUP(Table2[[#This Row], [Ticket]],Okey!A:B,2,0),"") -> ok | I51: Closed | J51: =VLOOKUP(Table2[[#This Row], [Author]],People!A:B,2,0) -> #N/A | M51: Nicolas Trautmann
A52: =1+A51 -> 51 | B52: F1 | C52: FR5092977 | D52: G000000359 | E52: SM-H Strategy & Transform. | G52: Rename | H52: =IFERROR(VLOOKUP(Table2[[#This Row], [Ticket]],Okey!A:B,2,0),"") -> ok | I52: Closed | J52: =VLOOKUP(Table2[[#This Row], [Author]],People!A:B,2,0) -> LS | M52: Nicolas Trautmann
A53: =1+A52 -> 52 | B53: F1 | C53: FR5092977 | D53: G000000365 | E53: SM-A Analytical Services | G53: Rename | H53: =IFERROR(VLOOKUP(Table2[[#This Row], [Ticket]],Okey!A:B,2,0),"") -> ok | I53: Closed | J53: =VLOOKUP(Table2[[#This Row], [Author]],People!A:B,2,0) -> LS | M53: Nicolas Trautmann
A54: =1+A53 -> 53 | B54: F1 | C54: FR5092977 | D54: G000000372 | E54: SM-E Engineering Services | G54: Rename | H54: =IFERROR(VLOOKUP(Table2[[#This Row], [Ticket]],Okey!A:B,2,0),"") -> ok | I54: Closed | J54: =VLOOKUP(Table2[[#This Row], [Author]],People!A:B,2,0) -> #N/A | M54: Nicolas Trautmann
A55: =1+A54 -> 54 | B55: F1 | C55: FR5092977 | D55: G000000410 | E55: SM-U | G55: Rename | H55: =IFERROR(VLOOKUP(Table2[[#This Row], [Ticket]],Okey!A:B,2,0),"") -> ok | I55: Closed | J55: =VLOOKUP(Table2[[#This Row], [Author]],People!A:B,2,0) -> #N/A | M55: Nicolas Trautmann
A56: =1+A55 -> 55 | B56: F1 | C56: FR5092977 | D56: G000000439 | E56: SM-Verrechnungen / Sachkosten | G56: Rename | H56: =IFERROR(VLOOKUP(Table2[[#This Row], [Ticket]],Okey!A:B,2,0),"") -> ok | I56: Closed | J56: =VLOOKUP(Table2[[#This Row], [Author]],People!A:B,2,0) -> #N/A | M56: Nicolas Trautmann
A57: =1+A56 -> 56 | B57: F1 | C57: FR5092977 | D57: G000000890 | E57: SM-HG Fluxum | G57: Rename | H57: =IFERROR(VLOOKUP(Table2[[#This Row], [Ticket]],Okey!A:B,2,0),"") -> ok | I57: Closed | J57: =VLOOKUP(Table2[[#This Row], [Author]],People!A:B,2,0) -> #N/A | M57: Nicolas Trautmann
A58: =1+A57 -> 57 | B58: F1 | C58: FR5092977 | D58: G000000360 | E58: SM-HF Future | G58: Rename | H58: =IFERROR(VLOOKUP(Table2[[#This Row], [Ticket]],Okey!A:B,2,0),"") -> ok | I58: Closed | J58: =VLOOKUP(Table2[[#This Row], [Author]],People!A:B,2,0) -> #N/A | M58: Nicolas Trautmann
A59: =1+A58 -> 58 | B59: F1 | C59: FR5092977 | D59: G000000361 | E59: DA Goes Global | G59: Rename | H59: =IFERROR(VLOOKUP(Table2[[#This Row], [Ticket]],Okey!A:B,2,0),"") -> ok | I59: Closed | J59: =VLOOKUP(Table2[[#This Row], [Author]],People!A:B,2,0) -> #N/A | M59: Nicolas Trautmann
A60: =1+A59 -> 59 | B60: F1 | C60: FR5092977 | D60: G000000362 | E60: SM-HM Marketing&Dialog | G60: Rename | H60: =IFERROR(VLOOKUP(Table2[[#This Row], [Ticket]],Okey!A:B,2,0),"") -> ok | I60: Closed | J60: =VLOOKUP(Table2[[#This Row], [Author]],People!A:B,2,0) -> #N/A | M60: Nicolas Trautmann
A61: =1+A60 -> 60 | B61: F1 | C61: FR5092977 | D61: G000000888 | E61: SM-HR HQ Relations & Mgmt of | G61: Rename | H61: =IFERROR(VLOOKUP(Table2[[#This Row], [Ticket]],Okey!A:B,2,0),"") -> ok | I61: Closed | J61: =VLOOKUP(Table2[[#This Row], [Author]],People!A:B,2,0) -> #N/A | M61: Nicolas Trautmann
A62: =1+A61 -> 61 | B62: F1 | C62: FR5092977 | D62: G000000889 | E62: SM-HP Plattforms | G62: Rename | H62: =IFERROR(VLOOKUP(Table2[[#This Row], [Ticket]],Okey!A:B,2,0),"") -> ok | I62: Closed | J62: =VLOOKUP(Table2[[#This Row], [Author]],People!A:B,2,0) -> #N/A | M62: Nicolas Trautmann
... A207: =1+A206 -> 206 | B207: F1 | C207: FR5092977 | D207: G000000416 | E207: SM-SCC Conference & Catering | G207: Rename | H207: =IFERROR(VLOOKUP(Table2[[#This Row], [Ticket]],Okey!A:B,2,0),"") -> ok | I207: Closed | J207: =VLOOKUP(Table2[[#This Row], [Author]],People!A:B,2,0) -> LS | M207: Nicolas Trautmann
A208: =1+A207 -> 207 | B208: F1 | C208: FR5099062 | D208: H000004191 | E208: Medical - Local R&D | F208: H000000447 | G208: New | H208: =IFERROR(VLOOKUP(Table2[[#This Row], [Ticket]],Okey!A:B,2,0),"") -> ok | I208: Closed | J208: =VLOOKUP(Table2[[#This Row], [Author]],People!A:B,2,0) -> LS | M208: Megan Wang
A209: =1+A208 -> 208 | B209: F1 | C209: FR5107986 | D209: H000000813 | E209: CMS International | G209: Rename | H209: =IFERROR(VLOOKUP(Table2[[#This Row], [Ticket]],Okey!A:B,2,0),"") -> ok | I209: Closed | J209: =VLOOKUP(Table2[[#This Row], [Author]],People!A:B,2,0) -> LS | M209: Marlon Abadia
A210: =1+A209 -> 209 | B210: F1 | C210: FR5107986 | D210: H000000814 | E210: CMS Clinical Biomarker & Tech. | G210: Rename | H210: =IFERROR(VLOOKUP(Table2[[#This Row], [Ticket]],Okey!A:B,2,0),"") -> ok | I210: Closed | J210: =VLOOKUP(Table2[[#This Row], [Author]],People!A:B,2,0) -> LS | M210: Marlon Abadia
A211: =1+A210 -> 210 | B211: F1 | C211: FR5107986 | D211: H000000899 | E211: CMS Data Sciences | G211: Rename | H211: =IFERROR(VLOOKUP(Table2[[#This Row], [Ticket]],Okey!A:B,2,0),"") -> ok | I211: Closed | J211: =VLOOKUP(Table2[[#This Row], [Author]],People!A:B,2,0) -> LS | M211: Marlon Abadia
A212: =1+A211 -> 211 | B212: F1 | C212: FR5107986 | D212: H000000815 | E212: CMS Quantitative Pharmacology | G212: Rename | H212: =IFERROR(VLOOKUP(Table2[[#This Row], [Ticket]],Okey!A:B,2,0),"") -> ok | I212: Closed | J212: =VLOOKUP(Table2[[#This Row], [Author]],People!A:B,2,0) -> LS | M212: Marlon Abadia
A213: =1+A212 -> 212 | B213: F1 | C213: FR5107986 | D213: H000000816 | E213: CMS Comp Diagnostics & Biomarker | F213: H000000906 | G213: Rename/Move | H213: =IFERROR(VLOOKUP(Table2[[#This Row], [Ticket]],Okey!A:B,2,0),"") -> ok | I213: Closed | J213: =VLOOKUP(Table2[[#This Row], [Author]],People!A:B,2,0) -> LS | M213: Marlon Abadia
A214: =1+A213 -> 213 | B214: F1 | C214: FR5107986 | D214: H000000818 | F214: H000000906 | G214: Move | H214: =IFERROR(VLOOKUP(Table2[[#This Row], [Ticket]],Okey!A:B,2,0),"") -> ok | I214: Closed | J214: =VLOOKUP(Table2[[#This Row], [Author]],People!A:B,2,0) -> LS | M214: Marlon Abadia
A215: =1+A214 -> 214 | B215: F1 | C215: FR5107986 | D215: H000000819 | E215: CMS Epideminology | F215: H000000906 | G215: Rename/Move | H215: =IFERROR(VLOOKUP(Table2[[#This Row], [Ticket]],Okey!A:B,2,0),"") -> ok | I215: Closed | J215: =VLOOKUP(Table2[[#This Row], [Author]],People!A:B,2,0) -> LS | M215: Marlon Abadia
A216: =1+A215 -> 215 | B216: F1 | C216: FR5107986 | D216: H000004192 | E216: CMS International | F216: H000000906 | G216: New | H216: =IFERROR(VLOOKUP(Table2[[#This Row], [Ticket]],Okey!A:B,2,0),"") -> ok | I216: Closed | J216: =VLOOKUP(Table2[[#This Row], [Author]],People!A:B,2,0) -> LS | M216: Marlon Abadia
A217: =1+A216 -> 216 | B217: F1 | C217: FR5109402 | D217: G000001005 | E217: SM-EP Site Darmstadt | F217: G000000421 | G217: New | H217: =IFERROR(VLOOKUP(Table2[[#This Row], [Ticket]],Okey!A:B,2,0),"") -> ok | I217: Closed | J217: =VLOOKUP(Table2[[#This Row], [Author]],People!A:B,2,0) -> LS | M217: Paul Kopp
A218: =1+A217 -> 217 | B218: F1 | C218: FR5109402 | D218: G000001006 | E218: SM-EP Site Gernsheim | F218: G000000421 | G218: New | H218: =IFERROR(VLOOKUP(Table2[[#This Row], [Ticket]],Okey!A:B,2,0),"") -> ok | I218: Closed | J218: =VLOOKUP(Table2[[#This Row], [Author]],People!A:B,2,0) -> LS | M218: Paul Kopp
A219: =1+A218 -> 218 | B219: F1 | C219: FR5109402 | D219: G000001007 | E219: SM-EP Site Hohenbrunn | F219: G000000421 | G219: New | H219: =IFERROR(VLOOKUP(Table2[[#This Row], [Ticket]],Okey!A:B,2,0),"") -> ok | I219: Closed | J219: =VLOOKUP(Table2[[#This Row], [Author]],People!A:B,2,0) -> LS | M219: Paul Kopp
A220: =1+A219 -> 219 | B220: F1 | C220: FR5109402 | D220: G000001008 | E220: SM-EP Grundstücke KGaA | F220: G000000421 | G220: New | H220: =IFERROR(VLOOKUP(Table2[[#This Row], [Ticket]],Okey!A:B,2,0),"") -> ok | I220: Closed | J220: =VLOOKUP(Table2[[#This Row], [Author]],People!A:B,2,0) -> LS | M220: Paul Kopp
A221: =1+A220 -> 220 | B221: F1 | C221: FR5109402 | D221: G000001009 | E221: SM-EP Verrechnungs-Kostenstellen | F221: G000000421 | G221: New | H221: =IFERROR(VLOOKUP(Table2[[#This Row], [Ticket]],Okey!A:B,2,0),"") -> ok | I221: Closed | J221: =VLOOKUP(Table2[[#This Row], [Author]],People!A:B,2,0) -> LS | M221: Paul Kopp
A222: =1+A221 -> 221 | B222: F1 | C222: FR5109402 | D222: G000001010 | E222: SM-EP Gebäude DA | F222: G000000421 | G222: New | H222: =IFERROR(VLOOKUP(Table2[[#This Row], [Ticket]],Okey!A:B,2,0),"") -> ok | I222: Closed | J222: =VLOOKUP(Table2[[#This Row], [Author]],People!A:B,2,0) -> LS | M222: Paul Kopp
A223: =1+A222 -> 222 | B223: F1 | C223: FR5109402 | D223: G000001011 | E223: SM-EP Freiflächen DA | F223: G000000421 | G223: New | H223: =IFERROR(VLOOKUP(Table2[[#This Row], [Ticket]],Okey!A:B,2,0),"") -> ok | I223: Closed | J223: =VLOOKUP(Table2[[#This Row], [Author]],People!A:B,2,0) -> LS | M223: Paul Kopp
A224: =1+A223 -> 223 | B224: F1 | C224: FR5109402 | D224: G000001012 | E224: Full Service Gebäude DA | F224: G000000421 | G224: New | H224: =IFERROR(VLOOKUP(Table2[[#This Row], [Ticket]],Okey!A:B,2,0),"") -> ok | I224: Closed | J224: =VLOOKUP(Table2[[#This Row], [Author]],People!A:B,2,0) -> LS | M224: Paul Kopp
A225: =1+A224 -> 224 | B225: F1 | C225: FR5109402 | D225: G000001013 | E225: Shell and Core Gebäude DA | F225: G000000421 | G225: New | H225: =IFERROR(VLOOKUP(Table2[[#This Row], [Ticket]],Okey!A:B,2,0),"") -> ok | I225: Closed | J225: =VLOOKUP(Table2[[#This Row], [Author]],People!A:B,2,0) -> LS | M225: Paul Kopp
A226: =1+A225 -> 225 | B226: F1 | C226: FR5109402 | D226: G000001014 | E226: Lease Hold Gebäude DA | F226: G000000421 | G226: New | H226: =IFERROR(VLOOKUP(Table2[[#This Row], [Ticket]],Okey!A:B,2,0),"") -> ok | I226: Closed | J226: =VLOOKUP(Table2[[#This Row], [Author]],People!A:B,2,0) -> LS | M226: Paul Kopp
... A315: =1+A314 -> 314 | B315: F1 | C315: FR5115101 | D315: H000004194 | E315: ES - Medical non R&D Evobrutinib | F315: H000003990 | G315: New | H315: =IFERROR(VLOOKUP(Table2[[#This Row], [Ticket]],Okey!A:B,2,0),"") -> ok | I315: Closed | J315: =VLOOKUP(Table2[[#This Row], [Author]],People!A:B,2,0) -> LS | M315: Karl Anatoly Uy
A316: =1+A315 -> 315 | B316: F1 | C316: FR5133979 | D316: H000003837 | E316: US - MAPS - Value & Access, Contract Ops | G316: Rename | H316: =IFERROR(VLOOKUP(Table2[[#This Row], [Ticket]],Okey!A:B,2,0),"") -> ok | I316: Closed | J316: =VLOOKUP(Table2[[#This Row], [Author]],People!A:B,2,0) -> LS | M316: Karl Anatoly Uy
A317: =1+A316 -> 316 | B317: F1 | C317: FR5133979 | D317: H000003839 | E317: US - MAPS - Channel Acct Mgmt & Ops | G317: Rename | H317: =IFERROR(VLOOKUP(Table2[[#This Row], [Ticket]],Okey!A:B,2,0),"") -> ok | I317: Closed | J317: =VLOOKUP(Table2[[#This Row], [Author]],People!A:B,2,0) -> LS | M317: Karl Anatoly Uy
A318: =1+A317 -> 317 | B318: F1 | C318: FR5133979 | D318: H000003843 | E318: US - MAPS - Value & Access | G318: Rename | H318: =IFERROR(VLOOKUP(Table2[[#This Row], [Ticket]],Okey!A:B,2,0),"") -> ok | I318: Closed | J318: =VLOOKUP(Table2[[#This Row], [Author]],People!A:B,2,0) -> LS | M318: Karl Anatoly Uy
A319: =1+A318 -> 318 | B319: F1 | C319: FR5133979 | D319: H000003844 | E319: US - MAPS - Contract, Pricing & Insights | G319: Rename | H319: =IFERROR(VLOOKUP(Table2[[#This Row], [Ticket]],Okey!A:B,2,0),"") -> ok | I319: Closed | J319: =VLOOKUP(Table2[[#This Row], [Author]],People!A:B,2,0) -> LS | M319: Karl Anatoly Uy
A320: =1+A319 -> 319 | B320: F1 | C320: FR5133979 | D320: H000003846 | E320: US - MAPS - Channel Acct Mgmt & Ops | G320: Rename | H320: =IFERROR(VLOOKUP(Table2[[#This Row], [Ticket]],Okey!A:B,2,0),"") -> ok | I320: Closed | J320: =VLOOKUP(Table2[[#This Row], [Author]],People!A:B,2,0) -> LS | M320: Karl Anatoly Uy
A321: =1+A320 -> 320 | B321: F1 | C321: FR5134014 | D321: H000001447 | E321: CN-FD ISS FBU Head | F321: H000001446 | G321: Rename/Move | H321: =IFERROR(VLOOKUP(Table2[[#This Row], [Ticket]],Okey!A:B,2,0),"") -> ok | I321: Closed | J321: =VLOOKUP(Table2[[#This Row], [Author]],People!A:B,2,0) -> LS | M321: Joebeth Navarro
A322: =1+A321 -> 321 | B322: F1 | C322: FR5134014 | D322: H000001452 | E322: CN-FD ISS MKT Non-HCP MCM | F322: H000001451 | G322: Rename/Move | H322: =IFERROR(VLOOKUP(Table2[[#This Row], [Ticket]],Okey!A:B,2,0),"") -> ok | I322: Closed | J322: =VLOOKUP(Table2[[#This Row], [Author]],People!A:B,2,0) -> LS | M322: Joebeth Navarro
A323: =1+A322 -> 322 | B323: F1 | C323: FR5134014 | D323: H000001454 | E323: CN-FD ISS BSE Team | F323: H000001453 | G323: Rename/Move | H323: =IFERROR(VLOOKUP(Table2[[#This Row], [Ticket]],Okey!A:B,2,0),"") -> ok | I323: Closed | J323: =VLOOKUP(Table2[[#This Row], [Author]],People!A:B,2,0) -> LS | M323: Joebeth Navarro
A324: =1+A323 -> 323 | B324: F1 | C324: FR5134014 | D324: H000004195 | E324: CN-FD FF Sales Mega Center | F324: H000001432 | G324: New | H324: =IFERROR(VLOOKUP(Table2[[#This Row], [Ticket]],Okey!A:B,2,0),"") -> ok | I324: Closed | J324: =VLOOKUP(Table2[[#This Row], [Author]],People!A:B,2,0) -> LS | M324: Joebeth Navarro
A325: =1+A324 -> 324 | B325: F1 | C325: FR5134014 | D325: H000004196 | E325: CN-FD ISS MKT Non-HCP Head | F325: H000001451 | G325: New | H325: =IFERROR(VLOOKUP(Table2[[#This Row], [Ticket]],Okey!A:B,2,0),"") -> ok | I325: Closed | J325: =VLOOKUP(Table2[[#This Row], [Author]],People!A:B,2,0) -> LS | M325: Joebeth Navarro
A326: =1+A325 -> 325 | B326: F1 | C326: FR5134014 | D326: H000004197 | E326: CN-FD ISS MKT Non-HCP CE | F326: H000001451 | G326: New | H326: =IFERROR(VLOOKUP(Table2[[#This Row], [Ticket]],Okey!A:B,2,0),"") -> ok | I326: Closed | J326: =VLOOKUP(Table2[[#This Row], [Author]],People!A:B,2,0) -> LS | M326: Joebeth Navarro
A327: =1+A326 -> 326 | B327: F1 | C327: FR5134014 | D327: H000004198 | E327: CN-FD SP Sales Mega Center | F327: H000001467 | G327: New | H327: =IFERROR(VLOOKUP(Table2[[#This Row], [Ticket]],Okey!A:B,2,0),"") -> ok | I327: Closed | J327: =VLOOKUP(Table2[[#This Row], [Author]],People!A:B,2,0) -> LS | M327: Joebeth Navarro
A328: =1+A327 -> 327 | B328: F1 | C328: FR5134014 | D328: H000004199 | E328: CN-FD SP MKT Non-HCP Head | F328: H000001483 | G328: New | H328: =IFERROR(VLOOKUP(Table2[[#This Row], [Ticket]],Okey!A:B,2,0),"") -> ok | I328: Closed | J328: =VLOOKUP(Table2[[#This Row], [Author]],People!A:B,2,0) -> LS | M328: Joebeth Navarro
A329: =1+A328 -> 328 | B329: F1 | C329: FR5134014 | D329: H000004200 | E329: CN-FD SP MKT Non-HCP CE | F329: H000001483 | G329: New | H329: =IFERROR(VLOOKUP(Table2[[#This Row], [Ticket]],Okey!A:B,2,0),"") -> ok | I329: Closed | J329: =VLOOKUP(Table2[[#This Row], [Author]],People!A:B,2,0) -> LS | M329: Joebeth Navarro
A330: =1+A329 -> 329 | B330: F1 | C330: FR5134014 | D330: H000001432 | E330: CN - FD Field Force National Sales | G330: Rename | H330: =IFERROR(VLOOKUP(Table2[[#This Row], [Ticket]],Okey!A:B,2,0),"") -> ok | I330: Closed | J330: =VLOOKUP(Table2[[#This Row], [Author]],People!A:B,2,0) -> LS | M330: Joebeth Navarro
A331: =1+A330 -> 330 | B331: F1 | C331: FR5134014 | D331: H000001433 | E331: CN - FD FF Sales Head | G331: Rename | H331: =IFERROR(VLOOKUP(Table2[[#This Row], [Ticket]],Okey!A:B,2,0),"") -> ok | I331: Closed | J331: =VLOOKUP(Table2[[#This Row], [Author]],People!A:B,2,0) -> LS | M331: Joebeth Navarro
A332: =1+A331 -> 331 | B332: F1 | C332: FR5134014 | D332: H000001434 | E332: CN - FD FF Sales North | G332: Rename | H332: =IFERROR(VLOOKUP(Table2[[#This Row], [Ticket]],Okey!A:B,2,0),"") -> ok | I332: Closed | J332: =VLOOKUP(Table2[[#This Row], [Author]],People!A:B,2,0) -> LS | M332: Joebeth Navarro
A333: =1+A332 -> 332 | B333: F1 | C333: FR5134014 | D333: H000001435 | E333: CN - FD FF Sales South | G333: Rename | H333: =IFERROR(VLOOKUP(Table2[[#This Row], [Ticket]],Okey!A:B,2,0),"") -> ok | I333: Closed | J333: =VLOOKUP(Table2[[#This Row], [Author]],People!A:B,2,0) -> LS | M333: Joebeth Navarro
A334: =1+A333 -> 333 | B334: F1 | C334: FR5134014 | D334: H000001436 | E334: CN - FD FF Sales East | G334: Rename | H334: =IFERROR(VLOOKUP(Table2[[#This Row], [Ticket]],Okey!A:B,2,0),"") -> ok | I334: Closed | J334: =VLOOKUP(Table2[[#This Row], [Author]],People!A:B,2,0) -> LS | M334: Joebeth Navarro
A335: =1+A334 -> 334 | B335: F1 | C335: FR5134014 | D335: H000001437 | E335: CN - FD FF Sales West | G335: Rename | H335: =IFERROR(VLOOKUP(Table2[[#This Row], [Ticket]],Okey!A:B,2,0),"") -> ok | I335: Closed | J335: =VLOOKUP(Table2[[#This Row], [Author]],People!A:B,2,0) -> LS | M335: Joebeth Navarro
A336: =1+A335 -> 335 | B336: F1 | C336: FR5134014 | D336: H000001438 | E336: CN - FD FF Sales RMM | G336: Rename | H336: =IFERROR(VLOOKUP(Table2[[#This Row], [Ticket]],Okey!A:B,2,0),"") -> ok | I336: Closed | J336: =VLOOKUP(Table2[[#This Row], [Author]],People!A:B,2,0) -> LS | M336: Joebeth Navarro
A337: =1+A336 -> 336 | B337: F1 | C337: FR5134014 | D337: H000001448 | E337: CN - FD ISS PMO | G337: Rename | H337: =IFERROR(VLOOKUP(Table2[[#This Row], [Ticket]],Okey!A:B,2,0),"") -> ok | I337: Closed | J337: =VLOOKUP(Table2[[#This Row], [Author]],People!A:B,2,0) -> LS | M337: Joebeth Navarro
A338: =1+A337 -> 337 | B338: F1 | C338: FR5134014 | D338: H000001449 | E338: CN - FD ISS PMO team | G338: Rename | H338: =IFERROR(VLOOKUP(Table2[[#This Row], [Ticket]],Okey!A:B,2,0),"") -> ok | I338: Closed | J338: =VLOOKUP(Table2[[#This Row], [Author]],People!A:B,2,0) -> LS | M338: Joebeth Navarro
A339: =1+A338 -> 338 | B339: F1 | C339: FR5134014 | D339: H000001451 | E339: CN - FD ISS MKT Non-HCP | G339: Rename | H339: =IFERROR(VLOOKUP(Table2[[#This Row], [Ticket]],Okey!A:B,2,0),"") -> ok | I339: Closed | J339: =VLOOKUP(Table2[[#This Row], [Author]],People!A:B,2,0) -> LS | M339: Joebeth Navarro
A340: =1+A339 -> 339 | B340: F1 | C340: FR5134014 | D340: H000001467 | E340: CN - FD Sales Promotion National Sales | G340: Rename | H340: =IFERROR(VLOOKUP(Table2[[#This Row], [Ticket]],Okey!A:B,2,0),"") -> ok | I340: Closed | J340: =VLOOKUP(Table2[[#This Row], [Author]],People!A:B,2,0) -> LS | M340: Joebeth Navarro
A341: =1+A340 -> 340 | B341: F1 | C341: FR5134014 | D341: H000001468 | E341: CN - FD SP Sales Head | G341: Rename | H341: =IFERROR(VLOOKUP(Table2[[#This Row], [Ticket]],Okey!A:B,2,0),"") -> ok | I341: Closed | J341: =VLOOKUP(Table2[[#This Row], [Author]],People!A:B,2,0) -> LS | M341: Joebeth Navarro
... A348: =1+A347 -> 347 | B348: F1 | C348: FR5134014 | D348: H000001484 | E348: CN - FD SP MKT Non - HCP MCM | G348: Rename | H348: =IFERROR(VLOOKUP(Table2[[#This Row], [Ticket]],Okey!A:B,2,0),"") -> ok | I348: Closed | J348: =VLOOKUP(Table2[[#This Row], [Author]],People!A:B,2,0) -> LS | M348: Joebeth Navarro
A349: =1+A348 -> 348 | B349: F1 | C349: FR5136045 | D349: L000011136 | E349: LS Management -G | F349: L000011110 | G349: Rename/Move | H349: =IFERROR(VLOOKUP(Table2[[#This Row], [Ticket]],Okey!A:B,2,0),"") -> ok | I349: Closed | J349: =VLOOKUP(Table2[[#This Row], [Author]],People!A:B,2,0) -> LS | M349: Phoebe Anne Fortaleza
A350: =1+A349 -> 349 | B350: F1 | C350: FR5136045 | D350: L000011336 | E350: Technology Pioneering | F350: L000013275 | G350: Rename/Move | H350: =IFERROR(VLOOKUP(Table2[[#This Row], [Ticket]],Okey!A:B,2,0),"") -> ok | I350: Closed | J350: =VLOOKUP(Table2[[#This Row], [Author]],People!A:B,2,0) -> LS | M350: Phoebe Anne Fortaleza
A351: =1+A350 -> 350 | B351: F1 | C351: FR5136045 | D351: L000013324 | F351: L000013275 | G351: Move | H351: =IFERROR(VLOOKUP(Table2[[#This Row], [Ticket]],Okey!A:B,2,0),"") -> ok | I351: Closed | J351: =VLOOKUP(Table2[[#This Row], [Author]],People!A:B,2,0) -> LS | M351: Phoebe Anne Fortaleza
A352: =1+A351 -> 351 | B352: F1 | C352: FR5136045 | D352: L000013325 | F352: L000013275 | G352: Move | H352: =IFERROR(VLOOKUP(Table2[[#This Row], [Ticket]],Okey!A:B,2,0),"") -> ok | I352: Closed | J352: =VLOOKUP(Table2[[#This Row], [Author]],People!A:B,2,0) -> LS | M352: Phoebe Anne Fortaleza
A353: =1+A352 -> 352 | B353: F1 | C353: FR5136045 | D353: L000013326 | F353: L000013275 | G353: Move | H353: =IFERROR(VLOOKUP(Table2[[#This Row], [Ticket]],Okey!A:B,2,0),"") -> ok | I353: Closed | J353: =VLOOKUP(Table2[[#This Row], [Author]],People!A:B,2,0) -> LS | M353: Phoebe Anne Fortaleza
A354: =1+A353 -> 353 | B354: F1 | C354: FR5138688 | D354: H000004116 | E354: FR - Sales promotion Xevinapant | F354: H000001612 | G354: Move | H354: =IFERROR(VLOOKUP(Table2[[#This Row], [Ticket]],Okey!A:B,2,0),"") -> ok | I354: Closed | J354: =VLOOKUP(Table2[[#This Row], [Author]],People!A:B,2,0) -> LS | M354: Thibault Pernelle
A355: =1+A354 -> 354 | B355: F1 | C355: FR5138688 | D355: H000004201 | E355: FR - Medical non R&D Evobrutinib | F355: H000001637 | G355: New | H355: =IFERROR(VLOOKUP(Table2[[#This Row], [Ticket]],Okey!A:B,2,0),"") -> ok | I355: Closed | J355: =VLOOKUP(Table2[[#This Row], [Author]],People!A:B,2,0) -> LS | M355: Thibault Pernelle
A356: =1+A355 -> 355 | B356: F1 | C356: FR5138688 | D356: H000004202 | E356: FR - Sales promotion Evobrutinib | F356: H000001619 | G356: New | H356: =IFERROR(VLOOKUP(Table2[[#This Row], [Ticket]],Okey!A:B,2,0),"") -> ok | I356: Closed | J356: =VLOOKUP(Table2[[#This Row], [Author]],People!A:B,2,0) -> LS | M356: Thibault Pernelle
A357: =1+A356 -> 356 | B357: F1 | C357: FR5140150 | D357: H000004203 | E357: FR - Production costs | F357: H000000186 | G357: New | H357: =IFERROR(VLOOKUP(Table2[[#This Row], [Ticket]],Okey!A:B,2,0),"") -> ok | I357: Closed | J357: =VLOOKUP(Table2[[#This Row], [Author]],People!A:B,2,0) -> LS | M357: Thibault Pernelle
A358: =1+A357 -> 357 | B358: F1 | C358: FR5140253 | D358: H000004204 | E358: GB - ISS -Xevinapant | F358: H000002080 | G358: New | H358: =IFERROR(VLOOKUP(Table2[[#This Row], [Ticket]],Okey!A:B,2,0),"") -> ok | I358: Closed | J358: =VLOOKUP(Table2[[#This Row], [Author]],People!A:B,2,0) -> LS | M358: Basak Buyukkosker
A359: =1+A358 -> 358 | B359: F1 | C359: FR5140253 | D359: H000004205 | E359: GB - ISS- Evobrutinib | F359: H000002092 | G359: New | H359: =IFERROR(VLOOKUP(Table2[[#This Row], [Ticket]],Okey!A:B,2,0),"") -> ok | I359: Closed | J359: =VLOOKUP(Table2[[#This Row], [Author]],People!A:B,2,0) -> LS | M359: Basak Buyukkosker
A360: =1+A359 -> 359 | B360: F1 | C360: FR5140253 | D360: H000004206 | E360: GB - LRD Evobrutinib | F360: H000002111 | G360: New | H360: =IFERROR(VLOOKUP(Table2[[#This Row], [Ticket]],Okey!A:B,2,0),"") -> ok | I360: Closed | J360: =VLOOKUP(Table2[[#This Row], [Author]],People!A:B,2,0) -> LS | M360: Basak Buyukkosker
A361: =1+A360 -> 360 | B361: F1 | C361: FR5140253 | D361: H000004207 | E361: GB - Medical Non R&D Xevinapant | F361: H000002116 | G361: New | H361: =IFERROR(VLOOKUP(Table2[[#This Row], [Ticket]],Okey!A:B,2,0),"") -> ok | I361: Closed | J361: =VLOOKUP(Table2[[#This Row], [Author]],People!A:B,2,0) -> LS | M361: Basak Buyukkosker
A362: =1+A361 -> 361 | B362: F1 | C362: FR5140253 | D362: H000004208 | E362: GB - Medical Non R&D Evobrutinib | F362: H000002116 | G362: New | H362: =IFERROR(VLOOKUP(Table2[[#This Row], [Ticket]],Okey!A:B,2,0),"") -> ok | I362: Closed | J362: =VLOOKUP(Table2[[#This Row], [Author]],People!A:B,2,0) -> LS | M362: Basak Buyukkosker
A363: =1+A362 -> 362 | B363: F1 | C363: FR5141188 | D363: H000004209 | E363: SCALA_1786 0000000350 | F363: H000000729 | G363: New | H363: =IFERROR(VLOOKUP(Table2[[#This Row], [Ticket]],Okey!A:B,2,0),"") -> ok | I363: Closed | J363: =VLOOKUP(Table2[[#This Row], [Author]],People!A:B,2,0) -> LS | M363: Marlon Abadia
...

Sheet 2024
A1: No. | B1: Forecast? | C1: Ticket | D1: Node | E1: Name | F1: Parent | G1: Action | H1: STATUS | I1: STATUS Check | J1: Sector | K1: Comments | L1: SANITY | M1: Author
A2: 1 | B2: F0 | C2: FR6700341 | D2: IT06042500 | F2: G000001240 | G2: Move | H2: =IFERROR(VLOOKUP(Table2[[#This Row], [Ticket]],Okey!A:B,2,0),"") -> ok | I2: completed | J2: MGF | M2: Joshua Cachola
A3: =1+A2 -> 2 | B3: F0 | C3: FR6700341 | D3: IT06100700 | F3: G000001238 | G3: Move | H3: =IFERROR(VLOOKUP(Table2[[#This Row], [Ticket]],Okey!A:B,2,0),"") -> ok | I3: completed | J3: MGF | M3: Joshua Cachola
A4: =1+A3 -> 3 | B4: F0 | C4: FR6700341 | D4: IT06100800 | F4: G000001239 | G4: Move | H4: =IFERROR(VLOOKUP(Table2[[#This Row], [Ticket]],Okey!A:B,2,0),"") -> ok | I4: completed | J4: MGF | M4: Joshua Cachola
A5: =1+A4 -> 4 | B5: F0 | C5: FR6711984 | D5: G000001096 | F5: G000000873 | G5: Move | H5: =IFERROR(VLOOKUP(Table2[[#This Row], [Ticket]],Okey!A:B,2,0),"") -> ok | I5: completed | J5: MGF | M5: Francesco Ricioppo
A6: =1+A5 -> 5 | B6: F0 | C6: FR6711984 | D6: G000000378 | F6: G000000873 | G6: Move | H6: =IFERROR(VLOOKUP(Table2[[#This Row], [Ticket]],Okey!A:B,2,0),"") -> ok | I6: completed | J6: MGF | M6: Francesco Ricioppo
A7: =1+A6 -> 6 | B7: F0 | C7: FR6711984 | D7: G000000869 | F7: G000000873 | G7: Move | H7: =IFERROR(VLOOKUP(Table2[[#This Row], [Ticket]],Okey!A:B,2,0),"") -> ok | I7: completed | J7: MGF | M7: Francesco Ricioppo
A8: =1+A7 -> 7 | B8: F0 | C8: FR6711984 | D8: G000000870 | F8: G000000873 | G8: Move | H8: =IFERROR(VLOOKUP(Table2[[#This Row], [Ticket]],Okey!A:B,2,0),"") -> ok | I8: completed | J8: MGF | M8: Francesco Ricioppo
A9: =1+A8 -> 8 | B9: F0 | C9: FR6711984 | D9: G000000871 | F9: G000000873 | G9: Move | H9: =IFERROR(VLOOKUP(Table2[[#This Row], [Ticket]],Okey!A:B,2,0),"") -> ok | I9: completed | J9: MGF | M9: Francesco Ricioppo
A10: =1+A9 -> 9 | B10: F0 | C10: FR6711984 | D10: G000000872 | F10: G000000873 | G10: Move | H10: =IFERROR(VLOOKUP(Table2[[#This Row], [Ticket]],Okey!A:B,2,0),"") -> ok | I10: completed | J10: MGF | M10: Francesco Ricioppo
A11: =1+A10 -> 10 | B11: F0 | C11: FR6711984 | D11: G000000464 | F11: G000000873 | G11: Move | H11: =IFERROR(VLOOKUP(Table2[[#This Row], [Ticket]],Okey!A:B,2,0),"") -> ok | I11: completed | J11: MGF | M11: Francesco Ricioppo
A12: =1+A11 -> 11 | B12: F0 | C12: FR6711984 | D12: G000000998 | F12: G000000873 | G12: Move | H12: =IFERROR(VLOOKUP(Table2[[#This Row], [Ticket]],Okey!A:B,2,0),"") -> ok | I12: completed | J12: MGF | M12: Francesco Ricioppo
A13: =1+A12 -> 12 | B13: F0 | C13: FR6711984 | D13: G000000996 | F13: G000000873 | G13: Move | H13: =IFERROR(VLOOKUP(Table2[[#This Row], [Ticket]],Okey!A:B,2,0),"") -> ok | I13: completed | J13: MGF | M13: Francesco Ricioppo
A14: =1+A13 -> 13 | B14: F0 | C14: FR6711984 | D14: G000000997 | F14: G000000873 | G14: Move | H14: =IFERROR(VLOOKUP(Table2[[#This Row], [Ticket]],Okey!A:B,2,0),"") -> ok | I14: completed | J14: MGF | M14: Francesco Ricioppo
A15: =1+A14 -> 14 | B15: F0 | C15: FR6712079 | D15: G000001020 | E15: FS Contractors DA | G15: Rename | H15: =IFERROR(VLOOKUP(Table2[[#This Row], [Ticket]],Okey!A:B,2,0),"") -> ok | I15: completed | J15: MGF | M15: Francesco Ricioppo
A16: =1+A15 -> 15 | B16: F0 | C16: FR6712079 | D16: G000001011 | E16: Contractors/Externals Area | F16: G000001020 | G16: Rename | H16: =IFERROR(VLOOKUP(Table2[[#This Row], [Ticket]],Okey!A:B,2,0),"") -> ok | I16: completed | J16: MGF | M16: Francesco Ricioppo
A17: =1+A16 -> 16 | B17: F0 | C17: FR6712079 | D17: G000001026 | E17: Z-Area | F17: G000001020 | G17: Rename | H17: =IFERROR(VLOOKUP(Table2[[#This Row], [Ticket]],Okey!A:B,2,0),"") -> ok | I17: completed | J17: MGF | M17: Francesco Ricioppo
A18: =1+A17 -> 17 | B18: F0 | C18: FR6712079 | D18: G000001010 | E18: W-Area | F18: G000001020 | G18: Rename | H18: =IFERROR(VLOOKUP(Table2[[#This Row], [Ticket]],Okey!A:B,2,0),"") -> ok | I18: completed | J18: MGF | M18: Francesco Ricioppo
A19: =1+A18 -> 18 | B19: F0 | C19: FR6736844 | D19: G000000398 | F19: G000000873 | G19: Move | H19: =IFERROR(VLOOKUP(Table2[[#This Row], [Ticket]],Okey!A:B,2,0),"") -> ok | I19: completed | J19: MGF | M19: Francesco Ricioppo
A20: =1+A19 -> 19 | B20: F0 | C20: FR6736844 | D20: G000000356 | F20: G000000873 | G20: Move | H20: =IFERROR(VLOOKUP(Table2[[#This Row], [Ticket]],Okey!A:B,2,0),"") -> ok | I20: completed | J20: MGF | M20: Francesco Ricioppo
A21: =1+A20 -> 20 | B21: F0 | C21: FR6736844 | D21: G000000357 | F21: G000000873 | G21: Move | H21: =IFERROR(VLOOKUP(Table2[[#This Row], [Ticket]],Okey!A:B,2,0),"") -> ok | I21: completed | J21: MGF | M21: Francesco Ricioppo
A22: =1+A21 -> 21 | B22: F0 | C22: FR6736844 | D22: G000000358 | F22: G000000873 | G22: Move | H22: =IFERROR(VLOOKUP(Table2[[#This Row], [Ticket]],Okey!A:B,2,0),"") -> ok | I22: completed | J22: MGF | M22: Francesco Ricioppo
A23: =1+A22 -> 22 | B23: F0 | C23: FR6736844 | D23: G000000399 | F23: G000000873 | G23: Move | H23: =IFERROR(VLOOKUP(Table2[[#This Row], [Ticket]],Okey!A:B,2,0),"") -> ok | I23: completed | J23: MGF | M23: Francesco Ricioppo
A24: =1+A23 -> 23 | B24: F0 | C24: FR6736844 | D24: G000000400 | F24: G000000873 | G24: Move | H24: =IFERROR(VLOOKUP(Table2[[#This Row], [Ticket]],Okey!A:B,2,0),"") -> ok | I24: completed | J24: MGF | M24: Francesco Ricioppo
A25: =1+A24 -> 24 | B25: F0 | C25: FR6736844 | D25: G000000401 | F25: G000000873 | G25: Move | H25: =IFERROR(VLOOKUP(Table2[[#This Row], [Ticket]],Okey!A:B,2,0),"") -> ok | I25: completed | J25: MGF | M25: Francesco Ricioppo
A26: =1+A25 -> 25 | B26: F0 | C26: FR6737570 | D26: G000000878 | E26: SM-SF/SC Fire Brigade & Security | G26: Rename | H26: =IFERROR(VLOOKUP(Table2[[#This Row], [Ticket]],Okey!A:B,2,0),"") -> ok | I26: completed | J26: MGF | M26: Francesco Ricioppo
A27: =1+A26 -> 26 | B27: F0 | C27: FR6737570 | D27: G000000435 | E27: SM-SF Fire Protection | F27: G000000878 | G27: Rename/Move | H27: =IFERROR(VLOOKUP(Table2[[#This Row], [Ticket]],Okey!A:B,2,0),"") -> ok | I27: completed | J27: MGF | M27: Francesco Ricioppo
A28: =1+A27 -> 27 | B28: F0 | C28: FR6737570 | D28: G000000436 | E28: SM-SC Site Security & Cross Services | F28: G000000878 | G28: Rename/Move | H28: =IFERROR(VLOOKUP(Table2[[#This Row], [Ticket]],Okey!A:B,2,0),"") -> ok | I28: completed | J28: MGF | M28: Francesco Ricioppo
A29: =1+A28 -> 28 | B29: F0 | C29: FR6762200 | D29: H000004388 | E29: GCD WBS elements | F29: H000000616 | G29: New | H29: =IFERROR(VLOOKUP(Table2[[#This Row], [Ticket]],Okey!A:B,2,0),"") -> ok | I29: completed | J29: HC | M29: Lena Brand
A30: =1+A29 -> 29 | B30: F0 | C30: FR6797793 | D30: P000001200 | E30: Separation Cost | F30: P000001198 | G30: New | H30: =IFERROR(VLOOKUP(Table2[[#This Row], [Ticket]],Okey!A:B,2,0),"") -> ok | I30: completed | J30: EL | M30: Eivy Denine Cruz
A31: =1+A30 -> 30 | B31: F0 | C31: FR6797793 | D31: P000001201 | E31: Set up of NewCos | F31: P000001200 | G31: New | H31: =IFERROR(VLOOKUP(Table2[[#This Row], [Ticket]],Okey!A:B,2,0),"") -> ok | I31: completed | J31: EL | M31: Eivy Denine Cruz
A32: =1+A31 -> 31 | B32: F0 | C32: FR6797793 | D32: P000001202 | E32: Set up of Export Model & Hubs | F32: P000001200 | G32: New | H32: =IFERROR(VLOOKUP(Table2[[#This Row], [Ticket]],Okey!A:B,2,0),"") -> ok | I32: completed | J32: EL | M32: Eivy Denine Cruz
A33: =1+A32 -> 32 | B33: F0 | C33: FR6797793 | D33: P000001203 | E33: Physical separation | F33: P000001200 | G33: New | H33: =IFERROR(VLOOKUP(Table2[[#This Row], [Ticket]],Okey!A:B,2,0),"") -> ok | I33: completed | J33: EL | M33: Eivy Denine Cruz
A34: =1+A33 -> 33 | B34: F0 | C34: FR6797793 | D34: P000001204 | E34: Legal C/O of POG-8 & POG-3 out of current legal entities | F34: P000001200 | G34: New | H34: =IFERROR(VLOOKUP(Table2[[#This Row], [Ticket]],Okey!A:B,2,0),"") -> ok | I34: completed | J34: EL | M34: Eivy Denine Cruz
A35: =1+A34 -> 34 | B35: F0 | C35: FR6797793 | D35: P000001205 | E35: IT Separation | F35: P000001200 | G35: New | H35: =IFERROR(VLOOKUP(Table2[[#This Row], [Ticket]],Okey!A:B,2,0),"") -> ok | I35: completed | J35: EL | M35: Eivy Denine Cruz
A36: =1+A35 -> 35 | B36: F0 | C36: FR6797793 | D36: P000001206 | E36: Business Backfills | F36: P000001205 | G36: New | H36: =IFERROR(VLOOKUP(Table2[[#This Row], [Ticket]],Okey!A:B,2,0),"") -> ok | I36: completed | J36: EL | M36: Eivy Denine Cruz
A37: =1+A36 -> 36 | B37: F0 | C37: FR6797793 | D37: P000001207 | E37: MBS Backfills & support | F37: P000001205 | G37: New | H37: =IFERROR(VLOOKUP(Table2[[#This Row], [Ticket]],Okey!A:B,2,0),"") -> ok | I37: completed | J37: EL | M37: Eivy Denine Cruz
A38: =1+A37 -> 37 | B38: F0 | C38: FR6797793 | D38: P000001208 | E38: Additional Cost | F38: P000001198 | G38: New | H38: =IFERROR(VLOOKUP(Table2[[#This Row], [Ticket]],Okey!A:B,2,0),"") -> ok | I38: completed | J38: EL | M38: Eivy Denine Cruz
... A83: =1+A82 -> 82 | B83: F0 | C83: FR6797793 | D83: P000001253 | E83: Feasibility | F83: P000000593 | G83: New | H83: =IFERROR(VLOOKUP(Table2[[#This Row], [Ticket]],Okey!A:B,2,0),"") -> ok | I83: completed | J83: EL | M83: Eivy Denine Cruz
A84: =1+A83 -> 83 | B84: F0 | C84: FR6797793 | D84: P000000551 | F84: O000000009 | G84: Delete | H84: =IFERROR(VLOOKUP(Table2[[#This Row], [Ticket]],Okey!A:B,2,0),"") -> ok | I84: completed | J84: EL | M84: Eivy Denine Cruz
A85: =1+A84 -> 84 | B85: F0 | C85: FR6799262 | D85: H000004389 | E85: CN - Onco ISS BU Pimi MKT | F85: H000001411 | G85: New | H85: =IFERROR(VLOOKUP(Table2[[#This Row], [Ticket]],Okey!A:B,2,0),"") -> ok | I85: completed | J85: HC | M85: Carlo Umali
A86: =1+A85 -> 85 | B86: F0 | C86: FR6799262 | D86: H000004390 | E86: CN - Onco Sales Promotion Pimi MKT | F86: H000001421 | G86: New | H86: =IFERROR(VLOOKUP(Table2[[#This Row], [Ticket]],Okey!A:B,2,0),"") -> ok | I86: completed | J86: HC | M86: Carlo Umali
A87: =1+A86 -> 86 | B87: F0 | C87: FR6799262 | D87: H000004391 | E87: CN - Medical Team Pimi MA | F87: H000001526 | G87: New | H87: =IFERROR(VLOOKUP(Table2[[#This Row], [Ticket]],Okey!A:B,2,0),"") -> ok | I87: completed | J87: HC | M87: Carlo Umali
A88: =1+A87 -> 87 | B88: F0 | C88: FR6799262 | D88: H000004392 | E88: CN - Medical activities Pimi MA | F88: H000001539 | G88: New | H88: =IFERROR(VLOOKUP(Table2[[#This Row], [Ticket]],Okey!A:B,2,0),"") -> ok | I88: completed | J88: HC | M88: Carlo Umali
A89: =1+A88 -> 88 | B89: F0 | C89: FR6799262 | D89: H000004393 | E89: CN - Local studies Pimi MA | F89: H000001549 | G89: New | H89: =IFERROR(VLOOKUP(Table2[[#This Row], [Ticket]],Okey!A:B,2,0),"") -> ok | I89: completed | J89: HC | M89: Carlo Umali
A90: =1+A89 -> 89 | B90: F0 | C90: FR6801039 | D90: H000000451 | F90: O000000009 | G90: Delete | H90: =IFERROR(VLOOKUP(Table2[[#This Row], [Ticket]],Okey!A:B,2,0),"") -> ok | I90: completed | J90: HC | M90: Henry Ifurung Jr.
A91: =1+A90 -> 90 | B91: F0 | C91: FR6801039 | D91: H000000452 | F91: O000000009 | G91: Delete | H91: =IFERROR(VLOOKUP(Table2[[#This Row], [Ticket]],Okey!A:B,2,0),"") -> ok | I91: completed | J91: HC | M91: Henry Ifurung Jr.
A92: =1+A91 -> 91 | B92: F0 | C92: FR6801039 | D92: H000000453 | F92: O000000009 | G92: Delete | H92: =IFERROR(VLOOKUP(Table2[[#This Row], [Ticket]],Okey!A:B,2,0),"") -> ok | I92: completed | J92: HC | M92: Henry Ifurung Jr.
A93: =1+A92 -> 92 | B93: F0 | C93: FR6801039 | D93: H000000946 | F93: O000000009 | G93: Delete | H93: =IFERROR(VLOOKUP(Table2[[#This Row], [Ticket]],Okey!A:B,2,0),"") -> ok | I93: completed | J93: HC | M93: Henry Ifurung Jr.
A94: =1+A93 -> 93 | B94: F0 | C94: FR6803608 | D94: H000000718 | E94: RD-R Regulatory, Quality, Safety | G94: Rename | H94: =IFERROR(VLOOKUP(Table2[[#This Row], [Ticket]],Okey!A:B,2,0),"") -> ok | I94: completed | J94: HC | M94: Gay Geanuza del Mundo
A95: =1+A94 -> 94 | B95: F0 | C95: FR6803608 | D95: H000000719 | E95: R&D Quality & Risk Management | G95: Rename | H95: =IFERROR(VLOOKUP(Table2[[#This Row], [Ticket]],Okey!A:B,2,0),"") -> ok | I95: completed | J95: HC | M95: Gay Geanuza del Mundo
A96: =1+A95 -> 95 | B96: F0 | C96: FR6803608 | D96: H000000720 | E96: RQS Operations | G96: Rename | H96: =IFERROR(VLOOKUP(Table2[[#This Row], [Ticket]],Okey!A:B,2,0),"") -> ok | I96: completed | J96: HC | M96: Gay Geanuza del Mundo
A97: =1+A96 -> 96 | B97: F0 | C97: FR6803608 | D97: H000000723 | E97: International Regulatory Affairs | G97: Rename | H97: =IFERROR(VLOOKUP(Table2[[#This Row], [Ticket]],Okey!A:B,2,0),"") -> ok | I97: completed | J97: HC | M97: Gay Geanuza del Mundo
A98: =1+A97 -> 97 | B98: F0 | C98: FR6803608 | D98: H000000737 | E98: TA Neurology, Immunology & Establ. Prod. | G98: Rename | H98: =IFERROR(VLOOKUP(Table2[[#This Row], [Ticket]],Okey!A:B,2,0),"") -> ok | I98: completed | J98: HC | M98: Gay Geanuza del Mundo
A99: =1+A98 -> 98 | B99: F0 | C99: FR6803608 | D99: H000000740 | E99: RQS Head | G99: Rename | H99: =IFERROR(VLOOKUP(Table2[[#This Row], [Ticket]],Okey!A:B,2,0),"") -> ok | I99: completed | J99: HC | M99: Gay Geanuza del Mundo
A100: =1+A99 -> 99 | B100: F0 | C100: FR6803608 | D100: H000000743 | E100: Regulatory CMC & Devices | G100: Rename | H100: =IFERROR(VLOOKUP(Table2[[#This Row], [Ticket]],Okey!A:B,2,0),"") -> ok | I100: completed | J100: HC | M100: Gay Geanuza del Mundo
A101: =1+A100 -> 100 | B101: F0 | C101: FR6803608 | D101: H000000908 | E101: Labeling Strategy & Advertising & Promo | G101: Rename | H101: =IFERROR(VLOOKUP(Table2[[#This Row], [Ticket]],Okey!A:B,2,0),"") -> ok | I101: completed | J101: HC | M101: Gay Geanuza del Mundo
A102: =1+A101 -> 101 | B102: F0 | C102: FR6808342 | D102: IT06100500 | E102: EF-IT-PB | F102: G000001238 | G102: Move | H102: =IFERROR(VLOOKUP(Table2[[#This Row], [Ticket]],Okey!A:B,2,0),"") -> ok | I102: completed | J102: MGF | M102: Joshua Cachola
A103: =1+A102 -> 102 | B103: F0 | C103: FR6808342 | D103: G000001275 | F103: O000000009 | G103: Delete | H103: =IFERROR(VLOOKUP(Table2[[#This Row], [Ticket]],Okey!A:B,2,0),"") -> ok | I103: completed | J103: MGF | M103: Joshua Cachola
A104: =1+A103 -> 103 | B104: F0 | C104: FR6808342 | D104: G000001273 | F104: O000000009 | G104: Delete | H104: =IFERROR(VLOOKUP(Table2[[#This Row], [Ticket]],Okey!A:B,2,0),"") -> ok | I104: completed | J104: MGF | M104: Joshua Cachola
A105: =1+A104 -> 104 | B105: F0 | C105: FR6808342 | D105: G000001274 | F105: O000000009 | G105: Delete | H105: =IFERROR(VLOOKUP(Table2[[#This Row], [Ticket]],Okey!A:B,2,0),"") -> ok | I105: completed | J105: MGF | M105: Joshua Cachola
A106: =1+A105 -> 105 | B106: F0 | C106: FR6821884 | D106: G000001265 | E106: GMR MBS Innovation & Data-Int.Automation | G106: Rename | H106: =IFERROR(VLOOKUP(Table2[[#This Row], [Ticket]],Okey!A:B,2,0),"") -> ok | I106: completed | J106: MGF | M106: Jojeff Tagnong
A107: =1+A106 -> 106 | B107: F0 | C107: FR6821884 | D107: G000001211 | E107: GLW MBS FS&P PO-Perform.Mgmt &Compl. PO | G107: Rename | H107: =IFERROR(VLOOKUP(Table2[[#This Row], [Ticket]],Okey!A:B,2,0),"") -> ok | I107: completed | J107: MGF | M107: Jojeff Tagnong
A108: =1+A107 -> 107 | B108: F0 | C108: FR6821884 | D108: G000001219 | E108: GMG MBS FS&P Ent.S.-Communication Serv. | G108: Rename | H108: =IFERROR(VLOOKUP(Table2[[#This Row], [Ticket]],Okey!A:B,2,0),"") -> ok | I108: completed | J108: MGF | M108: Jojeff Tagnong
A109: =1+A108 -> 108 | B109: F0 | C109: FR6821884 | D109: G000001279 | E109: GMS MBS Innovation & Data-Data Sci & AI | F109: G000001145 | G109: New | H109: =IFERROR(VLOOKUP(Table2[[#This Row], [Ticket]],Okey!A:B,2,0),"") -> ok | I109: completed | J109: MGF | M109: Jojeff Tagnong
A110: =1+A109 -> 109 | B110: F0 | C110: FR6821884 | D110: G000001280 | E110: GMT MBS FS&P Ent.S.- Event Services | F110: G000001148 | G110: New | H110: =IFERROR(VLOOKUP(Table2[[#This Row], [Ticket]],Okey!A:B,2,0),"") -> ok | I110: completed | J110: MGF | M110: Jojeff Tagnong
A111: =1+A110 -> 110 | B111: F0 | C111: FR6821884 | D111: G000001281 | E111: GN9 PS - Core Ext.Cost | F111: G000000131 | G111: New | H111: =IFERROR(VLOOKUP(Table2[[#This Row], [Ticket]],Okey!A:B,2,0),"") -> ok | I111: completed | J111: MGF | M111: Jojeff Tagnong
A112: =1+A111 -> 111 | B112: F0 | C112: FR6821884 | D112: G000001282 | E112: GP0 PS - Healthcare Ext.Cost | F112: G000000132 | G112: New | H112: =IFERROR(VLOOKUP(Table2[[#This Row], [Ticket]],Okey!A:B,2,0),"") -> ok | I112: completed | J112: MGF | M112: Jojeff Tagnong
A113: =1+A112 -> 112 | B113: F0 | C113: FR6821884 | D113: G000001283 | E113: GP1 PS - Life Science Ext.Cost | F113: G000000133 | G113: New | H113: =IFERROR(VLOOKUP(Table2[[#This Row], [Ticket]],Okey!A:B,2,0),"") -> ok | I113: completed | J113: MGF | M113: Jojeff Tagnong
A114: =1+A113 -> 113 | B114: F0 | C114: FR6821884 | D114: G000001284 | E114: GY1 PS - Electronics Ext.Cost | F114: G000000134 | G114: New | H114: =IFERROR(VLOOKUP(Table2[[#This Row], [Ticket]],Okey!A:B,2,0),"") -> ok | I114: completed | J114: MGF | M114: Jojeff Tagnong
A115: =1+A114 -> 114 | B115: F0 | C115: FR6821884 | D115: G000001285 | E115: GMU SQ - Bioethics | F115: G000000586 | G115: New | H115: =IFERROR(VLOOKUP(Table2[[#This Row], [Ticket]],Okey!A:B,2,0),"") -> ok | I115: completed | J115: MGF | M115: Jojeff Tagnong
A116: =1+A115 -> 115 | B116: F0 | C116: FR6837097 | D116: L000013790 | E116: Regional management_US East | F116: L000013446 | G116: New | H116: =IFERROR(VLOOKUP(Table2[[#This Row], [Ticket]],Okey!A:B,2,0),"") -> ok | I116: completed | J116: LS | M116: Jayson Martinez
A117: =1+A116 -> 116 | B117: F0 | C117: FR6837097 | D117: L000013791 | E117: Regional management_US Mid West | F117: L000013447 | G117: New | H117: =IFERROR(VLOOKUP(Table2[[#This Row], [Ticket]],Okey!A:B,2,0),"") -> ok | I117: completed | J117: LS | M117: Jayson Martinez
A118: =1+A117 -> 117 | B118: F0 | C118: FR6837097 | D118: L000013792 | E118: Regional management_US West | F118: L000013448 | G118: New | H118: =IFERROR(VLOOKUP(Table2[[#This Row], [Ticket]],Okey!A:B,2,0),"") -> ok | I118: completed | J118: LS | M118: Jayson Martinez
A119: =1+A118 -> 118 | B119: F0 | C119: FR6837097 | D119: L000013793 | E119: Regional management_Western Europe & ME | F119: L000013450 | G119: New | H119: =IFERROR(VLOOKUP(Table2[[#This Row], [Ticket]],Okey!A:B,2,0),"") -> ok | I119: completed | J119: LS | M119: Jayson Martinez
A120: =1+A119 -> 119 | B120: F0 | C120: FR6837097 | D120: L000013794 | E120: Regional management_Central Europe | F120: L000013451 | G120: New | H120: =IFERROR(VLOOKUP(Table2[[#This Row], [Ticket]],Okey!A:B,2,0),"") -> ok | I120: completed | J120: LS | M120: Jayson Martinez
... A142: =1+A141 -> 141 | B142: F0 | C142: FR6837097 | D142: L000013816 | E142: Spruce - Cell Marque Operations | F142: L000013656 | G142: New | H142: =IFERROR(VLOOKUP(Table2[[#This Row], [Ticket]],Okey!A:B,2,0),"") -> ok | I142: completed | J142: LS | M142: Jayson Martinez
A143: =1+A142 -> 142 | B143: F0 | C143: FR6837097 | D143: L000005678 | E143: BM - Mktg - Pharma & F&B -G | G143: Rename | H143: =IFERROR(VLOOKUP(Table2[[#This Row], [Ticket]],Okey!A:B,2,0),"") -> ok | I143: completed | J143: LS | M143: Jayson Martinez
A144: =1+A143 -> 143 | B144: F0 | C144: FR6837097 | D144: L000005683 | E144: BM - Technical Support | G144: Rename | H144: =IFERROR(VLOOKUP(Table2[[#This Row], [Ticket]],Okey!A:B,2,0),"") -> ok | I144: completed | J144: LS | M144: Jayson Martinez
A145: =1+A144 -> 144 | B145: F0 | C145: FR6837097 | D145: L000013611 | E145: DxRM - Molecular & Immunoassay Mat Old | G145: Rename | H145: =IFERROR(VLOOKUP(Table2[[#This Row], [Ticket]],Okey!A:B,2,0),"") -> ok | I145: completed | J145: LS | M145: Jayson Martinez
A146: =1+A145 -> 145 | B146: F0 | C146: FR6837097 | D146: L000013554 | E146: SingleUse & Integrated Platform Solution | G146: Rename | H146: =IFERROR(VLOOKUP(Table2[[#This Row], [Ticket]],Okey!A:B,2,0),"") -> ok | I146: completed | J146: LS | M146: Jayson Martinez
A147: =1+A146 -> 146 | B147: F0 | C147: FR6837097 | D147: L000008293 | E147: SLS Commercial APeC -G | G147: Rename | H147: =IFERROR(VLOOKUP(Table2[[#This Row], [Ticket]],Okey!A:B,2,0),"") -> ok | I147: completed | J147: LS | M147: Jayson Martinez
A148: =1+A147 -> 147 | B148: F0 | C148: FR6837097 | D148: L000011139 | E148: Analytics CoE | G148: Rename | H148: =IFERROR(VLOOKUP(Table2[[#This Row], [Ticket]],Okey!A:B,2,0),"") -> ok | I148: completed | J148: LS | M148: Jayson Martinez
A149: =1+A148 -> 148 | B149: F0 | C149: FR6837097 | D149: L000011322 | E149: Life Science Business Development | G149: Rename | H149: =IFERROR(VLOOKUP(Table2[[#This Row], [Ticket]],Okey!A:B,2,0),"") -> ok | I149: completed | J149: LS | M149: Jayson Martinez
A150: =1+A149 -> 149 | B150: F0 | C150: FR6837097 | D150: L000011344 | E150: Strategy & Market Intelligence | G150: Rename | H150: =IFERROR(VLOOKUP(Table2[[#This Row], [Ticket]],Okey!A:B,2,0),"") -> ok | I150: completed | J150: LS | M150: Jayson Martinez
A151: =1+A150 -> 150 | B151: F0 | C151: FR6837097 | D151: L000011353 | E151: Program Management and Change | G151: Rename | H151: =IFERROR(VLOOKUP(Table2[[#This Row], [Ticket]],Okey!A:B,2,0),"") -> ok | I151: completed | J151: LS | M151: Jayson Martinez
A152: =1+A151 -> 151 | B152: F0 | C152: FR6837097 | D152: L000012995 | E152: Sustainability & Social Business Innovat | G152: Rename | H152: =IFERROR(VLOOKUP(Table2[[#This Row], [Ticket]],Okey!A:B,2,0),"") -> ok | I152: completed | J152: LS | M152: Jayson Martinez
A153: =1+A152 -> 152 | B153: F0 | C153: FR6837097 | D153: L000005915 | E153: DxRM - Immunoassay Materials | F153: L000005842 | G153: Rename/Move | H153: =IFERROR(VLOOKUP(Table2[[#This Row], [Ticket]],Okey!A:B,2,0),"") -> ok | I153: completed | J153: LS | M153: Jayson Martinez
A154: =1+A153 -> 153 | B154: F0 | C154: FR6837097 | D154: L000006082 | E154: LW MEA | F154: L000013197 | G154: Rename/Move | H154: =IFERROR(VLOOKUP(Table2[[#This Row], [Ticket]],Okey!A:B,2,0),"") -> ok | I154: completed | J154: LS | M154: Jayson Martinez
A155: =1+A154 -> 154 | B155: F0 | C155: FR6837097 | D155: L000013711 | F155: L000013710 | G155: Move | H155: =IFERROR(VLOOKUP(Table2[[#This Row], [Ticket]],Okey!A:B,2,0),"") -> ok | I155: completed | J155: LS | M155: Jayson Martinez
A156: =1+A155 -> 155 | B156: F0 | C156: FR6837097 | D156: L000013712 | F156: L000013710 | G156: Move | H156: =IFERROR(VLOOKUP(Table2[[#This Row], [Ticket]],Okey!A:B,2,0),"") -> ok | I156: completed | J156: LS | M156: Jayson Martinez
A157: =1+A156 -> 156 | B157: F0 | C157: FR6837097 | D157: L000013713 | F157: L000013710 | G157: Move | H157: =IFERROR(VLOOKUP(Table2[[#This Row], [Ticket]],Okey!A:B,2,0),"") -> ok | I157: completed | J157: LS | M157: Jayson Martinez
A158: =1+A157 -> 157 | B158: F0 | C158: FR6837097 | D158: L000013714 | F158: L000013710 | G158: Move | H158: =IFERROR(VLOOKUP(Table2[[#This Row], [Ticket]],Okey!A:B,2,0),"") -> ok | I158: completed | J158: LS | M158: Jayson Martinez
A159: =1+A158 -> 158 | B159: F0 | C159: FR6837097 | D159: L000013715 | F159: L000013710 | G159: Move | H159: =IFERROR(VLOOKUP(Table2[[#This Row], [Ticket]],Okey!A:B,2,0),"") -> ok | I159: completed | J159: LS | M159: Jayson Martinez
A160: =1+A159 -> 159 | B160: F0 | C160: FR6837097 | D160: L000013716 | F160: L000013710 | G160: Move | H160: =IFERROR(VLOOKUP(Table2[[#This Row], [Ticket]],Okey!A:B,2,0),"") -> ok | I160: completed | J160: LS | M160: Jayson Martinez
A161: =1+A160 -> 160 | B161: F0 | C161: FR6837097 | D161: L000013717 | F161: L000013710 | G161: Move | H161: =IFERROR(VLOOKUP(Table2[[#This Row], [Ticket]],Okey!A:B,2,0),"") -> ok | I161: completed | J161: LS | M161: Jayson Martinez
A162: =1+A161 -> 161 | B162: F0 | C162: FR6837097 | D162: L000013719 | F162: L000013710 | G162: Move | H162: =IFERROR(VLOOKUP(Table2[[#This Row], [Ticket]],Okey!A:B,2,0),"") -> ok | I162: completed | J162: LS | M162: Jayson Martinez
A163: =1+A162 -> 162 | B163: F0 | C163: FR6837097 | D163: L000013720 | F163: L000013710 | G163: Move | H163: =IFERROR(VLOOKUP(Table2[[#This Row], [Ticket]],Okey!A:B,2,0),"") -> ok | I163: completed | J163: LS | M163: Jayson Martinez
A164: =1+A163 -> 163 | B164: F0 | C164: FR6837097 | D164: L000013721 | F164: L000013710 | G164: Move | H164: =IFERROR(VLOOKUP(Table2[[#This Row], [Ticket]],Okey!A:B,2,0),"") -> ok | I164: completed | J164: LS | M164: Jayson Martinez
A165: =1+A164 -> 164 | B165: F0 | C165: FR6837097 | D165: L000013722 | F165: L000013710 | G165: Move | H165: =IFERROR(VLOOKUP(Table2[[#This Row], [Ticket]],Okey!A:B,2,0),"") -> ok | I165: completed | J165: LS | M165: Jayson Martinez
...

Sheet old
A1: No. | B1: Forecast? | C1: Ticket | D1: Node | E1: Name | F1: Parent | G1: Action | H1: STATUS | I1: STATUS Check | J1: Sector | K1: Comments | L1: SANITY | M1: Author
A2: 1 | B2: F1 | C2: FR6934915 | D2: G000000994 | F2: G000000529 | G2: Move | H2: =IFERROR(VLOOKUP(Table2[[#This Row], [Ticket]],Okey!A:B,2,0),"") -> ok | I2: completed | J2: MGF | M2: Francesco Ricioppo
A3: =1+A2 -> 2 | B3: F1 | C3: FR6934915 | D3: G000000995 | F3: G000000529 | G3: Move | H3: =IFERROR(VLOOKUP(Table2[[#This Row], [Ticket]],Okey!A:B,2,0),"") -> ok | I3: completed | J3: MGF | M3: Francesco Ricioppo
A4: =1+A3 -> 3 | B4: F1 | C4: FR6934915 | D4: G000000993 | F4: G000000873 | G4: Move | H4: =IFERROR(VLOOKUP(Table2[[#This Row], [Ticket]],Okey!A:B,2,0),"") -> ok | I4: completed | J4: MGF | M4: Francesco Ricioppo
A5: =1+A4 -> 4 | B5: F1 | C5: FR6952137 | D5: G000001357 | E5: MBS S&T Learning & Develop., Knwldg Mgt | F5: G000001146 | G5: New | H5: =IFERROR(VLOOKUP(Table2[[#This Row], [Ticket]],Okey!A:B,2,0),"") -> ok | I5: completed | J5: MGF | M5: Yvonne Doernhofer
A6: =1+A5 -> 5 | B6: F1 | C6: FR6952137 | D6: G000001191 | E6: MBS S&T - Business Process Management | G6: Rename | H6: =IFERROR(VLOOKUP(Table2[[#This Row], [Ticket]],Okey!A:B,2,0),"") -> ok | I6: completed | J6: MGF | M6: Yvonne Doernhofer
A7: =1+A6 -> 6 | B7: F1 | C7: FR6995596 | D7: G000000511 | F7: G000000873 | G7: Move | H7: =IFERROR(VLOOKUP(Table2[[#This Row], [Ticket]],Okey!A:B,2,0),"") -> ok | I7: completed | J7: MGF | M7: Francesco Ricioppo
A8: =1+A7 -> 7 | B8: F1 | C8: FR6995596 | D8: G000000512 | F8: G000000873 | G8: Move | H8: =IFERROR(VLOOKUP(Table2[[#This Row], [Ticket]],Okey!A:B,2,0),"") -> ok | I8: completed | J8: MGF | M8: Francesco Ricioppo
A9: =1+A8 -> 8 | B9: F1 | C9: FR6995596 | D9: G000000513 | F9: G000000873 | G9: Move | H9: =IFERROR(VLOOKUP(Table2[[#This Row], [Ticket]],Okey!A:B,2,0),"") -> ok | I9: completed | J9: MGF | M9: Francesco Ricioppo
A10: =1+A9 -> 9 | B10: F1 | C10: FR6995596 | D10: G000000514 | F10: G000000873 | G10: Move | H10: =IFERROR(VLOOKUP(Table2[[#This Row], [Ticket]],Okey!A:B,2,0),"") -> ok | I10: completed | J10: MGF | M10: Francesco Ricioppo
A11: =1+A10 -> 10 | B11: F1 | C11: FR6995596 | D11: G000001007 | F11: G000000873 | G11: Move | H11: =IFERROR(VLOOKUP(Table2[[#This Row], [Ticket]],Okey!A:B,2,0),"") -> ok | I11: completed | J11: MGF | M11: Francesco Ricioppo
A12: =1+A11 -> 11 | B12: F1 | C12: FR6995596 | D12: G000001065 | F12: G000000873 | G12: Move | H12: =IFERROR(VLOOKUP(Table2[[#This Row], [Ticket]],Okey!A:B,2,0),"") -> ok | I12: completed | J12: MGF | M12: Francesco Ricioppo
A13: =1+A12 -> 12 | B13: F1 | C13: FR6995596 | D13: G000001066 | F13: G000000873 | G13: Move | H13: =IFERROR(VLOOKUP(Table2[[#This Row], [Ticket]],Okey!A:B,2,0),"") -> ok | I13: completed | J13: MGF | M13: Francesco Ricioppo
A14: =1+A13 -> 13 | B14: F1 | C14: FR7010885 | D14: G000000392 | E14: SM-PT | G14: Rename | H14: =IFERROR(VLOOKUP(Table2[[#This Row], [Ticket]],Okey!A:B,2,0),"") -> ok | I14: completed | J14: MGF | M14: Marcus Morowski
A15: =1+A14 -> 14 | B15: F1 | C15: FR7010885 | D15: G000000389 | E15: SM-PM und PT | G15: Rename | H15: =IFERROR(VLOOKUP(Table2[[#This Row], [Ticket]],Okey!A:B,2,0),"") -> ok | I15: completed | J15: MGF | M15: Marcus Morowski
A16: =1+A15 -> 15 | B16: F1 | C16: FR7010885 | D16: G000000918 | E16: SM-PTT Material Management | G16: Rename | H16: =IFERROR(VLOOKUP(Table2[[#This Row], [Ticket]],Okey!A:B,2,0),"") -> ok | I16: completed | J16: MGF | M16: Marcus Morowski
A17: =1+A16 -> 16 | B17: F1 | C17: FR7010885 | D17: G000000919 | E17: SM-PTT Technical Warehouse | G17: Rename | H17: =IFERROR(VLOOKUP(Table2[[#This Row], [Ticket]],Okey!A:B,2,0),"") -> ok | I17: completed | J17: MGF | M17: Marcus Morowski
A18: =1+A17 -> 17 | B18: F1 | C18: FR7010885 | D18: G000000919 | E18: SM-PTT IVV Allocation CCs | G18: Rename | H18: =IFERROR(VLOOKUP(Table2[[#This Row], [Ticket]],Okey!A:B,2,0),"") -> ok | I18: completed | J18: MGF | K18: WTF, duplicated | M18: Marcus Morowski
A19: =1+A18 -> 18 | B19: F1 | C19: FR7010885 | D19: G000000387 | E19: SM-PM | F19: G000000389 | G19: Rename/Move | H19: =IFERROR(VLOOKUP(Table2[[#This Row], [Ticket]],Okey!A:B,2,0),"") -> ok | I19: completed | J19: MGF | M19: Marcus Morowski
A20: =1+A19 -> 19 | B20: F1 | C20: FR7010885 | D20: G000000391 | E20: SM-PMA | F20: G000000387 | G20: Rename/Move | H20: =IFERROR(VLOOKUP(Table2[[#This Row], [Ticket]],Okey!A:B,2,0),"") -> ok | I20: completed | J20: MGF | M20: Marcus Morowski
A21: =1+A20 -> 20 | B21: F1 | C21: FR7015139 | D21: P000000196 | E21: PG1 Blending+Packaging | G21: Rename | H21: =IFERROR(VLOOKUP(Table2[[#This Row], [Ticket]],Okey!A:B,2,0),"") -> ok | I21: completed | J21: EL | M21: Gerhard Doeller
A22: =1+A21 -> 21 | B22: F1 | C22: FR7015139 | D22: P000000197 | E22: PG2 Coating | G22: Rename | H22: =IFERROR(VLOOKUP(Table2[[#This Row], [Ticket]],Okey!A:B,2,0),"") -> ok | I22: completed | J22: EL | M22: Gerhard Doeller
A23: =1+A22 -> 22 | B23: F1 | C23: FR7015139 | D23: P000000198 | E23: PG1 Substrates | G23: Rename | H23: =IFERROR(VLOOKUP(Table2[[#This Row], [Ticket]],Okey!A:B,2,0),"") -> ok | I23: completed | J23: EL | M23: Gerhard Doeller
A24: =1+A23 -> 23 | B24: F1 | C24: FR7037412 | D24: L000013817 | E24: Business Integration _GPO | F24: L000013445 | G24: New | H24: =IFERROR(VLOOKUP(Table2[[#This Row], [Ticket]],Okey!A:B,2,0),"") -> ok | I24: completed | J24: LS | M24: Jayson Martinez
A25: =1+A24 -> 24 | B25: F1 | C25: FR7037412 | D25: L000013818 | E25: Business Integration _PS VS | F25: L000013417 | G25: New | H25: =IFERROR(VLOOKUP(Table2[[#This Row], [Ticket]],Okey!A:B,2,0),"") -> ok | I25: completed | J25: LS | M25: Jayson Martinez
A26: =1+A25 -> 25 | B26: F1 | C26: FR7037412 | D26: L000013819 | E26: mRNA and LNP Innovation | F26: L000006420 | G26: New | H26: =IFERROR(VLOOKUP(Table2[[#This Row], [Ticket]],Okey!A:B,2,0),"") -> ok | I26: completed | J26: LS | M26: Jayson Martinez
A27: =1+A26 -> 26 | B27: F1 | C27: FR7037412 | D27: L000013820 | E27: Bioconujation and SM Innovation | F27: L000006420 | G27: New | H27: =IFERROR(VLOOKUP(Table2[[#This Row], [Ticket]],Okey!A:B,2,0),"") -> ok | I27: completed | J27: LS | M27: Jayson Martinez
A28: =1+A27 -> 27 | B28: F1 | C28: FR7037412 | D28: L000013821 | E28: Viral Vectors Innovation | F28: L000013174 | G28: New | H28: =IFERROR(VLOOKUP(Table2[[#This Row], [Ticket]],Okey!A:B,2,0),"") -> ok | I28: completed | J28: LS | M28: Jayson Martinez
A29: =1+A28 -> 28 | B29: F1 | C29: FR7037412 | D29: L000013822 | E29: Biologics Innovation | F29: L000013174 | G29: New | H29: =IFERROR(VLOOKUP(Table2[[#This Row], [Ticket]],Okey!A:B,2,0),"") -> ok | I29: completed | J29: LS | M29: Jayson Martinez
A30: =1+A29 -> 29 | B30: F1 | C30: FR7037412 | D30: L000013823 | E30: PMO CDMO Innovation | F30: L000013785 | G30: New | H30: =IFERROR(VLOOKUP(Table2[[#This Row], [Ticket]],Okey!A:B,2,0),"") -> ok | I30: completed | J30: LS | M30: Jayson Martinez
A31: =1+A30 -> 30 | B31: F1 | C31: FR7037412 | D31: L000005722 | E31: BM - Comm NA - South Pharma | G31: Rename | H31: =IFERROR(VLOOKUP(Table2[[#This Row], [Ticket]],Okey!A:B,2,0),"") -> ok | I31: completed | J31: LS | M31: Jayson Martinez
A32: =1+A31 -> 31 | B32: F1 | C32: FR7037412 | D32: L000013350 | E32: CDMO - APAC Sales | G32: Rename | H32: =IFERROR(VLOOKUP(Table2[[#This Row], [Ticket]],Okey!A:B,2,0),"") -> ok | I32: completed | J32: LS | M32: Jayson Martinez
A33: =1+A32 -> 32 | B33: F1 | C33: FR7037412 | D33: L000006425 | E33: Synthesis mRNA delivery & PEG's | F33: L000013819 | G33: Rename/Move | H33: =IFERROR(VLOOKUP(Table2[[#This Row], [Ticket]],Okey!A:B,2,0),"") -> ok | I33: completed | J33: LS | M33: Jayson Martinez
A34: =1+A33 -> 33 | B34: F1 | C34: FR7037412 | D34: L000006429 | E34: mRNA Delivery / Manufacturing | F34: L000013819 | G34: Rename/Move | H34: =IFERROR(VLOOKUP(Table2[[#This Row], [Ticket]],Okey!A:B,2,0),"") -> ok | I34: completed | J34: LS | M34: Jayson Martinez
A35: =1+A34 -> 34 | B35: F1 | C35: FR7037412 | D35: L000006431 | E35: ADC Payload Automation & Digital | F35: L000013820 | G35: Rename/Move | H35: =IFERROR(VLOOKUP(Table2[[#This Row], [Ticket]],Okey!A:B,2,0),"") -> ok | I35: completed | J35: LS | M35: Jayson Martinez
A36: =1+A35 -> 35 | B36: F1 | C36: FR7037412 | D36: L000011451 | E36: ADC Bionconjugation Template | F36: L000013820 | G36: Rename/Move | H36: =IFERROR(VLOOKUP(Table2[[#This Row], [Ticket]],Okey!A:B,2,0),"") -> ok | I36: completed | J36: LS | M36: Jayson Martinez
A37: =1+A36 -> 36 | B37: F1 | C37: FR7037412 | D37: L000007087 | E37: VV Innovation | F37: L000013821 | G37: Rename/Move | H37: =IFERROR(VLOOKUP(Table2[[#This Row], [Ticket]],Okey!A:B,2,0),"") -> ok | I37: completed | J37: LS | M37: Jayson Martinez
A38: =1+A37 -> 37 | B38: F1 | C38: FR7037412 | D38: L000006414 | E38: Synthesis & ADC CDMO Management | F38: L000013789 | G38: Rename/Move | H38: =IFERROR(VLOOKUP(Table2[[#This Row], [Ticket]],Okey!A:B,2,0),"") -> ok | I38: completed | J38: LS | M38: Jayson Martinez
A39: =1+A38 -> 38 | B39: F1 | C39: FR7037412 | D39: L000013151 | E39: CDMO Operations | F39: L000009201 | G39: Rename/Move | H39: =IFERROR(VLOOKUP(Table2[[#This Row], [Ticket]],Okey!A:B,2,0),"") -> ok | I39: completed | J39: LS | M39: Jayson Martinez
A40: =1+A39 -> 39 | B40: F1 | C40: FR7037412 | D40: L000013152 | E40: SAC BP & Implementation | F40: L000013789 | G40: Rename/Move | H40: =IFERROR(VLOOKUP(Table2[[#This Row], [Ticket]],Okey!A:B,2,0),"") -> ok | I40: completed | J40: LS | M40: Jayson Martinez
A41: =1+A40 -> 40 | B41: F1 | C41: FR7037412 | D41: L000006947 | E41: BioVV - Management | F41: L000013789 | G41: Rename/Move | H41: =IFERROR(VLOOKUP(Table2[[#This Row], [Ticket]],Okey!A:B,2,0),"") -> ok | I41: completed | J41: LS | M41: Jayson Martinez
A42: =1+A41 -> 41 | B42: F1 | C42: FR7037412 | D42: L000006952 | E42: BioVV - Strategy | F42: L000012321 | G42: Rename/Move | H42: =IFERROR(VLOOKUP(Table2[[#This Row], [Ticket]],Okey!A:B,2,0),"") -> ok | I42: completed | J42: LS | M42: Jayson Martinez
A43: =1+A42 -> 42 | B43: F1 | C43: FR7037412 | D43: L000009432 | E43: CDMO - Carlsbad | F43: L000013151 | G43: Rename/Move | H43: =IFERROR(VLOOKUP(Table2[[#This Row], [Ticket]],Okey!A:B,2,0),"") -> ok | I43: completed | J43: LS | M43: Jayson Martinez
A44: =1+A43 -> 43 | B44: F1 | C44: FR7037412 | D44: L000011494 | E44: CDMO - Martillac | F44: L000013151 | G44: Rename/Move | H44: =IFERROR(VLOOKUP(Table2[[#This Row], [Ticket]],Okey!A:B,2,0),"") -> ok | I44: completed | J44: LS | M44: Jayson Martinez
... A47: =1+A46 -> 46 | B47: F1 | C47: FR7037412 | D47: L000013398 | E47: CDMO - Shanghai | F47: L000013151 | G47: Rename/Move | H47: =IFERROR(VLOOKUP(Table2[[#This Row], [Ticket]],Okey!A:B,2,0),"") -> ok | I47: completed | J47: LS | M47: Jayson Martinez
A48: =1+A47 -> 47 | B48: F1 | C48: FR7037412 | D48: L000013527 | F48: L000013817 | G48: Move | H48: =IFERROR(VLOOKUP(Table2[[#This Row], [Ticket]],Okey!A:B,2,0),"") -> ok | I48: completed | J48: LS | M48: Jayson Martinez
A49: =1+A48 -> 48 | B49: F1 | C49: FR7037412 | D49: L000006951 | F49: L000013779 | G49: Move | H49: =IFERROR(VLOOKUP(Table2[[#This Row], [Ticket]],Okey!A:B,2,0),"") -> ok | I49: completed | J49: LS | M49: Jayson Martinez
A50: =1+A49 -> 49 | B50: F1 | C50: FR7037412 | D50: L000007094 | F50: L000013821 | G50: Move | H50: =IFERROR(VLOOKUP(Table2[[#This Row], [Ticket]],Okey!A:B,2,0),"") -> ok | I50: completed | J50: LS | M50: Jayson Martinez
A51: =1+A50 -> 50 | B51: F1 | C51: FR7037412 | D51: L000013272 | F51: L000013821 | G51: Move | H51: =IFERROR(VLOOKUP(Table2[[#This Row], [Ticket]],Okey!A:B,2,0),"") -> ok | I51: completed | J51: LS | M51: Jayson Martinez
A52: =1+A51 -> 51 | B52: F1 | C52: FR7037412 | D52: L000013808 | F52: L000013775 | G52: Move | H52: =IFERROR(VLOOKUP(Table2[[#This Row], [Ticket]],Okey!A:B,2,0),"") -> ok | I52: completed | J52: LS | M52: Jayson Martinez
A53: =1+A52 -> 52 | B53: F1 | C53: FR7037412 | D53: L000005433 | F53: L000005326 | G53: Move | H53: =IFERROR(VLOOKUP(Table2[[#This Row], [Ticket]],Okey!A:B,2,0),"") -> ok | I53: completed | J53: LS | M53: Jayson Martinez
A54: =1+A53 -> 53 | B54: F1 | C54: FR7037412 | D54: L000005673 | F54: L000005668 | G54: Move | H54: =IFERROR(VLOOKUP(Table2[[#This Row], [Ticket]],Okey!A:B,2,0),"") -> ok | I54: completed | J54: LS | M54: Jayson Martinez
A55: =1+A54 -> 54 | B55: F1 | C55: FR7037412 | D55: L000006391 | F55: L000013786 | G55: Move | H55: =IFERROR(VLOOKUP(Table2[[#This Row], [Ticket]],Okey!A:B,2,0),"") -> ok | I55: completed | J55: LS | M55: Jayson Martinez
A56: =1+A55 -> 55 | B56: F1 | C56: FR7037412 | D56: L000006420 | F56: L000013785 | G56: Move | H56: =IFERROR(VLOOKUP(Table2[[#This Row], [Ticket]],Okey!A:B,2,0),"") -> ok | I56: completed | J56: LS | M56: Jayson Martinez
A57: =1+A56 -> 56 | B57: F1 | C57: FR7037412 | D57: L000006448 | F57: L000012321 | G57: Move | H57: =IFERROR(VLOOKUP(Table2[[#This Row], [Ticket]],Okey!A:B,2,0),"") -> ok | I57: completed | J57: LS | M57: Jayson Martinez
A58: =1+A57 -> 57 | B58: F1 | C58: FR7037412 | D58: L000006496 | F58: L000013784 | G58: Move | H58: =IFERROR(VLOOKUP(Table2[[#This Row], [Ticket]],Okey!A:B,2,0),"") -> ok | I58: completed | J58: LS | M58: Jayson Martinez
A59: =1+A58 -> 58 | B59: F1 | C59: FR7037412 | D59: L000011470 | F59: L000013783 | G59: Move | H59: =IFERROR(VLOOKUP(Table2[[#This Row], [Ticket]],Okey!A:B,2,0),"") -> ok | I59: completed | J59: LS | M59: Jayson Martinez
... A65: =1+A64 -> 64 | B65: F1 | C65: FR7037412 | D65: L000006295 | F65: L000013685 | G65: Move | H65: =IFERROR(VLOOKUP(Table2[[#This Row], [Ticket]],Okey!A:B,2,0),"") -> ok | I65: completed | J65: LS | M65: Jayson Martinez
A66: =1+A65 -> 65 | B66: F1 | C66: FR7040358 | D66: G000001358 | E66: GMV MBS Hub Wroclaw - ABP | F66: G000001143 | G66: New | H66: =IFERROR(VLOOKUP(Table2[[#This Row], [Ticket]],Okey!A:B,2,0),"") -> ok | I66: completed | J66: MGF | M66: Jojeff Tagnong
A67: =1+A66 -> 66 | B67: F1 | C67: FR7040888 | D67: P000001254 | E67: EL-OP-M Metrology & Inspection | F67: P000000001 | G67: New | H67: =IFERROR(VLOOKUP(Table2[[#This Row], [Ticket]],Okey!A:B,2,0),"") -> ok | I67: completed | J67: EL | M67: Eivy Denine Cruz
A68: =1+A67 -> 67 | B68: F1 | C68: FR7040888 | D68: P000001255 | E68: EL-OP-M M&I Sales | F68: P000001254 | G68: New | H68: =IFERROR(VLOOKUP(Table2[[#This Row], [Ticket]],Okey!A:B,2,0),"") -> ok | I68: completed | J68: EL | M68: Eivy Denine Cruz
A69: =1+A68 -> 68 | B69: F1 | C69: FR7040888 | D69: P000001256 | E69: EL-OP-M M&I Marketing | F69: P000001254 | G69: New | H69: =IFERROR(VLOOKUP(Table2[[#This Row], [Ticket]],Okey!A:B,2,0),"") -> ok | I69: completed | J69: EL | M69: Eivy Denine Cruz
A70: =1+A69 -> 69 | B70: F1 | C70: FR7040888 | D70: P000001257 | E70: EL-OP-M M&I Operations | F70: P000001254 | G70: New | H70: =IFERROR(VLOOKUP(Table2[[#This Row], [Ticket]],Okey!A:B,2,0),"") -> ok | I70: completed | J70: EL | M70: Eivy Denine Cruz
A71: =1+A70 -> 70 | B71: F1 | C71: FR7040888 | D71: P000001258 | E71: EL-OP-M M&I R&D | F71: P000001254 | G71: New | H71: =IFERROR(VLOOKUP(Table2[[#This Row], [Ticket]],Okey!A:B,2,0),"") -> ok | I71: completed | J71: EL | M71: Eivy Denine Cruz
A72: =1+A71 -> 71 | B72: F1 | C72: FR7040888 | D72: P000001194 | F72: P000000635 | G72: Move | H72: =IFERROR(VLOOKUP(Table2[[#This Row], [Ticket]],Okey!A:B,2,0),"") -> ok | I72: completed | J72: EL | M72: Eivy Denine Cruz
A73: =1+A72 -> 72 | B73: F1 | C73: FR7040888 | D73: P000000391 | F73: O000000009 | G73: Delete | H73: =IFERROR(VLOOKUP(Table2[[#This Row], [Ticket]],Okey!A:B,2,0),"") -> ok | I73: completed | J73: EL | M73: Eivy Denine Cruz
A74: =1+A73 -> 73 | B74: F1 | C74: FR7040888 | D74: P000000773 | F74: O000000009 | G74: Delete | H74: =IFERROR(VLOOKUP(Table2[[#This Row], [Ticket]],Okey!A:B,2,0),"") -> ok | I74: completed | J74: EL | M74: Eivy Denine Cruz
A75: =1+A74 -> 74 | B75: F1 | C75: FR7040888 | D75: P000000543 | F75: O000000009 | G75: Delete | H75: =IFERROR(VLOOKUP(Table2[[#This Row], [Ticket]],Okey!A:B,2,0),"") -> ok | I75: completed | J75: EL | M75: Eivy Denine Cruz
A76: =1+A75 -> 75 | B76: F1 | C76: FR7040888 | D76: P000000549 | F76: O000000009 | G76: Delete | H76: =IFERROR(VLOOKUP(Table2[[#This Row], [Ticket]],Okey!A:B,2,0),"") -> ok | I76: completed | J76: EL | M76: Eivy Denine Cruz
A77: =1+A76 -> 76 | B77: F1 | C77: FR7040888 | D77: P000000798 | F77: O000000009 | G77: Delete | H77: =IFERROR(VLOOKUP(Table2[[#This Row], [Ticket]],Okey!A:B,2,0),"") -> ok | I77: completed | J77: EL | M77: Eivy Denine Cruz
A78: =1+A77 -> 77 | B78: F1 | C78: FR7040888 | D78: P000000799 | F78: O000000009 | G78: Delete | H78: =IFERROR(VLOOKUP(Table2[[#This Row], [Ticket]],Okey!A:B,2,0),"") -> ok | I78: completed | J78: EL | M78: Eivy Denine Cruz
A79: =1+A78 -> 78 | B79: F1 | C79: FR7040888 | D79: P000000961 | F79: O000000009 | G79: Delete | H79: =IFERROR(VLOOKUP(Table2[[#This Row], [Ticket]],Okey!A:B,2,0),"") -> ok | I79: completed | J79: EL | M79: Eivy Denine Cruz
A80: =1+A79 -> 79 | B80: F1 | C80: FR7040888 | D80: P000001095 | F80: O000000009 | G80: Delete | H80: =IFERROR(VLOOKUP(Table2[[#This Row], [Ticket]],Okey!A:B,2,0),"") -> ok | I80: completed | J80: EL | M80: Eivy Denine Cruz
A81: =1+A80 -> 80 | B81: F1 | C81: FR7040888 | D81: P000001096 | F81: O000000009 | G81: Delete | H81: =IFERROR(VLOOKUP(Table2[[#This Row], [Ticket]],Okey!A:B,2,0),"") -> ok | I81: completed | J81: EL | M81: Eivy Denine Cruz
A82: =1+A81 -> 81 | B82: F1 | C82: FR7040888 | D82: P000001097 | F82: O000000009 | G82: Delete | H82: =IFERROR(VLOOKUP(Table2[[#This Row], [Ticket]],Okey!A:B,2,0),"") -> ok | I82: completed | J82: EL | M82: Eivy Denine Cruz
A83: =1+A82 -> 82 | B83: F1 | C83: FR7040888 | D83: P000001098 | F83: O000000009 | G83: Delete | H83: =IFERROR(VLOOKUP(Table2[[#This Row], [Ticket]],Okey!A:B,2,0),"") -> ok | I83: completed | J83: EL | M83: Eivy Denine Cruz
... A88: =1+A87 -> 87 | B88: F1 | C88: FR7040888 | D88: P000001164 | F88: O000000009 | G88: Delete | H88: =IFERROR(VLOOKUP(Table2[[#This Row], [Ticket]],Okey!A:B,2,0),"") -> ok | I88: completed | J88: EL | M88: Eivy Denine Cruz
A89: =1+A88 -> 88 | B89: F1 | C89: FR7040888 | D89: P000000001 | E89: EL-OP Optronics | G89: Rename | H89: =IFERROR(VLOOKUP(Table2[[#This Row], [Ticket]],Okey!A:B,2,0),"") -> ok | I89: completed | J89: EL | M89: Eivy Denine Cruz
A90: =1+A89 -> 89 | B90: F1 | C90: FR7040888 | D90: P000000002 | E90: EL-OP BU Head & Other | G90: Rename | H90: =IFERROR(VLOOKUP(Table2[[#This Row], [Ticket]],Okey!A:B,2,0),"") -> ok | I90: completed | J90: EL | M90: Eivy Denine Cruz
A91: =1+A90 -> 90 | B91: F1 | C91: FR7040888 | D91: P000000695 | E91: EL-OP BU head Organization | G91: Rename | H91: =IFERROR(VLOOKUP(Table2[[#This Row], [Ticket]],Okey!A:B,2,0),"") -> ok | I91: completed | J91: EL | M91: Eivy Denine Cruz
A92: =1+A91 -> 91 | B92: F1 | C92: FR7040888 | D92: P000000696 | E92: EL-OP Inventor Remuneration | G92: Rename | H92: =IFERROR(VLOOKUP(Table2[[#This Row], [Ticket]],Okey!A:B,2,0),"") -> ok | I92: completed | J92: EL | M92: Eivy Denine Cruz
A93: =1+A92 -> 92 | B93: F1 | C93: FR7040888 | D93: P000000697 | E93: EL-OP Intangible Assets | G93: Rename | H93: =IFERROR(VLOOKUP(Table2[[#This Row], [Ticket]],Okey!A:B,2,0),"") -> ok | I93: completed | J93: EL | M93: Eivy Denine Cruz
A94: =1+A93 -> 93 | B94: F1 | C94: FR7040888 | D94: P000000698 | E94: EL-OP Other | G94: Rename | H94: =IFERROR(VLOOKUP(Table2[[#This Row], [Ticket]],Okey!A:B,2,0),"") -> ok | I94: completed | J94: EL | M94: Eivy Denine Cruz
A95: =1+A94 -> 94 | B95: F1 | C95: FR7040888 | D95: P000000022 | E95: EL-OP-W LC Windows | G95: Rename | H95: =IFERROR(VLOOKUP(Table2[[#This Row], [Ticket]],Okey!A:B,2,0),"") -> ok | I95: completed | J95: EL | M95: Eivy Denine Cruz
A96: =1+A95 -> 95 | B96: F1 | C96: FR7040888 | D96: P000000055 | E96: EL-OP-S Supply Chain Optronics | G96: Rename | H96: =IFERROR(VLOOKUP(Table2[[#This Row], [Ticket]],Okey!A:B,2,0),"") -> ok | I96: completed | J96: EL | M96: Eivy Denine Cruz
A97: =1+A96 -> 96 | B97: F1 | C97: FR7040888 | D97: P000000505 | E97: Optronics Production Sites | G97: Rename | H97: =IFERROR(VLOOKUP(Table2[[#This Row], [Ticket]],Okey!A:B,2,0),"") -> ok | I97: completed | J97: EL | M97: Eivy Denine Cruz
A98: =1+A97 -> 97 | B98: F1 | C98: FR7040888 | D98: P000000056 | E98: EL-OP-SD Site Darmstadt, Germany | G98: Rename | H98: =IFERROR(VLOOKUP(Table2[[#This Row], [Ticket]],Okey!A:B,2,0),"") -> ok | I98: completed | J98: EL | M98: Eivy Denine Cruz
A99: =1+A98 -> 98 | B99: F1 | C99: FR7040888 | D99: P000001172 | E99: EL-OP-SDPP Production Planning | G99: Rename | H99: =IFERROR(VLOOKUP(Table2[[#This Row], [Ticket]],Okey!A:B,2,0),"") -> ok | I99: completed | J99: EL | M99: Eivy Denine Cruz
A100: =1+A99 -> 99 | B100: F1 | C100: FR7040888 | D100: P000000087 | E100: EL-OP-SA Site Atsugi, Japan | G100: Rename | H100: =IFERROR(VLOOKUP(Table2[[#This Row], [Ticket]],Okey!A:B,2,0),"") -> ok | I100: completed | J100: EL | M100: Eivy Denine Cruz
... A176: =1+A175 -> 175 | B176: F1 | C176: FR7040888 | D176: P000001191 | E176: EL-SC-EE Global Capital Efficiency & Pro | G176: Rename | H176: =IFERROR(VLOOKUP(Table2[[#This Row], [Ticket]],Okey!A:B,2,0),"") -> ok | I176: completed | J176: EL | M176: Eivy Denine Cruz
A177: =1+A176 -> 176 | B177: F1 | C177: FR7047478 | D177: G000000414 | F177: G000000873 | G177: Move | H177: =IFERROR(VLOOKUP(Table2[[#This Row], [Ticket]],Okey!A:B,2,0),"") -> ok | I177: completed | J177: MGF | M177: Francesco Ricioppo
A178: =1+A177 -> 177 | B178: F1 | C178: FR7047478 | D178: G000000415 | F178: G000000873 | G178: Move | H178: =IFERROR(VLOOKUP(Table2[[#This Row], [Ticket]],Okey!A:B,2,0),"") -> ok | I178: completed | J178: MGF | M178: Francesco Ricioppo
A179: =1+A178 -> 178 | B179: F1 | C179: FR7047478 | D179: G000000879 | F179: G000000873 | G179: Move | H179: =IFERROR(VLOOKUP(Table2[[#This Row], [Ticket]],Okey!A:B,2,0),"") -> ok | I179: completed | J179: MGF | M179: Francesco Ricioppo
A180: =1+A179 -> 179 | B180: F1 | C180: FR7047478 | D180: G000000417 | F180: G000000873 | G180: Move | H180: =IFERROR(VLOOKUP(Table2[[#This Row], [Ticket]],Okey!A:B,2,0),"") -> ok | I180: completed | J180: MGF | M180: Francesco Ricioppo
A181: =1+A180 -> 180 | B181: F1 | C181: FR7047478 | D181: G000000880 | F181: G000000873 | G181: Move | H181: =IFERROR(VLOOKUP(Table2[[#This Row], [Ticket]],Okey!A:B,2,0),"") -> ok | I181: completed | J181: MGF | M181: Francesco Ricioppo
A182: =1+A181 -> 181 | B182: F1 | C182: FR7047478 | D182: G000000881 | F182: G000000873 | G182: Move | H182: =IFERROR(VLOOKUP(Table2[[#This Row], [Ticket]],Okey!A:B,2,0),"") -> ok | I182: completed | J182: MGF | M182: Francesco Ricioppo
A183: =1+A182 -> 182 | B183: F1 | C183: FR7047478 | D183: G000000495 | F183: G000000523 | G183: Move | H183: =IFERROR(VLOOKUP(Table2[[#This Row], [Ticket]],Okey!A:B,2,0),"") -> ok | I183: completed | J183: MGF | M183: Francesco Ricioppo
A184: =1+A183 -> 183 | B184: F1 | C184: FR7049853 | D184: P000001259 | E184: EL-PS Support Functions | F184: P000000024 | G184: New | H184: =IFERROR(VLOOKUP(Table2[[#This Row], [Ticket]],Okey!A:B,2,0),"") -> ok | I184: completed | J184: EL | M184: Eivy Denine Cruz
A185: =1+A184 -> 184 | B185: F1 | C185: FR7049853 | D185: P000001260 | E185: EL-PSL Legal | F185: P000001259 | G185: New | H185: =IFERROR(VLOOKUP(Table2[[#This Row], [Ticket]],Okey!A:B,2,0),"") -> ok | I185: completed | J185: EL | M185: Eivy Denine Cruz
A186: =1+A185 -> 185 | B186: F1 | C186: FR7049853 | D186: P000001261 | E186: EL-PSH HR | F186: P000001259 | G186: New | H186: =IFERROR(VLOOKUP(Table2[[#This Row], [Ticket]],Okey!A:B,2,0),"") -> ok | I186: completed | J186: EL | M186: Eivy Denine Cruz
...

Sheet Sectors
A1: P | B1: Electronics
A2: L | B2: Life Science
A3: H | B3: Healthcare
A4: G | B4: MGF
A5: O | B5: No known

Sheet KPI
A2: STATUS | B2: (All)
A4: Count of No. | B4: Column Labels
B5: F0 | G5: F0 Total | H5: F1 | M5: F1 Total | N5: F2 | O5: F2 Total | P5: Grand Total
A6: Row Labels | B6: Delete | C6: Move | D6: New | E6: Rename | F6: Rename/Move | H6: Delete | I6: Move | J6: New | K6: Rename | L6: Rename/Move | N6: Move
A7: MGF | B7: 3 | C7: 40 | D7: 79 | E7: 10 | F7: 2 | G7: 134 | I7: 30 | J7: 4 | K7: 6 | L7: 2 | M7: 42 | N7: 7 | O7: 7 | P7: 183
A8: LS | B8: 8 | C8: 35 | D8: 27 | E8: 10 | F8: 2 | G8: 82 | I8: 18 | J8: 7 | K8: 2 | L8: 15 | M8: 42 | P8: 124
A9: HC | B9: 4 | D9: 6 | E9: 8 | G9: 18 | P9: 18
A10: EL | B10: 1 | D10: 54 | G10: 55 | H10: 16 | I10: 1 | J10: 14 | K10: 93 | M10: 124 | P10: 179
A11: Grand Total | B11: 16 | C11: 75 | D11: 166 | E11: 28 | F11: 4 | G11: 289 | H11: 16 | I11: 49 | J11: 25 | K11: 101 | L11: 17 | M11: 208 | N11: 7 | O11: 7 | P11: 504
